Workbook

Sheet はじめに
B1: 請求・入金管理表 ― 使い方
B2: 請求書の「発行漏れ」「送付漏れ」「入金確認漏れ」「記入漏れ」を仕組みで防ぐための管理表です。金額はすべて税込。
B4: 1. 色の見方
B5: 黄色のセル | C5: 入力するセル(ここだけ入力します)
B6: 灰色のセル | C6: 自動計算(入力不要。シート保護で上書きできないようにしています)
B8: 2. シート構成
B9: チェック | C9: 要入力/未送付/期日超過/未消込などの件数。0件でない項目が「要対応」。まずここを開きます。
B10: 請求台帳 | C10: 請求書1枚=1行。請求番号は台帳が自動採番。入金期日・残高・ステータス・入力漏れを自動判定。
B11: 入金明細 | C11: 通帳/ネットバンキングの入金を【全件】転記し、消込先の請求番号を入れます。
B12: 取引先別残高 | C12: 取引先ごとの未回収残高(超過日数別)、毎月請求先の請求漏れ候補。
B13: 月別集計 | C13: 取引先×月の請求額・入金額(収支一覧表の収入欄と同じ形)。収支一覧表への転記・報告用。
B14: 取引先マスタ | C14: 取引先コード・支払条件(サイト/支払日)・毎月請求の有無を登録。
B15: 月次チェック記録 | C15: 月次締めのチェック結果と承認を記録(誰がいつ確認したかを残す)。
B16: 設定 | C16: 請求番号の接頭辞、基準日、期日間近の日数、月別集計の期首、プルダウンの選択肢。
B18: 3. 基本の流れ
B19: ① 請求書を作る前 | C19: 請求台帳に1行追加(請求日・取引先・件名・請求額・送付方法)→ 採番された請求番号を請求書に記載。
B20: ② 請求書を送ったら | C20: 送付日・送付者を入力。未入力の間はステータスが「未送付」のまま残ります。
B21: ③ 入金があったら | C21: 入金明細に入金日・名義・金額を転記し、消込先の請求番号を入力。台帳の入金額・残高が自動更新。
B22: ④ 消込を確認したら | C22: 残高が0になった請求を別の人が確認し「消込確認者」に記名(未記名だと「要入力」)。
B23: ⑤ 毎週 | C23: チェックシートで「期日超過」「期日間近」を確認し、担当者から督促・状況確認。
B24: ⑥ 毎月(締め後) | C24: チェックシートの全項目が「OK」になることを確認し、月次チェック記録に実施者・承認者を記入。
B26: 4. ステータスの意味(請求台帳)
B27: 要入力 | C27: 必須項目の漏れ、取引先コード誤り、支払条件未登録、未来の送付日、送付者・消込確認者の未記入。「入力漏れ」列に内容を表示。
B28: 未送付 | C28: 台帳登録済みだが送付日が空欄。請求書の出し忘れ・送り忘れの可能性。
B29: 入金待ち / 期日間近 | C29: 送付済みで期日前。期日まで「設定」の日数以内なら期日間近。
B30: 期日超過 | C30: 入金期日を過ぎても未回収残高がある。督促が必要。
B31: 一部入金 / 一部入金・超過 | C31: 入金額が請求額に足りない(振込手数料の差引なら「手数料・値引等」に入力)。
B32: 過入金 | C32: 請求額より多く入金されている(二重振込・消込先誤りの可能性)。
B33: 入金済 | C33: 未回収残高が0。
B34: 取消 | C34: 「取消」列で取消した請求。行は削除せず残します(番号の欠番を作らないため)。
B36: 5. 守るルール
B37: 請求書1枚=1行 | C37: 同じ取引先・同じ月でも請求書が別なら行を分ける(金額を「=A+B」で合算しない)。入金確認は請求書単位。
B38: 日付は年から入力 | C38: 「12/30」だけだと入力した日の年が補われ、年をまたぐと誤る。「2026/12/30」のように年から入力。未来日付はエラー表示。
B39: 入金は通帳の実額 | C39: 入金額は通帳の金額を入力(請求額をそのまま写さない)。1回の入金ごとに1行。
B40: 入金は全件転記 | C40: 請求に対応しない入金も含めて全件入力。「未消込」が残れば消込漏れか不明入金。
B41: 1入金で複数請求 | C41: 入金明細を請求の数だけ行に分け、金額を按分して各請求番号を入力。
B42: 振込手数料の差引 | C42: 先方負担の手数料が差し引かれた場合、請求台帳の「手数料・値引等」に差額を入力。
B43: 行を削除しない | C43: 間違えた請求は「取消」を選び、備考に理由。正しい請求は新しい行で再発行。
B44: 並べ替えをしない | C44: 請求番号は行位置から採番されるため並べ替え不可(シート保護で制限)。絞り込みはフィルタで。
B45: シート保護 | C45: パスワードなしで保護。列の追加などが必要な場合は[校閲]→[シート保護の解除]。

Sheet チェック
A1: チェック(ダッシュボード)
A2: 判定が「要対応」の項目を解消してください。月次締めでは全項目「OK」を確認して「月次チェック記録」に記入します。
B4: 対象月(月次チェック用) | C4: =DATE(YEAR(設定!$C$5),MONTH(設定!$C$5)-1,1) -> 46235 | D4: 既定は基準日の前月。確認したい月の1日を入力(例: 2026/10/1)
B5: 基準日 | C5: =設定!$C$5 -> 46294 | D5: 「設定」シートで変更
B7: チェック項目 | C7: 件数 | D7: 金額 | E7: 判定 | F7: 対応方法
B8: ■ 請求(請求台帳)
B9: 要入力(入力漏れ) | C9: =COUNTIF(請求台帳!$R$5:$R$504,"要入力") -> 1 | E9: =IF(C9=0,"OK","要対応") -> 要対応 | F9: 請求台帳を「ステータス=要入力」で絞り込み、「入力漏れ」列の項目を入力
B10: 未送付 | C10: =COUNTIF(請求台帳!$R$5:$R$504,"未送付") -> 1 | D10: =SUMIF(請求台帳!$R$5:$R$504,"未送付",請求台帳!$F$5:$F$504) -> 110000 | E10: =IF(C10=0,"OK","要対応") -> 要対応 | F10: 請求書を送付し送付日・送付者を入力。不要な請求なら「取消」
B11: 期日超過(一部入金含む) | C11: =COUNTIF(請求台帳!$R$5:$R$504,"期日超過")+COUNTIF(請求台帳!$R$5:$R$504,"一部入金・超過") -> 1 | D11: =SUMIF(請求台帳!$R$5:$R$504,"期日超過",請求台帳!$P$5:$P$504)+SUMIF(請求台帳!$R$5:$R$504,"一部入金・超過",請求台帳!$P$5:$P$504) -> 165000 | E11: =IF(C11=0,"OK","要対応") -> 要対応 | F11: 担当者から先方へ確認・督促。入金済なら入金明細の転記・消込漏れを確認
B12: 過入金 | C12: =COUNTIF(請求台帳!$R$5:$R$504,"過入金") -> 0 | D12: =SUMIF(請求台帳!$R$5:$R$504,"過入金",請求台帳!$P$5:$P$504) -> 0 | E12: =IF(C12=0,"OK","要対応") -> OK | F12: 二重振込・消込先の誤りを確認。返金または次回請求と相殺し備考に記録
B13: 期日間近(参考) | C13: =COUNTIF(請求台帳!$R$5:$R$504,"期日間近") -> 1 | D13: =SUMIF(請求台帳!$R$5:$R$504,"期日間近",請求台帳!$P$5:$P$504) -> 36300 | E13: 参考 | F13: 期日前の確認・リマインド(任意)
B14: 入金待ち(参考) | C14: =COUNTIF(請求台帳!$R$5:$R$504,"入金待ち")+COUNTIF(請求台帳!$R$5:$R$504,"一部入金") -> 1 | D14: =SUMIF(請求台帳!$R$5:$R$504,"入金待ち",請求台帳!$P$5:$P$504)+SUMIF(請求台帳!$R$5:$R$504,"一部入金",請求台帳!$P$5:$P$504) -> 38000 | E14: 参考 | F14: 対応不要
B15: ■ 入金(入金明細)
B16: 未消込の入金 | C16: =COUNTIF(入金明細!$J$5:$J$1004,"未消込") -> 1 | D16: =SUMIF(入金明細!$J$5:$J$1004,"未消込",入金明細!$E$5:$E$1004) -> 5500 | E16: =IF(C16=0,"OK","要対応") -> 要対応 | F16: 振込名義・金額から該当請求を探して請求番号を入力。不明なら先方・担当者に確認
B17: 消込先の請求番号誤り | C17: =COUNTIF(入金明細!$J$5:$J$1004,"番号誤り") -> 0 | D17: =SUMIF(入金明細!$J$5:$J$1004,"番号誤り",入金明細!$E$5:$E$1004) -> 0 | E17: =IF(C17=0,"OK","要対応") -> OK | F17: 請求番号を正しく入力し直す
B18: 取消した請求への消込 | C18: =COUNTIF(入金明細!$J$5:$J$1004,"取消請求へ消込") -> 0 | D18: =SUMIF(入金明細!$J$5:$J$1004,"取消請求へ消込",入金明細!$E$5:$E$1004) -> 0 | E18: =IF(C18=0,"OK","要対応") -> OK | F18: 再発行後の請求番号へ付け替える
B19: 入金日の誤り(未来の日付) | C19: =COUNTIF(入金明細!$J$5:$J$1004,"日付誤り") -> 0 | D19: =SUMIF(入金明細!$J$5:$J$1004,"日付誤り",入金明細!$E$5:$E$1004) -> 0 | E19: =IF(C19=0,"OK","要対応") -> OK | F19: 入金日を年から入力し直す(「12/30」だけの入力は年がずれる)
B20: 入金明細の入力漏れ | C20: =COUNTIF(入金明細!$J$5:$J$1004,"要入力") -> 0 | E20: =IF(C20=0,"OK","要対応") -> OK | F20: 入金日・入金額を入力
B21: ■ 請求漏れ(対象月)
B22: 毎月請求先で対象月の請求が未登録 | C22: =COUNTIF(取引先別残高!$J$5:$J$204,"請求漏れ候補") -> 1 | E22: =IF(C22=0,"OK","要対応") -> 要対応 | F22: 「取引先別残高」の請求漏れ候補を確認し、請求するか理由を記録
B23: マスタの取引先コード重複 | C23: =COUNTIF(取引先マスタ!$L$5:$L$204,"コード重複") -> 0 | E23: =IF(C23=0,"OK","要対応") -> OK | F23: 取引先マスタを修正
B24: ■ 月次の数字(対象月)
B25: 対象月の請求(取消除く) | C25: =COUNTIFS(請求台帳!$B$5:$B$504,">="&チェック!$C$4,請求台帳!$B$5:$B$504,"<="&EOMONTH(チェック!$C$4,0),請求台帳!$Q$5:$Q$504,"<>取消") -> 1 | D25: =SUMIFS(請求台帳!$F$5:$F$504,請求台帳!$B$5:$B$504,">="&チェック!$C$4,請求台帳!$B$5:$B$504,"<="&EOMONTH(チェック!$C$4,0),請求台帳!$Q$5:$Q$504,"<>取消") -> 88000 | F25: 工事・検査の完了一覧、作業報告と件数を突合し、請求漏れがないか確認
B26: 対象月の入金 | C26: =COUNTIFS(入金明細!$B$5:$B$1004,">="&チェック!$C$4,入金明細!$B$5:$B$1004,"<="&EOMONTH(チェック!$C$4,0)) -> 1 | D26: =SUMIFS(入金明細!$E$5:$E$1004,入金明細!$B$5:$B$1004,">="&チェック!$C$4,入金明細!$B$5:$B$1004,"<="&EOMONTH(チェック!$C$4,0)) -> 110000 | F26: 通帳の対象月の入金合計(売上入金分)と一致するか確認
B27: 未回収残高 合計(基準日時点) | C27: =COUNTIFS(請求台帳!$P$5:$P$504,">0",請求台帳!$Q$5:$Q$504,"<>取消")+COUNTIFS(請求台帳!$P$5:$P$504,"<0",請求台帳!$Q$5:$Q$504,"<>取消") -> 4 | D27: =SUMIF(請求台帳!$Q$5:$Q$504,"<>取消",請求台帳!$P$5:$P$504) -> 349300 | F27: 下の会計ソフトの売掛金残高と照合
B29: ■ 会計ソフトとの残高照合(月次)
B30: 会計ソフトの売掛金残高(基準日時点) | F30: 会計ソフト(または税理士への資料)の売掛金残高を入力(基準日と同じ日付時点)
B31: 差額(台帳 − 会計ソフト) | D31: =IF(D30="","",D27-D30) | E31: =IF(D30="","未入力",IF(D31=0,"OK","要対応")) -> 未入力 | F31: 差額があれば、台帳への登録漏れ・会計側の計上漏れ・消込漏れのいずれかを調査
B33: 総合判定 | C33: =IF(COUNTIF(E8:E31,"要対応")+COUNTIF(E8:E31,"未入力")=0,"すべてOK","要対応あり") -> 要対応あり

Sheet 請求台帳
A1: 請求台帳
A2: 請求書1枚=1行。請求書を作る前に登録し、採番された請求番号を請求書に記載。黄色=入力 / 灰色=自動。行は削除せず、誤りは「取消」を選択。
A4: 請求番号 | B4: 請求日 | C4: 取引先コード | D4: 取引先名 | E4: 件名 | F4: 請求額(税込) | G4: 入金期日(自動) | H4: 入金期日(個別) | I4: 入金期日 | J4: 送付方法 | K4: 送付日 | L4: 送付者 | M4: 入金額 | N4: 最終入金日 | O4: 手数料・値引等 | P4: 未回収残高 | Q4: 取消 | R4: ステータス | S4: 超過日数 | T4: 入力漏れ | U4: 消込確認者 | V4: 備考
A5: =IF(COUNTA(B5,C5,E5,F5)=0,"",設定!$C$4&TEXT(ROW()-4,"00000")) -> INV-00001 | B5: 46234 | C5: C001 | D5: =IF(C5="","",IFERROR(INDEX(取引先マスタ!$B$5:$B$204,MATCH(C5,取引先マスタ!$A$5:$A$204,0)),"コード誤り")) -> 株式会社サンプル商事 | E5: 2026年7月分 保守料 | F5: 110000 | G5: =IF(OR(B5="",C5="",D5="コード誤り"),"",IFERROR(IF(OR(INDEX(取引先マスタ!$E$5:$E$204,MATCH(C5,取引先マスタ!$A$5:$A$204,0))="",INDEX(取引先マスタ!$F$5:$F$204,MATCH(C5,取引先マスタ!$A$5:$A$204,0))=""),"",DATE(YEAR(B5),MONTH(B5)+INDEX(取引先マスタ!$E$5:$E$204,MATCH(C5,取引先マスタ!$A$5:$A$204,0)),MIN(INDEX(取引先マスタ!$F$5:$F$204,MATCH(C5,取引先マスタ!$A$5:$A$204,0)),DAY(EOMONTH(B5,INDEX(取引先マスタ!$E$5:$E$204,MATCH(C5,取引先マスタ!$A$5:$A$204,0))))))),"")) -> 46265 | I5: =IF(H5<>"",H5,G5) -> 46265 | J5: メール(PDF) | K5: 46234 | L5: 鈴木 | M5: =IF(A5="","",SUMIF(入金明細!$F$5:$F$1004,A5,入金明細!$E$5:$E$1004)) -> 110000 | N5: =IF(OR(A5="",N(M5)=0),"",SUMPRODUCT(MAX((入金明細!$F$5:$F$1004=A5)*入金明細!$B$5:$B$1004))) -> 46265 | P5: =IF(OR(A5="",F5=""),"",F5-N(M5)-N(O5)) -> 0 | R5: =IF(A5="","",IF(Q5="取消","取消",IF(T5<>"","要入力",IF(K5="","未送付",IF(P5=0,"入金済",IF(P5<0,"過入金",IF(設定!$C$5>I5,IF(N(M5)>0,"一部入金・超過","期日超過"),IF(N(M5)>0,"一部入金",IF(I5-設定!$C$5<=設定!$C$6,"期日間近","入金待ち"))))))))) -> 入金済 | S5: =IF(OR(R5="期日超過",R5="一部入金・超過"),設定!$C$5-I5,"") | T5: =IF(A5="","",TRIM(IF(B5="","請求日 ","")&IF(C5="","取引先 ",IF(D5="コード誤り","取引先コード誤り ",""))&IF(E5="","件名 ","")&IF(F5="","請求額 ","")&IF(AND(F5<>"",I5=""),"入金期日(マスタの支払条件が未登録) ","")&IF(J5="","送付方法 ","")&IF(AND(K5<>"",L5=""),"送付者 ","")&IF(AND(K5<>"",N(K5)>設定!$C$5),"送付日が未来の日付 ","")&IF(AND(K5<>"",N(M5)>0,N(P5)<=0,U5=""),"消込確認者 ",""))) | U5: 田中 | V5: SAMPLE: 入金済
A6: =IF(COUNTA(B6,C6,E6,F6)=0,"",設定!$C$4&TEXT(ROW()-4,"00000")) -> INV-00002 | B6: 46234 | C6: C002 | D6: =IF(C6="","",IFERROR(INDEX(取引先マスタ!$B$5:$B$204,MATCH(C6,取引先マスタ!$A$5:$A$204,0)),"コード誤り")) -> 有限会社テスト工業 | E6: ○○部品 納品分 | F6: 275000 | G6: =IF(OR(B6="",C6="",D6="コード誤り"),"",IFERROR(IF(OR(INDEX(取引先マスタ!$E$5:$E$204,MATCH(C6,取引先マスタ!$A$5:$A$204,0))="",INDEX(取引先マスタ!$F$5:$F$204,MATCH(C6,取引先マスタ!$A$5:$A$204,0))=""),"",DATE(YEAR(B6),MONTH(B6)+INDEX(取引先マスタ!$E$5:$E$204,MATCH(C6,取引先マスタ!$A$5:$A$204,0)),MIN(INDEX(取引先マスタ!$F$5:$F$204,MATCH(C6,取引先マスタ!$A$5:$A$204,0)),DAY(EOMONTH(B6,INDEX(取引先マスタ!$E$5:$E$204,MATCH(C6,取引先マスタ!$A$5:$A$204,0))))))),"")) -> 46275 | I6: =IF(H6<>"",H6,G6) -> 46275 | J6: 郵送 | K6: 46237 | L6: 鈴木 | M6: =IF(A6="","",SUMIF(入金明細!$F$5:$F$1004,A6,入金明細!$E$5:$E$1004)) -> 274560 | N6: =IF(OR(A6="",N(M6)=0),"",SUMPRODUCT(MAX((入金明細!$F$5:$F$1004=A6)*入金明細!$B$5:$B$1004))) -> 46275 | O6: 440 | P6: =IF(OR(A6="",F6=""),"",F6-N(M6)-N(O6)) -> 0 | R6: =IF(A6="","",IF(Q6="取消","取消",IF(T6<>"","要入力",IF(K6="","未送付",IF(P6=0,"入金済",IF(P6<0,"過入金",IF(設定!$C$5>I6,IF(N(M6)>0,"一部入金・超過","期日超過"),IF(N(M6)>0,"一部入金",IF(I6-設定!$C$5<=設定!$C$6,"期日間近","入金待ち"))))))))) -> 要入力 | S6: =IF(OR(R6="期日超過",R6="一部入金・超過"),設定!$C$5-I6,"") | T6: =IF(A6="","",TRIM(IF(B6="","請求日 ","")&IF(C6="","取引先 ",IF(D6="コード誤り","取引先コード誤り ",""))&IF(E6="","件名 ","")&IF(F6="","請求額 ","")&IF(AND(F6<>"",I6=""),"入金期日(マスタの支払条件が未登録) ","")&IF(J6="","送付方法 ","")&IF(AND(K6<>"",L6=""),"送付者 ","")&IF(AND(K6<>"",N(K6)>設定!$C$5),"送付日が未来の日付 ","")&IF(AND(K6<>"",N(M6)>0,N(P6)<=0,U6=""),"消込確認者 ",""))) -> 消込確認者 | V6: SAMPLE: 手数料差引で入金(確認者未記入→要入力)
A7: =IF(COUNTA(B7,C7,E7,F7)=0,"",設定!$C$4&TEXT(ROW()-4,"00000")) -> INV-00003 | B7: 46203 | C7: C002 | D7: =IF(C7="","",IFERROR(INDEX(取引先マスタ!$B$5:$B$204,MATCH(C7,取引先マスタ!$A$5:$A$204,0)),"コード誤り")) -> 有限会社テスト工業 | E7: ○○部品 6月納品分 | F7: 165000 | G7: =IF(OR(B7="",C7="",D7="コード誤り"),"",IFERROR(IF(OR(INDEX(取引先マスタ!$E$5:$E$204,MATCH(C7,取引先マスタ!$A$5:$A$204,0))="",INDEX(取引先マスタ!$F$5:$F$204,MATCH(C7,取引先マスタ!$A$5:$A$204,0))=""),"",DATE(YEAR(B7),MONTH(B7)+INDEX(取引先マスタ!$E$5:$E$204,MATCH(C7,取引先マスタ!$A$5:$A$204,0)),MIN(INDEX(取引先マスタ!$F$5:$F$204,MATCH(C7,取引先マスタ!$A$5:$A$204,0)),DAY(EOMONTH(B7,INDEX(取引先マスタ!$E$5:$E$204,MATCH(C7,取引先マスタ!$A$5:$A$204,0))))))),"")) -> 46244 | I7: =IF(H7<>"",H7,G7) -> 46244 | J7: 郵送 | K7: 46204 | L7: 鈴木 | M7: =IF(A7="","",SUMIF(入金明細!$F$5:$F$1004,A7,入金明細!$E$5:$E$1004)) -> 0 | N7: =IF(OR(A7="",N(M7)=0),"",SUMPRODUCT(MAX((入金明細!$F$5:$F$1004=A7)*入金明細!$B$5:$B$1004))) | P7: =IF(OR(A7="",F7=""),"",F7-N(M7)-N(O7)) -> 165000 | R7: =IF(A7="","",IF(Q7="取消","取消",IF(T7<>"","要入力",IF(K7="","未送付",IF(P7=0,"入金済",IF(P7<0,"過入金",IF(設定!$C$5>I7,IF(N(M7)>0,"一部入金・超過","期日超過"),IF(N(M7)>0,"一部入金",IF(I7-設定!$C$5<=設定!$C$6,"期日間近","入金待ち"))))))))) -> 期日超過 | S7: =IF(OR(R7="期日超過",R7="一部入金・超過"),設定!$C$5-I7,"") -> 50 | T7: =IF(A7="","",TRIM(IF(B7="","請求日 ","")&IF(C7="","取引先 ",IF(D7="コード誤り","取引先コード誤り ",""))&IF(E7="","件名 ","")&IF(F7="","請求額 ","")&IF(AND(F7<>"",I7=""),"入金期日(マスタの支払条件が未登録) ","")&IF(J7="","送付方法 ","")&IF(AND(K7<>"",L7=""),"送付者 ","")&IF(AND(K7<>"",N(K7)>設定!$C$5),"送付日が未来の日付 ","")&IF(AND(K7<>"",N(M7)>0,N(P7)<=0,U7=""),"消込確認者 ",""))) | V7: SAMPLE: 期日超過
A8: =IF(COUNTA(B8,C8,E8,F8)=0,"",設定!$C$4&TEXT(ROW()-4,"00000")) -> INV-00004 | B8: 46265 | C8: C003 | D8: =IF(C8="","",IFERROR(INDEX(取引先マスタ!$B$5:$B$204,MATCH(C8,取引先マスタ!$A$5:$A$204,0)),"コード誤り")) -> 合同会社デモ | E8: 8月分 業務委託料 | F8: 88000 | G8: =IF(OR(B8="",C8="",D8="コード誤り"),"",IFERROR(IF(OR(INDEX(取引先マスタ!$E$5:$E$204,MATCH(C8,取引先マスタ!$A$5:$A$204,0))="",INDEX(取引先マスタ!$F$5:$F$204,MATCH(C8,取引先マスタ!$A$5:$A$204,0))=""),"",DATE(YEAR(B8),MONTH(B8)+INDEX(取引先マスタ!$E$5:$E$204,MATCH(C8,取引先マスタ!$A$5:$A$204,0)),MIN(INDEX(取引先マスタ!$F$5:$F$204,MATCH(C8,取引先マスタ!$A$5:$A$204,0)),DAY(EOMONTH(B8,INDEX(取引先マスタ!$E$5:$E$204,MATCH(C8,取引先マスタ!$A$5:$A$204,0))))))),"")) -> 46295 | I8: =IF(H8<>"",H8,G8) -> 46295 | J8: 請求書発行システム | K8: 46266 | L8: 鈴木 | M8: =IF(A8="","",SUMIF(入金明細!$F$5:$F$1004,A8,入金明細!$E$5:$E$1004)) -> 50000 | N8: =IF(OR(A8="",N(M8)=0),"",SUMPRODUCT(MAX((入金明細!$F$5:$F$1004=A8)*入金明細!$B$5:$B$1004))) -> 46293 | P8: =IF(OR(A8="",F8=""),"",F8-N(M8)-N(O8)) -> 38000 | R8: =IF(A8="","",IF(Q8="取消","取消",IF(T8<>"","要入力",IF(K8="","未送付",IF(P8=0,"入金済",IF(P8<0,"過入金",IF(設定!$C$5>I8,IF(N(M8)>0,"一部入金・超過","期日超過"),IF(N(M8)>0,"一部入金",IF(I8-設定!$C$5<=設定!$C$6,"期日間近","入金待ち"))))))))) -> 一部入金 | S8: =IF(OR(R8="期日超過",R8="一部入金・超過"),設定!$C$5-I8,"") | T8: =IF(A8="","",TRIM(IF(B8="","請求日 ","")&IF(C8="","取引先 ",IF(D8="コード誤り","取引先コード誤り ",""))&IF(E8="","件名 ","")&IF(F8="","請求額 ","")&IF(AND(F8<>"",I8=""),"入金期日(マスタの支払条件が未登録) ","")&IF(J8="","送付方法 ","")&IF(AND(K8<>"",L8=""),"送付者 ","")&IF(AND(K8<>"",N(K8)>設定!$C$5),"送付日が未来の日付 ","")&IF(AND(K8<>"",N(M8)>0,N(P8)<=0,U8=""),"消込確認者 ",""))) | V8: SAMPLE: 一部入金
A9: =IF(COUNTA(B9,C9,E9,F9)=0,"",設定!$C$4&TEXT(ROW()-4,"00000")) -> INV-00005 | B9: 46295 | C9: C001 | D9: =IF(C9="","",IFERROR(INDEX(取引先マスタ!$B$5:$B$204,MATCH(C9,取引先マスタ!$A$5:$A$204,0)),"コード誤り")) -> 株式会社サンプル商事 | E9: 2026年9月分 保守料 | F9: 110000 | G9: =IF(OR(B9="",C9="",D9="コード誤り"),"",IFERROR(IF(OR(INDEX(取引先マスタ!$E$5:$E$204,MATCH(C9,取引先マスタ!$A$5:$A$204,0))="",INDEX(取引先マスタ!$F$5:$F$204,MATCH(C9,取引先マスタ!$A$5:$A$204,0))=""),"",DATE(YEAR(B9),MONTH(B9)+INDEX(取引先マスタ!$E$5:$E$204,MATCH(C9,取引先マスタ!$A$5:$A$204,0)),MIN(INDEX(取引先マスタ!$F$5:$F$204,MATCH(C9,取引先マスタ!$A$5:$A$204,0)),DAY(EOMONTH(B9,INDEX(取引先マスタ!$E$5:$E$204,MATCH(C9,取引先マスタ!$A$5:$A$204,0))))))),"")) -> 46326 | I9: =IF(H9<>"",H9,G9) -> 46326 | J9: メール(PDF) | M9: =IF(A9="","",SUMIF(入金明細!$F$5:$F$1004,A9,入金明細!$E$5:$E$1004)) -> 0 | N9: =IF(OR(A9="",N(M9)=0),"",SUMPRODUCT(MAX((入金明細!$F$5:$F$1004=A9)*入金明細!$B$5:$B$1004))) | P9: =IF(OR(A9="",F9=""),"",F9-N(M9)-N(O9)) -> 110000 | R9: =IF(A9="","",IF(Q9="取消","取消",IF(T9<>"","要入力",IF(K9="","未送付",IF(P9=0,"入金済",IF(P9<0,"過入金",IF(設定!$C$5>I9,IF(N(M9)>0,"一部入金・超過","期日超過"),IF(N(M9)>0,"一部入金",IF(I9-設定!$C$5<=設定!$C$6,"期日間近","入金待ち"))))))))) -> 未送付 | S9: =IF(OR(R9="期日超過",R9="一部入金・超過"),設定!$C$5-I9,"") | T9: =IF(A9="","",TRIM(IF(B9="","請求日 ","")&IF(C9="","取引先 ",IF(D9="コード誤り","取引先コード誤り ",""))&IF(E9="","件名 ","")&IF(F9="","請求額 ","")&IF(AND(F9<>"",I9=""),"入金期日(マスタの支払条件が未登録) ","")&IF(J9="","送付方法 ","")&IF(AND(K9<>"",L9=""),"送付者 ","")&IF(AND(K9<>"",N(K9)>設定!$C$5),"送付日が未来の日付 ","")&IF(AND(K9<>"",N(M9)>0,N(P9)<=0,U9=""),"消込確認者 ",""))) | V9: SAMPLE: 未送付
A10: =IF(COUNTA(B10,C10,E10,F10)=0,"",設定!$C$4&TEXT(ROW()-4,"00000")) -> INV-00006 | B10: 46280 | C10: C003 | D10: =IF(C10="","",IFERROR(INDEX(取引先マスタ!$B$5:$B$204,MATCH(C10,取引先マスタ!$A$5:$A$204,0)),"コード誤り")) -> 合同会社デモ | E10: 追加作業費 | F10: 33000 | G10: =IF(OR(B10="",C10="",D10="コード誤り"),"",IFERROR(IF(OR(INDEX(取引先マスタ!$E$5:$E$204,MATCH(C10,取引先マスタ!$A$5:$A$204,0))="",INDEX(取引先マスタ!$F$5:$F$204,MATCH(C10,取引先マスタ!$A$5:$A$204,0))=""),"",DATE(YEAR(B10),MONTH(B10)+INDEX(取引先マスタ!$E$5:$E$204,MATCH(C10,取引先マスタ!$A$5:$A$204,0)),MIN(INDEX(取引先マスタ!$F$5:$F$204,MATCH(C10,取引先マスタ!$A$5:$A$204,0)),DAY(EOMONTH(B10,INDEX(取引先マスタ!$E$5:$E$204,MATCH(C10,取引先マスタ!$A$5:$A$204,0))))))),"")) -> 46326 | I10: =IF(H10<>"",H10,G10) -> 46326 | J10: 請求書発行システム | K10: 46280 | L10: 鈴木 | M10: =IF(A10="","",SUMIF(入金明細!$F$5:$F$1004,A10,入金明細!$E$5:$E$1004)) -> 0 | N10: =IF(OR(A10="",N(M10)=0),"",SUMPRODUCT(MAX((入金明細!$F$5:$F$1004=A10)*入金明細!$B$5:$B$1004))) | P10: =IF(OR(A10="",F10=""),"",F10-N(M10)-N(O10)) -> 33000 | Q10: 取消 | R10: =IF(A10="","",IF(Q10="取消","取消",IF(T10<>"","要入力",IF(K10="","未送付",IF(P10=0,"入金済",IF(P10<0,"過入金",IF(設定!$C$5>I10,IF(N(M10)>0,"一部入金・超過","期日超過"),IF(N(M10)>0,"一部入金",IF(I10-設定!$C$5<=設定!$C$6,"期日間近","入金待ち"))))))))) -> 取消 | S10: =IF(OR(R10="期日超過",R10="一部入金・超過"),設定!$C$5-I10,"") | T10: =IF(A10="","",TRIM(IF(B10="","請求日 ","")&IF(C10="","取引先 ",IF(D10="コード誤り","取引先コード誤り ",""))&IF(E10="","件名 ","")&IF(F10="","請求額 ","")&IF(AND(F10<>"",I10=""),"入金期日(マスタの支払条件が未登録) ","")&IF(J10="","送付方法 ","")&IF(AND(K10<>"",L10=""),"送付者 ","")&IF(AND(K10<>"",N(K10)>設定!$C$5),"送付日が未来の日付 ","")&IF(AND(K10<>"",N(M10)>0,N(P10)<=0,U10=""),"消込確認者 ",""))) | V10: SAMPLE: 金額誤りのため取消→次行で再発行
A11: =IF(COUNTA(B11,C11,E11,F11)=0,"",設定!$C$4&TEXT(ROW()-4,"00000")) -> INV-00007 | B11: 46280 | C11: C003 | D11: =IF(C11="","",IFERROR(INDEX(取引先マスタ!$B$5:$B$204,MATCH(C11,取引先マスタ!$A$5:$A$204,0)),"コード誤り")) -> 合同会社デモ | E11: 追加作業費(再発行) | F11: 36300 | G11: =IF(OR(B11="",C11="",D11="コード誤り"),"",IFERROR(IF(OR(INDEX(取引先マスタ!$E$5:$E$204,MATCH(C11,取引先マスタ!$A$5:$A$204,0))="",INDEX(取引先マスタ!$F$5:$F$204,MATCH(C11,取引先マスタ!$A$5:$A$204,0))=""),"",DATE(YEAR(B11),MONTH(B11)+INDEX(取引先マスタ!$E$5:$E$204,MATCH(C11,取引先マスタ!$A$5:$A$204,0)),MIN(INDEX(取引先マスタ!$F$5:$F$204,MATCH(C11,取引先マスタ!$A$5:$A$204,0)),DAY(EOMONTH(B11,INDEX(取引先マスタ!$E$5:$E$204,MATCH(C11,取引先マスタ!$A$5:$A$204,0))))))),"")) -> 46326 | H11: 46300 | I11: =IF(H11<>"",H11,G11) -> 46300 | J11: 請求書発行システム | K11: 46281 | L11: 鈴木 | M11: =IF(A11="","",SUMIF(入金明細!$F$5:$F$1004,A11,入金明細!$E$5:$E$1004)) -> 0 | N11: =IF(OR(A11="",N(M11)=0),"",SUMPRODUCT(MAX((入金明細!$F$5:$F$1004=A11)*入金明細!$B$5:$B$1004))) | P11: =IF(OR(A11="",F11=""),"",F11-N(M11)-N(O11)) -> 36300 | R11: =IF(A11="","",IF(Q11="取消","取消",IF(T11<>"","要入力",IF(K11="","未送付",IF(P11=0,"入金済",IF(P11<0,"過入金",IF(設定!$C$5>I11,IF(N(M11)>0,"一部入金・超過","期日超過"),IF(N(M11)>0,"一部入金",IF(I11-設定!$C$5<=設定!$C$6,"期日間近","入金待ち"))))))))) -> 期日間近 | S11: =IF(OR(R11="期日超過",R11="一部入金・超過"),設定!$C$5-I11,"") | T11: =IF(A11="","",TRIM(IF(B11="","請求日 ","")&IF(C11="","取引先 ",IF(D11="コード誤り","取引先コード誤り ",""))&IF(E11="","件名 ","")&IF(F11="","請求額 ","")&IF(AND(F11<>"",I11=""),"入金期日(マスタの支払条件が未登録) ","")&IF(J11="","送付方法 ","")&IF(AND(K11<>"",L11=""),"送付者 ","")&IF(AND(K11<>"",N(K11)>設定!$C$5),"送付日が未来の日付 ","")&IF(AND(K11<>"",N(M11)>0,N(P11)<=0,U11=""),"消込確認者 ",""))) | V11: SAMPLE: 個別期日・期日間近
A12: =IF(COUNTA(B12,C12,E12,F12)=0,"",設定!$C$4&TEXT(ROW()-4,"00000")) | D12: =IF(C12="","",IFERROR(INDEX(取引先マスタ!$B$5:$B$204,MATCH(C12,取引先マスタ!$A$5:$A$204,0)),"コード誤り")) | G12: =IF(OR(B12="",C12="",D12="コード誤り"),"",IFERROR(IF(OR(INDEX(取引先マスタ!$E$5:$E$204,MATCH(C12,取引先マスタ!$A$5:$A$204,0))="",INDEX(取引先マスタ!$F$5:$F$204,MATCH(C12,取引先マスタ!$A$5:$A$204,0))=""),"",DATE(YEAR(B12),MONTH(B12)+INDEX(取引先マスタ!$E$5:$E$204,MATCH(C12,取引先マスタ!$A$5:$A$204,0)),MIN(INDEX(取引先マスタ!$F$5:$F$204,MATCH(C12,取引先マスタ!$A$5:$A$204,0)),DAY(EOMONTH(B12,INDEX(取引先マスタ!$E$5:$E$204,MATCH(C12,取引先マスタ!$A$5:$A$204,0))))))),"")) | I12: =IF(H12<>"",H12,G12) | M12: =IF(A12="","",SUMIF(入金明細!$F$5:$F$1004,A12,入金明細!$E$5:$E$1004)) | N12: =IF(OR(A12="",N(M12)=0),"",SUMPRODUCT(MAX((入金明細!$F$5:$F$1004=A12)*入金明細!$B$5:$B$1004))) | P12: =IF(OR(A12="",F12=""),"",F12-N(M12)-N(O12)) | R12: =IF(A12="","",IF(Q12="取消","取消",IF(T12<>"","要入力",IF(K12="","未送付",IF(P12=0,"入金済",IF(P12<0,"過入金",IF(設定!$C$5>I12,IF(N(M12)>0,"一部入金・超過","期日超過"),IF(N(M12)>0,"一部入金",IF(I12-設定!$C$5<=設定!$C$6,"期日間近","入金待ち"))))))))) | S12: =IF(OR(R12="期日超過",R12="一部入金・超過"),設定!$C$5-I12,"") | T12: =IF(A12="","",TRIM(IF(B12="","請求日 ","")&IF(C12="","取引先 ",IF(D12="コード誤り","取引先コード誤り ",""))&IF(E12="","件名 ","")&IF(F12="","請求額 ","")&IF(AND(F12<>"",I12=""),"入金期日(マスタの支払条件が未登録) ","")&IF(J12="","送付方法 ","")&IF(AND(K12<>"",L12=""),"送付者 ","")&IF(AND(K12<>"",N(K12)>設定!$C$5),"送付日が未来の日付 ","")&IF(AND(K12<>"",N(M12)>0,N(P12)<=0,U12=""),"消込確認者 ","")))
A13: =IF(COUNTA(B13,C13,E13,F13)=0,"",設定!$C$4&TEXT(ROW()-4,"00000")) | D13: =IF(C13="","",IFERROR(INDEX(取引先マスタ!$B$5:$B$204,MATCH(C13,取引先マスタ!$A$5:$A$204,0)),"コード誤り")) | G13: =IF(OR(B13="",C13="",D13="コード誤り"),"",IFERROR(IF(OR(INDEX(取引先マスタ!$E$5:$E$204,MATCH(C13,取引先マスタ!$A$5:$A$204,0))="",INDEX(取引先マスタ!$F$5:$F$204,MATCH(C13,取引先マスタ!$A$5:$A$204,0))=""),"",DATE(YEAR(B13),MONTH(B13)+INDEX(取引先マスタ!$E$5:$E$204,MATCH(C13,取引先マスタ!$A$5:$A$204,0)),MIN(INDEX(取引先マスタ!$F$5:$F$204,MATCH(C13,取引先マスタ!$A$5:$A$204,0)),DAY(EOMONTH(B13,INDEX(取引先マスタ!$E$5:$E$204,MATCH(C13,取引先マスタ!$A$5:$A$204,0))))))),"")) | I13: =IF(H13<>"",H13,G13) | M13: =IF(A13="","",SUMIF(入金明細!$F$5:$F$1004,A13,入金明細!$E$5:$E$1004)) | N13: =IF(OR(A13="",N(M13)=0),"",SUMPRODUCT(MAX((入金明細!$F$5:$F$1004=A13)*入金明細!$B$5:$B$1004))) | P13: =IF(OR(A13="",F13=""),"",F13-N(M13)-N(O13)) | R13: =IF(A13="","",IF(Q13="取消","取消",IF(T13<>"","要入力",IF(K13="","未送付",IF(P13=0,"入金済",IF(P13<0,"過入金",IF(設定!$C$5>I13,IF(N(M13)>0,"一部入金・超過","期日超過"),IF(N(M13)>0,"一部入金",IF(I13-設定!$C$5<=設定!$C$6,"期日間近","入金待ち"))))))))) | S13: =IF(OR(R13="期日超過",R13="一部入金・超過"),設定!$C$5-I13,"") | T13: =IF(A13="","",TRIM(IF(B13="","請求日 ","")&IF(C13="","取引先 ",IF(D13="コード誤り","取引先コード誤り ",""))&IF(E13="","件名 ","")&IF(F13="","請求額 ","")&IF(AND(F13<>"",I13=""),"入金期日(マスタの支払条件が未登録) ","")&IF(J13="","送付方法 ","")&IF(AND(K13<>"",L13=""),"送付者 ","")&IF(AND(K13<>"",N(K13)>設定!$C$5),"送付日が未来の日付 ","")&IF(AND(K13<>"",N(M13)>0,N(P13)<=0,U13=""),"消込確認者 ","")))
A14: =IF(COUNTA(B14,C14,E14,F14)=0,"",設定!$C$4&TEXT(ROW()-4,"00000")) | D14: =IF(C14="","",IFERROR(INDEX(取引先マスタ!$B$5:$B$204,MATCH(C14,取引先マスタ!$A$5:$A$204,0)),"コード誤り")) | G14: =IF(OR(B14="",C14="",D14="コード誤り"),"",IFERROR(IF(OR(INDEX(取引先マスタ!$E$5:$E$204,MATCH(C14,取引先マスタ!$A$5:$A$204,0))="",INDEX(取引先マスタ!$F$5:$F$204,MATCH(C14,取引先マスタ!$A$5:$A$204,0))=""),"",DATE(YEAR(B14),MONTH(B14)+INDEX(取引先マスタ!$E$5:$E$204,MATCH(C14,取引先マスタ!$A$5:$A$204,0)),MIN(INDEX(取引先マスタ!$F$5:$F$204,MATCH(C14,取引先マスタ!$A$5:$A$204,0)),DAY(EOMONTH(B14,INDEX(取引先マスタ!$E$5:$E$204,MATCH(C14,取引先マスタ!$A$5:$A$204,0))))))),"")) | I14: =IF(H14<>"",H14,G14) | M14: =IF(A14="","",SUMIF(入金明細!$F$5:$F$1004,A14,入金明細!$E$5:$E$1004)) | N14: =IF(OR(A14="",N(M14)=0),"",SUMPRODUCT(MAX((入金明細!$F$5:$F$1004=A14)*入金明細!$B$5:$B$1004))) | P14: =IF(OR(A14="",F14=""),"",F14-N(M14)-N(O14)) | R14: =IF(A14="","",IF(Q14="取消","取消",IF(T14<>"","要入力",IF(K14="","未送付",IF(P14=0,"入金済",IF(P14<0,"過入金",IF(設定!$C$5>I14,IF(N(M14)>0,"一部入金・超過","期日超過"),IF(N(M14)>0,"一部入金",IF(I14-設定!$C$5<=設定!$C$6,"期日間近","入金待ち"))))))))) | S14: =IF(OR(R14="期日超過",R14="一部入金・超過"),設定!$C$5-I14,"") | T14: =IF(A14="","",TRIM(IF(B14="","請求日 ","")&IF(C14="","取引先 ",IF(D14="コード誤り","取引先コード誤り ",""))&IF(E14="","件名 ","")&IF(F14="","請求額 ","")&IF(AND(F14<>"",I14=""),"入金期日(マスタの支払条件が未登録) ","")&IF(J14="","送付方法 ","")&IF(AND(K14<>"",L14=""),"送付者 ","")&IF(AND(K14<>"",N(K14)>設定!$C$5),"送付日が未来の日付 ","")&IF(AND(K14<>"",N(M14)>0,N(P14)<=0,U14=""),"消込確認者 ","")))
A15: =IF(COUNTA(B15,C15,E15,F15)=0,"",設定!$C$4&TEXT(ROW()-4,"00000")) | D15: =IF(C15="","",IFERROR(INDEX(取引先マスタ!$B$5:$B$204,MATCH(C15,取引先マスタ!$A$5:$A$204,0)),"コード誤り")) | G15: =IF(OR(B15="",C15="",D15="コード誤り"),"",IFERROR(IF(OR(INDEX(取引先マスタ!$E$5:$E$204,MATCH(C15,取引先マスタ!$A$5:$A$204,0))="",INDEX(取引先マスタ!$F$5:$F$204,MATCH(C15,取引先マスタ!$A$5:$A$204,0))=""),"",DATE(YEAR(B15),MONTH(B15)+INDEX(取引先マスタ!$E$5:$E$204,MATCH(C15,取引先マスタ!$A$5:$A$204,0)),MIN(INDEX(取引先マスタ!$F$5:$F$204,MATCH(C15,取引先マスタ!$A$5:$A$204,0)),DAY(EOMONTH(B15,INDEX(取引先マスタ!$E$5:$E$204,MATCH(C15,取引先マスタ!$A$5:$A$204,0))))))),"")) | I15: =IF(H15<>"",H15,G15) | M15: =IF(A15="","",SUMIF(入金明細!$F$5:$F$1004,A15,入金明細!$E$5:$E$1004)) | N15: =IF(OR(A15="",N(M15)=0),"",SUMPRODUCT(MAX((入金明細!$F$5:$F$1004=A15)*入金明細!$B$5:$B$1004))) | P15: =IF(OR(A15="",F15=""),"",F15-N(M15)-N(O15)) | R15: =IF(A15="","",IF(Q15="取消","取消",IF(T15<>"","要入力",IF(K15="","未送付",IF(P15=0,"入金済",IF(P15<0,"過入金",IF(設定!$C$5>I15,IF(N(M15)>0,"一部入金・超過","期日超過"),IF(N(M15)>0,"一部入金",IF(I15-設定!$C$5<=設定!$C$6,"期日間近","入金待ち"))))))))) | S15: =IF(OR(R15="期日超過",R15="一部入金・超過"),設定!$C$5-I15,"") | T15: =IF(A15="","",TRIM(IF(B15="","請求日 ","")&IF(C15="","取引先 ",IF(D15="コード誤り","取引先コード誤り ",""))&IF(E15="","件名 ","")&IF(F15="","請求額 ","")&IF(AND(F15<>"",I15=""),"入金期日(マスタの支払条件が未登録) ","")&IF(J15="","送付方法 ","")&IF(AND(K15<>"",L15=""),"送付者 ","")&IF(AND(K15<>"",N(K15)>設定!$C$5),"送付日が未来の日付 ","")&IF(AND(K15<>"",N(M15)>0,N(P15)<=0,U15=""),"消込確認者 ","")))
A16: =IF(COUNTA(B16,C16,E16,F16)=0,"",設定!$C$4&TEXT(ROW()-4,"00000")) | D16: =IF(C16="","",IFERROR(INDEX(取引先マスタ!$B$5:$B$204,MATCH(C16,取引先マスタ!$A$5:$A$204,0)),"コード誤り")) | G16: =IF(OR(B16="",C16="",D16="コード誤り"),"",IFERROR(IF(OR(INDEX(取引先マスタ!$E$5:$E$204,MATCH(C16,取引先マスタ!$A$5:$A$204,0))="",INDEX(取引先マスタ!$F$5:$F$204,MATCH(C16,取引先マスタ!$A$5:$A$204,0))=""),"",DATE(YEAR(B16),MONTH(B16)+INDEX(取引先マスタ!$E$5:$E$204,MATCH(C16,取引先マスタ!$A$5:$A$204,0)),MIN(INDEX(取引先マスタ!$F$5:$F$204,MATCH(C16,取引先マスタ!$A$5:$A$204,0)),DAY(EOMONTH(B16,INDEX(取引先マスタ!$E$5:$E$204,MATCH(C16,取引先マスタ!$A$5:$A$204,0))))))),"")) | I16: =IF(H16<>"",H16,G16) | M16: =IF(A16="","",SUMIF(入金明細!$F$5:$F$1004,A16,入金明細!$E$5:$E$1004)) | N16: =IF(OR(A16="",N(M16)=0),"",SUMPRODUCT(MAX((入金明細!$F$5:$F$1004=A16)*入金明細!$B$5:$B$1004))) | P16: =IF(OR(A16="",F16=""),"",F16-N(M16)-N(O16)) | R16: =IF(A16="","",IF(Q16="取消","取消",IF(T16<>"","要入力",IF(K16="","未送付",IF(P16=0,"入金済",IF(P16<0,"過入金",IF(設定!$C$5>I16,IF(N(M16)>0,"一部入金・超過","期日超過"),IF(N(M16)>0,"一部入金",IF(I16-設定!$C$5<=設定!$C$6,"期日間近","入金待ち"))))))))) | S16: =IF(OR(R16="期日超過",R16="一部入金・超過"),設定!$C$5-I16,"") | T16: =IF(A16="","",TRIM(IF(B16="","請求日 ","")&IF(C16="","取引先 ",IF(D16="コード誤り","取引先コード誤り ",""))&IF(E16="","件名 ","")&IF(F16="","請求額 ","")&IF(AND(F16<>"",I16=""),"入金期日(マスタの支払条件が未登録) ","")&IF(J16="","送付方法 ","")&IF(AND(K16<>"",L16=""),"送付者 ","")&IF(AND(K16<>"",N(K16)>設定!$C$5),"送付日が未来の日付 ","")&IF(AND(K16<>"",N(M16)>0,N(P16)<=0,U16=""),"消込確認者 ","")))
A17: =IF(COUNTA(B17,C17,E17,F17)=0,"",設定!$C$4&TEXT(ROW()-4,"00000")) | D17: =IF(C17="","",IFERROR(INDEX(取引先マスタ!$B$5:$B$204,MATCH(C17,取引先マスタ!$A$5:$A$204,0)),"コード誤り")) | G17: =IF(OR(B17="",C17="",D17="コード誤り"),"",IFERROR(IF(OR(INDEX(取引先マスタ!$E$5:$E$204,MATCH(C17,取引先マスタ!$A$5:$A$204,0))="",INDEX(取引先マスタ!$F$5:$F$204,MATCH(C17,取引先マスタ!$A$5:$A$204,0))=""),"",DATE(YEAR(B17),MONTH(B17)+INDEX(取引先マスタ!$E$5:$E$204,MATCH(C17,取引先マスタ!$A$5:$A$204,0)),MIN(INDEX(取引先マスタ!$F$5:$F$204,MATCH(C17,取引先マスタ!$A$5:$A$204,0)),DAY(EOMONTH(B17,INDEX(取引先マスタ!$E$5:$E$204,MATCH(C17,取引先マスタ!$A$5:$A$204,0))))))),"")) | I17: =IF(H17<>"",H17,G17) | M17: =IF(A17="","",SUMIF(入金明細!$F$5:$F$1004,A17,入金明細!$E$5:$E$1004)) | N17: =IF(OR(A17="",N(M17)=0),"",SUMPRODUCT(MAX((入金明細!$F$5:$F$1004=A17)*入金明細!$B$5:$B$1004))) | P17: =IF(OR(A17="",F17=""),"",F17-N(M17)-N(O17)) | R17: =IF(A17="","",IF(Q17="取消","取消",IF(T17<>"","要入力",IF(K17="","未送付",IF(P17=0,"入金済",IF(P17<0,"過入金",IF(設定!$C$5>I17,IF(N(M17)>0,"一部入金・超過","期日超過"),IF(N(M17)>0,"一部入金",IF(I17-設定!$C$5<=設定!$C$6,"期日間近","入金待ち"))))))))) | S17: =IF(OR(R17="期日超過",R17="一部入金・超過"),設定!$C$5-I17,"") | T17: =IF(A17="","",TRIM(IF(B17="","請求日 ","")&IF(C17="","取引先 ",IF(D17="コード誤り","取引先コード誤り ",""))&IF(E17="","件名 ","")&IF(F17="","請求額 ","")&IF(AND(F17<>"",I17=""),"入金期日(マスタの支払条件が未登録) ","")&IF(J17="","送付方法 ","")&IF(AND(K17<>"",L17=""),"送付者 ","")&IF(AND(K17<>"",N(K17)>設定!$C$5),"送付日が未来の日付 ","")&IF(AND(K17<>"",N(M17)>0,N(P17)<=0,U17=""),"消込確認者 ","")))
A18: =IF(COUNTA(B18,C18,E18,F18)=0,"",設定!$C$4&TEXT(ROW()-4,"00000")) | D18: =IF(C18="","",IFERROR(INDEX(取引先マスタ!$B$5:$B$204,MATCH(C18,取引先マスタ!$A$5:$A$204,0)),"コード誤り")) | G18: =IF(OR(B18="",C18="",D18="コード誤り"),"",IFERROR(IF(OR(INDEX(取引先マスタ!$E$5:$E$204,MATCH(C18,取引先マスタ!$A$5:$A$204,0))="",INDEX(取引先マスタ!$F$5:$F$204,MATCH(C18,取引先マスタ!$A$5:$A$204,0))=""),"",DATE(YEAR(B18),MONTH(B18)+INDEX(取引先マスタ!$E$5:$E$204,MATCH(C18,取引先マスタ!$A$5:$A$204,0)),MIN(INDEX(取引先マスタ!$F$5:$F$204,MATCH(C18,取引先マスタ!$A$5:$A$204,0)),DAY(EOMONTH(B18,INDEX(取引先マスタ!$E$5:$E$204,MATCH(C18,取引先マスタ!$A$5:$A$204,0))))))),"")) | I18: =IF(H18<>"",H18,G18) | M18: =IF(A18="","",SUMIF(入金明細!$F$5:$F$1004,A18,入金明細!$E$5:$E$1004)) | N18: =IF(OR(A18="",N(M18)=0),"",SUMPRODUCT(MAX((入金明細!$F$5:$F$1004=A18)*入金明細!$B$5:$B$1004))) | P18: =IF(OR(A18="",F18=""),"",F18-N(M18)-N(O18)) | R18: =IF(A18="","",IF(Q18="取消","取消",IF(T18<>"","要入力",IF(K18="","未送付",IF(P18=0,"入金済",IF(P18<0,"過入金",IF(設定!$C$5>I18,IF(N(M18)>0,"一部入金・超過","期日超過"),IF(N(M18)>0,"一部入金",IF(I18-設定!$C$5<=設定!$C$6,"期日間近","入金待ち"))))))))) | S18: =IF(OR(R18="期日超過",R18="一部入金・超過"),設定!$C$5-I18,"") | T18: =IF(A18="","",TRIM(IF(B18="","請求日 ","")&IF(C18="","取引先 ",IF(D18="コード誤り","取引先コード誤り ",""))&IF(E18="","件名 ","")&IF(F18="","請求額 ","")&IF(AND(F18<>"",I18=""),"入金期日(マスタの支払条件が未登録) ","")&IF(J18="","送付方法 ","")&IF(AND(K18<>"",L18=""),"送付者 ","")&IF(AND(K18<>"",N(K18)>設定!$C$5),"送付日が未来の日付 ","")&IF(AND(K18<>"",N(M18)>0,N(P18)<=0,U18=""),"消込確認者 ","")))
A19: =IF(COUNTA(B19,C19,E19,F19)=0,"",設定!$C$4&TEXT(ROW()-4,"00000")) | D19: =IF(C19="","",IFERROR(INDEX(取引先マスタ!$B$5:$B$204,MATCH(C19,取引先マスタ!$A$5:$A$204,0)),"コード誤り")) | G19: =IF(OR(B19="",C19="",D19="コード誤り"),"",IFERROR(IF(OR(INDEX(取引先マスタ!$E$5:$E$204,MATCH(C19,取引先マスタ!$A$5:$A$204,0))="",INDEX(取引先マスタ!$F$5:$F$204,MATCH(C19,取引先マスタ!$A$5:$A$204,0))=""),"",DATE(YEAR(B19),MONTH(B19)+INDEX(取引先マスタ!$E$5:$E$204,MATCH(C19,取引先マスタ!$A$5:$A$204,0)),MIN(INDEX(取引先マスタ!$F$5:$F$204,MATCH(C19,取引先マスタ!$A$5:$A$204,0)),DAY(EOMONTH(B19,INDEX(取引先マスタ!$E$5:$E$204,MATCH(C19,取引先マスタ!$A$5:$A$204,0))))))),"")) | I19: =IF(H19<>"",H19,G19) | M19: =IF(A19="","",SUMIF(入金明細!$F$5:$F$1004,A19,入金明細!$E$5:$E$1004)) | N19: =IF(OR(A19="",N(M19)=0),"",SUMPRODUCT(MAX((入金明細!$F$5:$F$1004=A19)*入金明細!$B$5:$B$1004))) | P19: =IF(OR(A19="",F19=""),"",F19-N(M19)-N(O19)) | R19: =IF(A19="","",IF(Q19="取消","取消",IF(T19<>"","要入力",IF(K19="","未送付",IF(P19=0,"入金済",IF(P19<0,"過入金",IF(設定!$C$5>I19,IF(N(M19)>0,"一部入金・超過","期日超過"),IF(N(M19)>0,"一部入金",IF(I19-設定!$C$5<=設定!$C$6,"期日間近","入金待ち"))))))))) | S19: =IF(OR(R19="期日超過",R19="一部入金・超過"),設定!$C$5-I19,"") | T19: =IF(A19="","",TRIM(IF(B19="","請求日 ","")&IF(C19="","取引先 ",IF(D19="コード誤り","取引先コード誤り ",""))&IF(E19="","件名 ","")&IF(F19="","請求額 ","")&IF(AND(F19<>"",I19=""),"入金期日(マスタの支払条件が未登録) ","")&IF(J19="","送付方法 ","")&IF(AND(K19<>"",L19=""),"送付者 ","")&IF(AND(K19<>"",N(K19)>設定!$C$5),"送付日が未来の日付 ","")&IF(AND(K19<>"",N(M19)>0,N(P19)<=0,U19=""),"消込確認者 ","")))
A20: =IF(COUNTA(B20,C20,E20,F20)=0,"",設定!$C$4&TEXT(ROW()-4,"00000")) | D20: =IF(C20="","",IFERROR(INDEX(取引先マスタ!$B$5:$B$204,MATCH(C20,取引先マスタ!$A$5:$A$204,0)),"コード誤り")) | G20: =IF(OR(B20="",C20="",D20="コード誤り"),"",IFERROR(IF(OR(INDEX(取引先マスタ!$E$5:$E$204,MATCH(C20,取引先マスタ!$A$5:$A$204,0))="",INDEX(取引先マスタ!$F$5:$F$204,MATCH(C20,取引先マスタ!$A$5:$A$204,0))=""),"",DATE(YEAR(B20),MONTH(B20)+INDEX(取引先マスタ!$E$5:$E$204,MATCH(C20,取引先マスタ!$A$5:$A$204,0)),MIN(INDEX(取引先マスタ!$F$5:$F$204,MATCH(C20,取引先マスタ!$A$5:$A$204,0)),DAY(EOMONTH(B20,INDEX(取引先マスタ!$E$5:$E$204,MATCH(C20,取引先マスタ!$A$5:$A$204,0))))))),"")) | I20: =IF(H20<>"",H20,G20) | M20: =IF(A20="","",SUMIF(入金明細!$F$5:$F$1004,A20,入金明細!$E$5:$E$1004)) | N20: =IF(OR(A20="",N(M20)=0),"",SUMPRODUCT(MAX((入金明細!$F$5:$F$1004=A20)*入金明細!$B$5:$B$1004))) | P20: =IF(OR(A20="",F20=""),"",F20-N(M20)-N(O20)) | R20: =IF(A20="","",IF(Q20="取消","取消",IF(T20<>"","要入力",IF(K20="","未送付",IF(P20=0,"入金済",IF(P20<0,"過入金",IF(設定!$C$5>I20,IF(N(M20)>0,"一部入金・超過","期日超過"),IF(N(M20)>0,"一部入金",IF(I20-設定!$C$5<=設定!$C$6,"期日間近","入金待ち"))))))))) | S20: =IF(OR(R20="期日超過",R20="一部入金・超過"),設定!$C$5-I20,"") | T20: =IF(A20="","",TRIM(IF(B20="","請求日 ","")&IF(C20="","取引先 ",IF(D20="コード誤り","取引先コード誤り ",""))&IF(E20="","件名 ","")&IF(F20="","請求額 ","")&IF(AND(F20<>"",I20=""),"入金期日(マスタの支払条件が未登録) ","")&IF(J20="","送付方法 ","")&IF(AND(K20<>"",L20=""),"送付者 ","")&IF(AND(K20<>"",N(K20)>設定!$C$5),"送付日が未来の日付 ","")&IF(AND(K20<>"",N(M20)>0,N(P20)<=0,U20=""),"消込確認者 ","")))
A21: =IF(COUNTA(B21,C21,E21,F21)=0,"",設定!$C$4&TEXT(ROW()-4,"00000")) | D21: =IF(C21="","",IFERROR(INDEX(取引先マスタ!$B$5:$B$204,MATCH(C21,取引先マスタ!$A$5:$A$204,0)),"コード誤り")) | G21: =IF(OR(B21="",C21="",D21="コード誤り"),"",IFERROR(IF(OR(INDEX(取引先マスタ!$E$5:$E$204,MATCH(C21,取引先マスタ!$A$5:$A$204,0))="",INDEX(取引先マスタ!$F$5:$F$204,MATCH(C21,取引先マスタ!$A$5:$A$204,0))=""),"",DATE(YEAR(B21),MONTH(B21)+INDEX(取引先マスタ!$E$5:$E$204,MATCH(C21,取引先マスタ!$A$5:$A$204,0)),MIN(INDEX(取引先マスタ!$F$5:$F$204,MATCH(C21,取引先マスタ!$A$5:$A$204,0)),DAY(EOMONTH(B21,INDEX(取引先マスタ!$E$5:$E$204,MATCH(C21,取引先マスタ!$A$5:$A$204,0))))))),"")) | I21: =IF(H21<>"",H21,G21) | M21: =IF(A21="","",SUMIF(入金明細!$F$5:$F$1004,A21,入金明細!$E$5:$E$1004)) | N21: =IF(OR(A21="",N(M21)=0),"",SUMPRODUCT(MAX((入金明細!$F$5:$F$1004=A21)*入金明細!$B$5:$B$1004))) | P21: =IF(OR(A21="",F21=""),"",F21-N(M21)-N(O21)) | R21: =IF(A21="","",IF(Q21="取消","取消",IF(T21<>"","要入力",IF(K21="","未送付",IF(P21=0,"入金済",IF(P21<0,"過入金",IF(設定!$C$5>I21,IF(N(M21)>0,"一部入金・超過","期日超過"),IF(N(M21)>0,"一部入金",IF(I21-設定!$C$5<=設定!$C$6,"期日間近","入金待ち"))))))))) | S21: =IF(OR(R21="期日超過",R21="一部入金・超過"),設定!$C$5-I21,"") | T21: =IF(A21="","",TRIM(IF(B21="","請求日 ","")&IF(C21="","取引先 ",IF(D21="コード誤り","取引先コード誤り ",""))&IF(E21="","件名 ","")&IF(F21="","請求額 ","")&IF(AND(F21<>"",I21=""),"入金期日(マスタの支払条件が未登録) ","")&IF(J21="","送付方法 ","")&IF(AND(K21<>"",L21=""),"送付者 ","")&IF(AND(K21<>"",N(K21)>設定!$C$5),"送付日が未来の日付 ","")&IF(AND(K21<>"",N(M21)>0,N(P21)<=0,U21=""),"消込確認者 ","")))
A22: =IF(COUNTA(B22,C22,E22,F22)=0,"",設定!$C$4&TEXT(ROW()-4,"00000")) | D22: =IF(C22="","",IFERROR(INDEX(取引先マスタ!$B$5:$B$204,MATCH(C22,取引先マスタ!$A$5:$A$204,0)),"コード誤り")) | G22: =IF(OR(B22="",C22="",D22="コード誤り"),"",IFERROR(IF(OR(INDEX(取引先マスタ!$E$5:$E$204,MATCH(C22,取引先マスタ!$A$5:$A$204,0))="",INDEX(取引先マスタ!$F$5:$F$204,MATCH(C22,取引先マスタ!$A$5:$A$204,0))=""),"",DATE(YEAR(B22),MONTH(B22)+INDEX(取引先マスタ!$E$5:$E$204,MATCH(C22,取引先マスタ!$A$5:$A$204,0)),MIN(INDEX(取引先マスタ!$F$5:$F$204,MATCH(C22,取引先マスタ!$A$5:$A$204,0)),DAY(EOMONTH(B22,INDEX(取引先マスタ!$E$5:$E$204,MATCH(C22,取引先マスタ!$A$5:$A$204,0))))))),"")) | I22: =IF(H22<>"",H22,G22) | M22: =IF(A22="","",SUMIF(入金明細!$F$5:$F$1004,A22,入金明細!$E$5:$E$1004)) | N22: =IF(OR(A22="",N(M22)=0),"",SUMPRODUCT(MAX((入金明細!$F$5:$F$1004=A22)*入金明細!$B$5:$B$1004))) | P22: =IF(OR(A22="",F22=""),"",F22-N(M22)-N(O22)) | R22: =IF(A22="","",IF(Q22="取消","取消",IF(T22<>"","要入力",IF(K22="","未送付",IF(P22=0,"入金済",IF(P22<0,"過入金",IF(設定!$C$5>I22,IF(N(M22)>0,"一部入金・超過","期日超過"),IF(N(M22)>0,"一部入金",IF(I22-設定!$C$5<=設定!$C$6,"期日間近","入金待ち"))))))))) | S22: =IF(OR(R22="期日超過",R22="一部入金・超過"),設定!$C$5-I22,"") | T22: =IF(A22="","",TRIM(IF(B22="","請求日 ","")&IF(C22="","取引先 ",IF(D22="コード誤り","取引先コード誤り ",""))&IF(E22="","件名 ","")&IF(F22="","請求額 ","")&IF(AND(F22<>"",I22=""),"入金期日(マスタの支払条件が未登録) ","")&IF(J22="","送付方法 ","")&IF(AND(K22<>"",L22=""),"送付者 ","")&IF(AND(K22<>"",N(K22)>設定!$C$5),"送付日が未来の日付 ","")&IF(AND(K22<>"",N(M22)>0,N(P22)<=0,U22=""),"消込確認者 ","")))
A23: =IF(COUNTA(B23,C23,E23,F23)=0,"",設定!$C$4&TEXT(ROW()-4,"00000")) | D23: =IF(C23="","",IFERROR(INDEX(取引先マスタ!$B$5:$B$204,MATCH(C23,取引先マスタ!$A$5:$A$204,0)),"コード誤り")) | G23: =IF(OR(B23="",C23="",D23="コード誤り"),"",IFERROR(IF(OR(INDEX(取引先マスタ!$E$5:$E$204,MATCH(C23,取引先マスタ!$A$5:$A$204,0))="",INDEX(取引先マスタ!$F$5:$F$204,MATCH(C23,取引先マスタ!$A$5:$A$204,0))=""),"",DATE(YEAR(B23),MONTH(B23)+INDEX(取引先マスタ!$E$5:$E$204,MATCH(C23,取引先マスタ!$A$5:$A$204,0)),MIN(INDEX(取引先マスタ!$F$5:$F$204,MATCH(C23,取引先マスタ!$A$5:$A$204,0)),DAY(EOMONTH(B23,INDEX(取引先マスタ!$E$5:$E$204,MATCH(C23,取引先マスタ!$A$5:$A$204,0))))))),"")) | I23: =IF(H23<>"",H23,G23) | M23: =IF(A23="","",SUMIF(入金明細!$F$5:$F$1004,A23,入金明細!$E$5:$E$1004)) | N23: =IF(OR(A23="",N(M23)=0),"",SUMPRODUCT(MAX((入金明細!$F$5:$F$1004=A23)*入金明細!$B$5:$B$1004))) | P23: =IF(OR(A23="",F23=""),"",F23-N(M23)-N(O23)) | R23: =IF(A23="","",IF(Q23="取消","取消",IF(T23<>"","要入力",IF(K23="","未送付",IF(P23=0,"入金済",IF(P23<0,"過入金",IF(設定!$C$5>I23,IF(N(M23)>0,"一部入金・超過","期日超過"),IF(N(M23)>0,"一部入金",IF(I23-設定!$C$5<=設定!$C$6,"期日間近","入金待ち"))))))))) | S23: =IF(OR(R23="期日超過",R23="一部入金・超過"),設定!$C$5-I23,"") | T23: =IF(A23="","",TRIM(IF(B23="","請求日 ","")&IF(C23="","取引先 ",IF(D23="コード誤り","取引先コード誤り ",""))&IF(E23="","件名 ","")&IF(F23="","請求額 ","")&IF(AND(F23<>"",I23=""),"入金期日(マスタの支払条件が未登録) ","")&IF(J23="","送付方法 ","")&IF(AND(K23<>"",L23=""),"送付者 ","")&IF(AND(K23<>"",N(K23)>設定!$C$5),"送付日が未来の日付 ","")&IF(AND(K23<>"",N(M23)>0,N(P23)<=0,U23=""),"消込確認者 ","")))
... A504: =IF(COUNTA(B504,C504,E504,F504)=0,"",設定!$C$4&TEXT(ROW()-4,"00000")) | D504: =IF(C504="","",IFERROR(INDEX(取引先マスタ!$B$5:$B$204,MATCH(C504,取引先マスタ!$A$5:$A$204,0)),"コード誤り")) | G504: =IF(OR(B504="",C504="",D504="コード誤り"),"",IFERROR(IF(OR(INDEX(取引先マスタ!$E$5:$E$204,MATCH(C504,取引先マスタ!$A$5:$A$204,0))="",INDEX(取引先マスタ!$F$5:$F$204,MATCH(C504,取引先マスタ!$A$5:$A$204,0))=""),"",DATE(YEAR(B504),MONTH(B504)+INDEX(取引先マスタ!$E$5:$E$204,MATCH(C504,取引先マスタ!$A$5:$A$204,0)),MIN(INDEX(取引先マスタ!$F$5:$F$204,MATCH(C504,取引先マスタ!$A$5:$A$204,0)),DAY(EOMONTH(B504,INDEX(取引先マスタ!$E$5:$E$204,MATCH(C504,取引先マスタ!$A$5:$A$204,0))))))),"")) | I504: =IF(H504<>"",H504,G504) | M504: =IF(A504="","",SUMIF(入金明細!$F$5:$F$1004,A504,入金明細!$E$5:$E$1004)) | N504: =IF(OR(A504="",N(M504)=0),"",SUMPRODUCT(MAX((入金明細!$F$5:$F$1004=A504)*入金明細!$B$5:$B$1004))) | P504: =IF(OR(A504="",F504=""),"",F504-N(M504)-N(O504)) | R504: =IF(A504="","",IF(Q504="取消","取消",IF(T504<>"","要入力",IF(K504="","未送付",IF(P504=0,"入金済",IF(P504<0,"過入金",IF(設定!$C$5>I504,IF(N(M504)>0,"一部入金・超過","期日超過"),IF(N(M504)>0,"一部入金",IF(I504-設定!$C$5<=設定!$C$6,"期日間近","入金待ち"))))))))) | S504: =IF(OR(R504="期日超過",R504="一部入金・超過"),設定!$C$5-I504,"") | T504: =IF(A504="","",TRIM(IF(B504="","請求日 ","")&IF(C504="","取引先 ",IF(D504="コード誤り","取引先コード誤り ",""))&IF(E504="","件名 ","")&IF(F504="","請求額 ","")&IF(AND(F504<>"",I504=""),"入金期日(マスタの支払条件が未登録) ","")&IF(J504="","送付方法 ","")&IF(AND(K504<>"",L504=""),"送付者 ","")&IF(AND(K504<>"",N(K504)>設定!$C$5),"送付日が未来の日付 ","")&IF(AND(K504<>"",N(M504)>0,N(P504)<=0,U504=""),"消込確認者 ","")))

Sheet 入金明細
A1: 入金明細
A2: 通帳・ネットバンキングの入金を全件、1入金1行で転記し「消込先請求番号」を入力。1つの入金で複数の請求分が払われた場合は行を分けて金額を按分。
A4: No | B4: 入金日 | C4: 入金口座 | D4: 振込名義 | E4: 入金額 | F4: 消込先請求番号 | G4: 取引先コード | H4: 取引先名(請求) | I4: 請求額 | J4: 消込状態 | K4: 記帳者 | L4: 備考
A5: =IF(COUNTA(B5,D5,E5,F5)=0,"",ROW()-4) -> 1 | B5: 46265 | C5: 平塚信用金庫 | D5: カ)サンプルシヨウジ | E5: 110000 | F5: INV-00001 | G5: =IF(F5="","",IFERROR(INDEX(請求台帳!$C$5:$C$504,MATCH(F5,請求台帳!$A$5:$A$504,0)),"")) -> C001 | H5: =IF(F5="","",IFERROR(INDEX(請求台帳!$D$5:$D$504,MATCH(F5,請求台帳!$A$5:$A$504,0)),"")) -> 株式会社サンプル商事 | I5: =IF(F5="","",IFERROR(INDEX(請求台帳!$F$5:$F$504,MATCH(F5,請求台帳!$A$5:$A$504,0)),"")) -> 110000 | J5: =IF(COUNTA(B5,D5,E5,F5)=0,"",IF(OR(B5="",E5=""),"要入力",IF(N(B5)>設定!$C$5,"日付誤り",IF(F5="","未消込",IF(ISNA(MATCH(F5,請求台帳!$A$5:$A$504,0)),"番号誤り",IF(INDEX(請求台帳!$Q$5:$Q$504,MATCH(F5,請求台帳!$A$5:$A$504,0))="取消","取消請求へ消込","消込済")))))) -> 消込済 | K5: 佐々木 | L5: SAMPLE
A6: =IF(COUNTA(B6,D6,E6,F6)=0,"",ROW()-4) -> 2 | B6: 46275 | C6: 平塚信用金庫 | D6: ユ)テストコウギヨウ | E6: 274560 | F6: INV-00002 | G6: =IF(F6="","",IFERROR(INDEX(請求台帳!$C$5:$C$504,MATCH(F6,請求台帳!$A$5:$A$504,0)),"")) -> C002 | H6: =IF(F6="","",IFERROR(INDEX(請求台帳!$D$5:$D$504,MATCH(F6,請求台帳!$A$5:$A$504,0)),"")) -> 有限会社テスト工業 | I6: =IF(F6="","",IFERROR(INDEX(請求台帳!$F$5:$F$504,MATCH(F6,請求台帳!$A$5:$A$504,0)),"")) -> 275000 | J6: =IF(COUNTA(B6,D6,E6,F6)=0,"",IF(OR(B6="",E6=""),"要入力",IF(N(B6)>設定!$C$5,"日付誤り",IF(F6="","未消込",IF(ISNA(MATCH(F6,請求台帳!$A$5:$A$504,0)),"番号誤り",IF(INDEX(請求台帳!$Q$5:$Q$504,MATCH(F6,請求台帳!$A$5:$A$504,0))="取消","取消請求へ消込","消込済")))))) -> 消込済 | K6: 佐々木 | L6: SAMPLE: 振込手数料440円差引
A7: =IF(COUNTA(B7,D7,E7,F7)=0,"",ROW()-4) -> 3 | B7: 46293 | C7: 平塚信用金庫 | D7: ド)デモ | E7: 50000 | F7: INV-00004 | G7: =IF(F7="","",IFERROR(INDEX(請求台帳!$C$5:$C$504,MATCH(F7,請求台帳!$A$5:$A$504,0)),"")) -> C003 | H7: =IF(F7="","",IFERROR(INDEX(請求台帳!$D$5:$D$504,MATCH(F7,請求台帳!$A$5:$A$504,0)),"")) -> 合同会社デモ | I7: =IF(F7="","",IFERROR(INDEX(請求台帳!$F$5:$F$504,MATCH(F7,請求台帳!$A$5:$A$504,0)),"")) -> 88000 | J7: =IF(COUNTA(B7,D7,E7,F7)=0,"",IF(OR(B7="",E7=""),"要入力",IF(N(B7)>設定!$C$5,"日付誤り",IF(F7="","未消込",IF(ISNA(MATCH(F7,請求台帳!$A$5:$A$504,0)),"番号誤り",IF(INDEX(請求台帳!$Q$5:$Q$504,MATCH(F7,請求台帳!$A$5:$A$504,0))="取消","取消請求へ消込","消込済")))))) -> 消込済 | K7: 佐々木 | L7: SAMPLE: 一部入金
A8: =IF(COUNTA(B8,D8,E8,F8)=0,"",ROW()-4) -> 4 | B8: 46293 | C8: 平塚信用金庫 | D8: ヤマダ タロウ | E8: 5500 | G8: =IF(F8="","",IFERROR(INDEX(請求台帳!$C$5:$C$504,MATCH(F8,請求台帳!$A$5:$A$504,0)),"")) | H8: =IF(F8="","",IFERROR(INDEX(請求台帳!$D$5:$D$504,MATCH(F8,請求台帳!$A$5:$A$504,0)),"")) | I8: =IF(F8="","",IFERROR(INDEX(請求台帳!$F$5:$F$504,MATCH(F8,請求台帳!$A$5:$A$504,0)),"")) | J8: =IF(COUNTA(B8,D8,E8,F8)=0,"",IF(OR(B8="",E8=""),"要入力",IF(N(B8)>設定!$C$5,"日付誤り",IF(F8="","未消込",IF(ISNA(MATCH(F8,請求台帳!$A$5:$A$504,0)),"番号誤り",IF(INDEX(請求台帳!$Q$5:$Q$504,MATCH(F8,請求台帳!$A$5:$A$504,0))="取消","取消請求へ消込","消込済")))))) -> 未消込 | K8: 佐々木 | L8: SAMPLE: 不明入金(未消込)
A9: =IF(COUNTA(B9,D9,E9,F9)=0,"",ROW()-4) | G9: =IF(F9="","",IFERROR(INDEX(請求台帳!$C$5:$C$504,MATCH(F9,請求台帳!$A$5:$A$504,0)),"")) | H9: =IF(F9="","",IFERROR(INDEX(請求台帳!$D$5:$D$504,MATCH(F9,請求台帳!$A$5:$A$504,0)),"")) | I9: =IF(F9="","",IFERROR(INDEX(請求台帳!$F$5:$F$504,MATCH(F9,請求台帳!$A$5:$A$504,0)),"")) | J9: =IF(COUNTA(B9,D9,E9,F9)=0,"",IF(OR(B9="",E9=""),"要入力",IF(N(B9)>設定!$C$5,"日付誤り",IF(F9="","未消込",IF(ISNA(MATCH(F9,請求台帳!$A$5:$A$504,0)),"番号誤り",IF(INDEX(請求台帳!$Q$5:$Q$504,MATCH(F9,請求台帳!$A$5:$A$504,0))="取消","取消請求へ消込","消込済"))))))
A10: =IF(COUNTA(B10,D10,E10,F10)=0,"",ROW()-4) | G10: =IF(F10="","",IFERROR(INDEX(請求台帳!$C$5:$C$504,MATCH(F10,請求台帳!$A$5:$A$504,0)),"")) | H10: =IF(F10="","",IFERROR(INDEX(請求台帳!$D$5:$D$504,MATCH(F10,請求台帳!$A$5:$A$504,0)),"")) | I10: =IF(F10="","",IFERROR(INDEX(請求台帳!$F$5:$F$504,MATCH(F10,請求台帳!$A$5:$A$504,0)),"")) | J10: =IF(COUNTA(B10,D10,E10,F10)=0,"",IF(OR(B10="",E10=""),"要入力",IF(N(B10)>設定!$C$5,"日付誤り",IF(F10="","未消込",IF(ISNA(MATCH(F10,請求台帳!$A$5:$A$504,0)),"番号誤り",IF(INDEX(請求台帳!$Q$5:$Q$504,MATCH(F10,請求台帳!$A$5:$A$504,0))="取消","取消請求へ消込","消込済"))))))
A11: =IF(COUNTA(B11,D11,E11,F11)=0,"",ROW()-4) | G11: =IF(F11="","",IFERROR(INDEX(請求台帳!$C$5:$C$504,MATCH(F11,請求台帳!$A$5:$A$504,0)),"")) | H11: =IF(F11="","",IFERROR(INDEX(請求台帳!$D$5:$D$504,MATCH(F11,請求台帳!$A$5:$A$504,0)),"")) | I11: =IF(F11="","",IFERROR(INDEX(請求台帳!$F$5:$F$504,MATCH(F11,請求台帳!$A$5:$A$504,0)),"")) | J11: =IF(COUNTA(B11,D11,E11,F11)=0,"",IF(OR(B11="",E11=""),"要入力",IF(N(B11)>設定!$C$5,"日付誤り",IF(F11="","未消込",IF(ISNA(MATCH(F11,請求台帳!$A$5:$A$504,0)),"番号誤り",IF(INDEX(請求台帳!$Q$5:$Q$504,MATCH(F11,請求台帳!$A$5:$A$504,0))="取消","取消請求へ消込","消込済"))))))
A12: =IF(COUNTA(B12,D12,E12,F12)=0,"",ROW()-4) | G12: =IF(F12="","",IFERROR(INDEX(請求台帳!$C$5:$C$504,MATCH(F12,請求台帳!$A$5:$A$504,0)),"")) | H12: =IF(F12="","",IFERROR(INDEX(請求台帳!$D$5:$D$504,MATCH(F12,請求台帳!$A$5:$A$504,0)),"")) | I12: =IF(F12="","",IFERROR(INDEX(請求台帳!$F$5:$F$504,MATCH(F12,請求台帳!$A$5:$A$504,0)),"")) | J12: =IF(COUNTA(B12,D12,E12,F12)=0,"",IF(OR(B12="",E12=""),"要入力",IF(N(B12)>設定!$C$5,"日付誤り",IF(F12="","未消込",IF(ISNA(MATCH(F12,請求台帳!$A$5:$A$504,0)),"番号誤り",IF(INDEX(請求台帳!$Q$5:$Q$504,MATCH(F12,請求台帳!$A$5:$A$504,0))="取消","取消請求へ消込","消込済"))))))
A13: =IF(COUNTA(B13,D13,E13,F13)=0,"",ROW()-4) | G13: =IF(F13="","",IFERROR(INDEX(請求台帳!$C$5:$C$504,MATCH(F13,請求台帳!$A$5:$A$504,0)),"")) | H13: =IF(F13="","",IFERROR(INDEX(請求台帳!$D$5:$D$504,MATCH(F13,請求台帳!$A$5:$A$504,0)),"")) | I13: =IF(F13="","",IFERROR(INDEX(請求台帳!$F$5:$F$504,MATCH(F13,請求台帳!$A$5:$A$504,0)),"")) | J13: =IF(COUNTA(B13,D13,E13,F13)=0,"",IF(OR(B13="",E13=""),"要入力",IF(N(B13)>設定!$C$5,"日付誤り",IF(F13="","未消込",IF(ISNA(MATCH(F13,請求台帳!$A$5:$A$504,0)),"番号誤り",IF(INDEX(請求台帳!$Q$5:$Q$504,MATCH(F13,請求台帳!$A$5:$A$504,0))="取消","取消請求へ消込","消込済"))))))
A14: =IF(COUNTA(B14,D14,E14,F14)=0,"",ROW()-4) | G14: =IF(F14="","",IFERROR(INDEX(請求台帳!$C$5:$C$504,MATCH(F14,請求台帳!$A$5:$A$504,0)),"")) | H14: =IF(F14="","",IFERROR(INDEX(請求台帳!$D$5:$D$504,MATCH(F14,請求台帳!$A$5:$A$504,0)),"")) | I14: =IF(F14="","",IFERROR(INDEX(請求台帳!$F$5:$F$504,MATCH(F14,請求台帳!$A$5:$A$504,0)),"")) | J14: =IF(COUNTA(B14,D14,E14,F14)=0,"",IF(OR(B14="",E14=""),"要入力",IF(N(B14)>設定!$C$5,"日付誤り",IF(F14="","未消込",IF(ISNA(MATCH(F14,請求台帳!$A$5:$A$504,0)),"番号誤り",IF(INDEX(請求台帳!$Q$5:$Q$504,MATCH(F14,請求台帳!$A$5:$A$504,0))="取消","取消請求へ消込","消込済"))))))
A15: =IF(COUNTA(B15,D15,E15,F15)=0,"",ROW()-4) | G15: =IF(F15="","",IFERROR(INDEX(請求台帳!$C$5:$C$504,MATCH(F15,請求台帳!$A$5:$A$504,0)),"")) | H15: =IF(F15="","",IFERROR(INDEX(請求台帳!$D$5:$D$504,MATCH(F15,請求台帳!$A$5:$A$504,0)),"")) | I15: =IF(F15="","",IFERROR(INDEX(請求台帳!$F$5:$F$504,MATCH(F15,請求台帳!$A$5:$A$504,0)),"")) | J15: =IF(COUNTA(B15,D15,E15,F15)=0,"",IF(OR(B15="",E15=""),"要入力",IF(N(B15)>設定!$C$5,"日付誤り",IF(F15="","未消込",IF(ISNA(MATCH(F15,請求台帳!$A$5:$A$504,0)),"番号誤り",IF(INDEX(請求台帳!$Q$5:$Q$504,MATCH(F15,請求台帳!$A$5:$A$504,0))="取消","取消請求へ消込","消込済"))))))
A16: =IF(COUNTA(B16,D16,E16,F16)=0,"",ROW()-4) | G16: =IF(F16="","",IFERROR(INDEX(請求台帳!$C$5:$C$504,MATCH(F16,請求台帳!$A$5:$A$504,0)),"")) | H16: =IF(F16="","",IFERROR(INDEX(請求台帳!$D$5:$D$504,MATCH(F16,請求台帳!$A$5:$A$504,0)),"")) | I16: =IF(F16="","",IFERROR(INDEX(請求台帳!$F$5:$F$504,MATCH(F16,請求台帳!$A$5:$A$504,0)),"")) | J16: =IF(COUNTA(B16,D16,E16,F16)=0,"",IF(OR(B16="",E16=""),"要入力",IF(N(B16)>設定!$C$5,"日付誤り",IF(F16="","未消込",IF(ISNA(MATCH(F16,請求台帳!$A$5:$A$504,0)),"番号誤り",IF(INDEX(請求台帳!$Q$5:$Q$504,MATCH(F16,請求台帳!$A$5:$A$504,0))="取消","取消請求へ消込","消込済"))))))
A17: =IF(COUNTA(B17,D17,E17,F17)=0,"",ROW()-4) | G17: =IF(F17="","",IFERROR(INDEX(請求台帳!$C$5:$C$504,MATCH(F17,請求台帳!$A$5:$A$504,0)),"")) | H17: =IF(F17="","",IFERROR(INDEX(請求台帳!$D$5:$D$504,MATCH(F17,請求台帳!$A$5:$A$504,0)),"")) | I17: =IF(F17="","",IFERROR(INDEX(請求台帳!$F$5:$F$504,MATCH(F17,請求台帳!$A$5:$A$504,0)),"")) | J17: =IF(COUNTA(B17,D17,E17,F17)=0,"",IF(OR(B17="",E17=""),"要入力",IF(N(B17)>設定!$C$5,"日付誤り",IF(F17="","未消込",IF(ISNA(MATCH(F17,請求台帳!$A$5:$A$504,0)),"番号誤り",IF(INDEX(請求台帳!$Q$5:$Q$504,MATCH(F17,請求台帳!$A$5:$A$504,0))="取消","取消請求へ消込","消込済"))))))
A18: =IF(COUNTA(B18,D18,E18,F18)=0,"",ROW()-4) | G18: =IF(F18="","",IFERROR(INDEX(請求台帳!$C$5:$C$504,MATCH(F18,請求台帳!$A$5:$A$504,0)),"")) | H18: =IF(F18="","",IFERROR(INDEX(請求台帳!$D$5:$D$504,MATCH(F18,請求台帳!$A$5:$A$504,0)),"")) | I18: =IF(F18="","",IFERROR(INDEX(請求台帳!$F$5:$F$504,MATCH(F18,請求台帳!$A$5:$A$504,0)),"")) | J18: =IF(COUNTA(B18,D18,E18,F18)=0,"",IF(OR(B18="",E18=""),"要入力",IF(N(B18)>設定!$C$5,"日付誤り",IF(F18="","未消込",IF(ISNA(MATCH(F18,請求台帳!$A$5:$A$504,0)),"番号誤り",IF(INDEX(請求台帳!$Q$5:$Q$504,MATCH(F18,請求台帳!$A$5:$A$504,0))="取消","取消請求へ消込","消込済"))))))
A19: =IF(COUNTA(B19,D19,E19,F19)=0,"",ROW()-4) | G19: =IF(F19="","",IFERROR(INDEX(請求台帳!$C$5:$C$504,MATCH(F19,請求台帳!$A$5:$A$504,0)),"")) | H19: =IF(F19="","",IFERROR(INDEX(請求台帳!$D$5:$D$504,MATCH(F19,請求台帳!$A$5:$A$504,0)),"")) | I19: =IF(F19="","",IFERROR(INDEX(請求台帳!$F$5:$F$504,MATCH(F19,請求台帳!$A$5:$A$504,0)),"")) | J19: =IF(COUNTA(B19,D19,E19,F19)=0,"",IF(OR(B19="",E19=""),"要入力",IF(N(B19)>設定!$C$5,"日付誤り",IF(F19="","未消込",IF(ISNA(MATCH(F19,請求台帳!$A$5:$A$504,0)),"番号誤り",IF(INDEX(請求台帳!$Q$5:$Q$504,MATCH(F19,請求台帳!$A$5:$A$504,0))="取消","取消請求へ消込","消込済"))))))
A20: =IF(COUNTA(B20,D20,E20,F20)=0,"",ROW()-4) | G20: =IF(F20="","",IFERROR(INDEX(請求台帳!$C$5:$C$504,MATCH(F20,請求台帳!$A$5:$A$504,0)),"")) | H20: =IF(F20="","",IFERROR(INDEX(請求台帳!$D$5:$D$504,MATCH(F20,請求台帳!$A$5:$A$504,0)),"")) | I20: =IF(F20="","",IFERROR(INDEX(請求台帳!$F$5:$F$504,MATCH(F20,請求台帳!$A$5:$A$504,0)),"")) | J20: =IF(COUNTA(B20,D20,E20,F20)=0,"",IF(OR(B20="",E20=""),"要入力",IF(N(B20)>設定!$C$5,"日付誤り",IF(F20="","未消込",IF(ISNA(MATCH(F20,請求台帳!$A$5:$A$504,0)),"番号誤り",IF(INDEX(請求台帳!$Q$5:$Q$504,MATCH(F20,請求台帳!$A$5:$A$504,0))="取消","取消請求へ消込","消込済"))))))
... A1004: =IF(COUNTA(B1004,D1004,E1004,F1004)=0,"",ROW()-4) | G1004: =IF(F1004="","",IFERROR(INDEX(請求台帳!$C$5:$C$504,MATCH(F1004,請求台帳!$A$5:$A$504,0)),"")) | H1004: =IF(F1004="","",IFERROR(INDEX(請求台帳!$D$5:$D$504,MATCH(F1004,請求台帳!$A$5:$A$504,0)),"")) | I1004: =IF(F1004="","",IFERROR(INDEX(請求台帳!$F$5:$F$504,MATCH(F1004,請求台帳!$A$5:$A$504,0)),"")) | J1004: =IF(COUNTA(B1004,D1004,E1004,F1004)=0,"",IF(OR(B1004="",E1004=""),"要入力",IF(N(B1004)>設定!$C$5,"日付誤り",IF(F1004="","未消込",IF(ISNA(MATCH(F1004,請求台帳!$A$5:$A$504,0)),"番号誤り",IF(INDEX(請求台帳!$Q$5:$Q$504,MATCH(F1004,請求台帳!$A$5:$A$504,0))="取消","取消請求へ消込","消込済"))))))

Sheet 取引先別残高
A1: 取引先別残高
A2: 取引先マスタの順に自動表示(入力不要)。超過日数別の残高と、毎月請求先の対象月請求漏れ候補を表示します。
C3: 合計 | D3: =D205 -> 349300 | E3: =E205 -> 184300 | F3: =F205 -> 0 | G3: =G205 -> 165000 | H3: =H205 -> 0
A4: 取引先コード | B4: 取引先名 | C4: 担当者 | D4: 未回収残高 | E4: 期日内 | F4: 超過 1〜30日 | G4: 超過 31〜60日 | H4: 超過 61日以上 | I4: 対象月の請求件数 | J4: 請求漏れ判定
A5: =IF(取引先マスタ!A5="","",取引先マスタ!A5) -> C001 | B5: =IF(A5="","",取引先マスタ!B5) -> 株式会社サンプル商事 | C5: =IF(A5="","",取引先マスタ!J5&"") -> 山田 | D5: =IF(A5="","",SUMIFS(請求台帳!$P$5:$P$504,請求台帳!$C$5:$C$504,A5,請求台帳!$Q$5:$Q$504,"<>取消")) -> 110000 | E5: =IF(A5="","",D5-SUM(F5:H5)) -> 110000 | F5: =IF(A5="","",SUMIFS(請求台帳!$P$5:$P$504,請求台帳!$C$5:$C$504,A5,請求台帳!$S$5:$S$504,">=1",請求台帳!$S$5:$S$504,"<=30")) -> 0 | G5: =IF(A5="","",SUMIFS(請求台帳!$P$5:$P$504,請求台帳!$C$5:$C$504,A5,請求台帳!$S$5:$S$504,">=31",請求台帳!$S$5:$S$504,"<=60")) -> 0 | H5: =IF(A5="","",SUMIFS(請求台帳!$P$5:$P$504,請求台帳!$C$5:$C$504,A5,請求台帳!$S$5:$S$504,">=61")) -> 0 | I5: =IF(A5="","",COUNTIFS(請求台帳!$C$5:$C$504,A5,請求台帳!$B$5:$B$504,">="&チェック!$C$4,請求台帳!$B$5:$B$504,"<="&EOMONTH(チェック!$C$4,0),請求台帳!$Q$5:$Q$504,"<>取消")) -> 0 | J5: =IF(A5="","",IF(AND(取引先マスタ!G5="有",I5=0),"請求漏れ候補","")) -> 請求漏れ候補
A6: =IF(取引先マスタ!A6="","",取引先マスタ!A6) -> C002 | B6: =IF(A6="","",取引先マスタ!B6) -> 有限会社テスト工業 | C6: =IF(A6="","",取引先マスタ!J6&"") -> 佐藤 | D6: =IF(A6="","",SUMIFS(請求台帳!$P$5:$P$504,請求台帳!$C$5:$C$504,A6,請求台帳!$Q$5:$Q$504,"<>取消")) -> 165000 | E6: =IF(A6="","",D6-SUM(F6:H6)) -> 0 | F6: =IF(A6="","",SUMIFS(請求台帳!$P$5:$P$504,請求台帳!$C$5:$C$504,A6,請求台帳!$S$5:$S$504,">=1",請求台帳!$S$5:$S$504,"<=30")) -> 0 | G6: =IF(A6="","",SUMIFS(請求台帳!$P$5:$P$504,請求台帳!$C$5:$C$504,A6,請求台帳!$S$5:$S$504,">=31",請求台帳!$S$5:$S$504,"<=60")) -> 165000 | H6: =IF(A6="","",SUMIFS(請求台帳!$P$5:$P$504,請求台帳!$C$5:$C$504,A6,請求台帳!$S$5:$S$504,">=61")) -> 0 | I6: =IF(A6="","",COUNTIFS(請求台帳!$C$5:$C$504,A6,請求台帳!$B$5:$B$504,">="&チェック!$C$4,請求台帳!$B$5:$B$504,"<="&EOMONTH(チェック!$C$4,0),請求台帳!$Q$5:$Q$504,"<>取消")) -> 0 | J6: =IF(A6="","",IF(AND(取引先マスタ!G6="有",I6=0),"請求漏れ候補",""))
A7: =IF(取引先マスタ!A7="","",取引先マスタ!A7) -> C003 | B7: =IF(A7="","",取引先マスタ!B7) -> 合同会社デモ | C7: =IF(A7="","",取引先マスタ!J7&"") -> 山田 | D7: =IF(A7="","",SUMIFS(請求台帳!$P$5:$P$504,請求台帳!$C$5:$C$504,A7,請求台帳!$Q$5:$Q$504,"<>取消")) -> 74300 | E7: =IF(A7="","",D7-SUM(F7:H7)) -> 74300 | F7: =IF(A7="","",SUMIFS(請求台帳!$P$5:$P$504,請求台帳!$C$5:$C$504,A7,請求台帳!$S$5:$S$504,">=1",請求台帳!$S$5:$S$504,"<=30")) -> 0 | G7: =IF(A7="","",SUMIFS(請求台帳!$P$5:$P$504,請求台帳!$C$5:$C$504,A7,請求台帳!$S$5:$S$504,">=31",請求台帳!$S$5:$S$504,"<=60")) -> 0 | H7: =IF(A7="","",SUMIFS(請求台帳!$P$5:$P$504,請求台帳!$C$5:$C$504,A7,請求台帳!$S$5:$S$504,">=61")) -> 0 | I7: =IF(A7="","",COUNTIFS(請求台帳!$C$5:$C$504,A7,請求台帳!$B$5:$B$504,">="&チェック!$C$4,請求台帳!$B$5:$B$504,"<="&EOMONTH(チェック!$C$4,0),請求台帳!$Q$5:$Q$504,"<>取消")) -> 1 | J7: =IF(A7="","",IF(AND(取引先マスタ!G7="有",I7=0),"請求漏れ候補",""))
A8: =IF(取引先マスタ!A8="","",取引先マスタ!A8) | B8: =IF(A8="","",取引先マスタ!B8) | C8: =IF(A8="","",取引先マスタ!J8&"") | D8: =IF(A8="","",SUMIFS(請求台帳!$P$5:$P$504,請求台帳!$C$5:$C$504,A8,請求台帳!$Q$5:$Q$504,"<>取消")) | E8: =IF(A8="","",D8-SUM(F8:H8)) | F8: =IF(A8="","",SUMIFS(請求台帳!$P$5:$P$504,請求台帳!$C$5:$C$504,A8,請求台帳!$S$5:$S$504,">=1",請求台帳!$S$5:$S$504,"<=30")) | G8: =IF(A8="","",SUMIFS(請求台帳!$P$5:$P$504,請求台帳!$C$5:$C$504,A8,請求台帳!$S$5:$S$504,">=31",請求台帳!$S$5:$S$504,"<=60")) | H8: =IF(A8="","",SUMIFS(請求台帳!$P$5:$P$504,請求台帳!$C$5:$C$504,A8,請求台帳!$S$5:$S$504,">=61")) | I8: =IF(A8="","",COUNTIFS(請求台帳!$C$5:$C$504,A8,請求台帳!$B$5:$B$504,">="&チェック!$C$4,請求台帳!$B$5:$B$504,"<="&EOMONTH(チェック!$C$4,0),請求台帳!$Q$5:$Q$504,"<>取消")) | J8: =IF(A8="","",IF(AND(取引先マスタ!G8="有",I8=0),"請求漏れ候補",""))
A9: =IF(取引先マスタ!A9="","",取引先マスタ!A9) | B9: =IF(A9="","",取引先マスタ!B9) | C9: =IF(A9="","",取引先マスタ!J9&"") | D9: =IF(A9="","",SUMIFS(請求台帳!$P$5:$P$504,請求台帳!$C$5:$C$504,A9,請求台帳!$Q$5:$Q$504,"<>取消")) | E9: =IF(A9="","",D9-SUM(F9:H9)) | F9: =IF(A9="","",SUMIFS(請求台帳!$P$5:$P$504,請求台帳!$C$5:$C$504,A9,請求台帳!$S$5:$S$504,">=1",請求台帳!$S$5:$S$504,"<=30")) | G9: =IF(A9="","",SUMIFS(請求台帳!$P$5:$P$504,請求台帳!$C$5:$C$504,A9,請求台帳!$S$5:$S$504,">=31",請求台帳!$S$5:$S$504,"<=60")) | H9: =IF(A9="","",SUMIFS(請求台帳!$P$5:$P$504,請求台帳!$C$5:$C$504,A9,請求台帳!$S$5:$S$504,">=61")) | I9: =IF(A9="","",COUNTIFS(請求台帳!$C$5:$C$504,A9,請求台帳!$B$5:$B$504,">="&チェック!$C$4,請求台帳!$B$5:$B$504,"<="&EOMONTH(チェック!$C$4,0),請求台帳!$Q$5:$Q$504,"<>取消")) | J9: =IF(A9="","",IF(AND(取引先マスタ!G9="有",I9=0),"請求漏れ候補",""))
A10: =IF(取引先マスタ!A10="","",取引先マスタ!A10) | B10: =IF(A10="","",取引先マスタ!B10) | C10: =IF(A10="","",取引先マスタ!J10&"") | D10: =IF(A10="","",SUMIFS(請求台帳!$P$5:$P$504,請求台帳!$C$5:$C$504,A10,請求台帳!$Q$5:$Q$504,"<>取消")) | E10: =IF(A10="","",D10-SUM(F10:H10)) | F10: =IF(A10="","",SUMIFS(請求台帳!$P$5:$P$504,請求台帳!$C$5:$C$504,A10,請求台帳!$S$5:$S$504,">=1",請求台帳!$S$5:$S$504,"<=30")) | G10: =IF(A10="","",SUMIFS(請求台帳!$P$5:$P$504,請求台帳!$C$5:$C$504,A10,請求台帳!$S$5:$S$504,">=31",請求台帳!$S$5:$S$504,"<=60")) | H10: =IF(A10="","",SUMIFS(請求台帳!$P$5:$P$504,請求台帳!$C$5:$C$504,A10,請求台帳!$S$5:$S$504,">=61")) | I10: =IF(A10="","",COUNTIFS(請求台帳!$C$5:$C$504,A10,請求台帳!$B$5:$B$504,">="&チェック!$C$4,請求台帳!$B$5:$B$504,"<="&EOMONTH(チェック!$C$4,0),請求台帳!$Q$5:$Q$504,"<>取消")) | J10: =IF(A10="","",IF(AND(取引先マスタ!G10="有",I10=0),"請求漏れ候補",""))
A11: =IF(取引先マスタ!A11="","",取引先マスタ!A11) | B11: =IF(A11="","",取引先マスタ!B11) | C11: =IF(A11="","",取引先マスタ!J11&"") | D11: =IF(A11="","",SUMIFS(請求台帳!$P$5:$P$504,請求台帳!$C$5:$C$504,A11,請求台帳!$Q$5:$Q$504,"<>取消")) | E11: =IF(A11="","",D11-SUM(F11:H11)) | F11: =IF(A11="","",SUMIFS(請求台帳!$P$5:$P$504,請求台帳!$C$5:$C$504,A11,請求台帳!$S$5:$S$504,">=1",請求台帳!$S$5:$S$504,"<=30")) | G11: =IF(A11="","",SUMIFS(請求台帳!$P$5:$P$504,請求台帳!$C$5:$C$504,A11,請求台帳!$S$5:$S$504,">=31",請求台帳!$S$5:$S$504,"<=60")) | H11: =IF(A11="","",SUMIFS(請求台帳!$P$5:$P$504,請求台帳!$C$5:$C$504,A11,請求台帳!$S$5:$S$504,">=61")) | I11: =IF(A11="","",COUNTIFS(請求台帳!$C$5:$C$504,A11,請求台帳!$B$5:$B$504,">="&チェック!$C$4,請求台帳!$B$5:$B$504,"<="&EOMONTH(チェック!$C$4,0),請求台帳!$Q$5:$Q$504,"<>取消")) | J11: =IF(A11="","",IF(AND(取引先マスタ!G11="有",I11=0),"請求漏れ候補",""))
A12: =IF(取引先マスタ!A12="","",取引先マスタ!A12) | B12: =IF(A12="","",取引先マスタ!B12) | C12: =IF(A12="","",取引先マスタ!J12&"") | D12: =IF(A12="","",SUMIFS(請求台帳!$P$5:$P$504,請求台帳!$C$5:$C$504,A12,請求台帳!$Q$5:$Q$504,"<>取消")) | E12: =IF(A12="","",D12-SUM(F12:H12)) | F12: =IF(A12="","",SUMIFS(請求台帳!$P$5:$P$504,請求台帳!$C$5:$C$504,A12,請求台帳!$S$5:$S$504,">=1",請求台帳!$S$5:$S$504,"<=30")) | G12: =IF(A12="","",SUMIFS(請求台帳!$P$5:$P$504,請求台帳!$C$5:$C$504,A12,請求台帳!$S$5:$S$504,">=31",請求台帳!$S$5:$S$504,"<=60")) | H12: =IF(A12="","",SUMIFS(請求台帳!$P$5:$P$504,請求台帳!$C$5:$C$504,A12,請求台帳!$S$5:$S$504,">=61")) | I12: =IF(A12="","",COUNTIFS(請求台帳!$C$5:$C$504,A12,請求台帳!$B$5:$B$504,">="&チェック!$C$4,請求台帳!$B$5:$B$504,"<="&EOMONTH(チェック!$C$4,0),請求台帳!$Q$5:$Q$504,"<>取消")) | J12: =IF(A12="","",IF(AND(取引先マスタ!G12="有",I12=0),"請求漏れ候補",""))
A13: =IF(取引先マスタ!A13="","",取引先マスタ!A13) | B13: =IF(A13="","",取引先マスタ!B13) | C13: =IF(A13="","",取引先マスタ!J13&"") | D13: =IF(A13="","",SUMIFS(請求台帳!$P$5:$P$504,請求台帳!$C$5:$C$504,A13,請求台帳!$Q$5:$Q$504,"<>取消")) | E13: =IF(A13="","",D13-SUM(F13:H13)) | F13: =IF(A13="","",SUMIFS(請求台帳!$P$5:$P$504,請求台帳!$C$5:$C$504,A13,請求台帳!$S$5:$S$504,">=1",請求台帳!$S$5:$S$504,"<=30")) | G13: =IF(A13="","",SUMIFS(請求台帳!$P$5:$P$504,請求台帳!$C$5:$C$504,A13,請求台帳!$S$5:$S$504,">=31",請求台帳!$S$5:$S$504,"<=60")) | H13: =IF(A13="","",SUMIFS(請求台帳!$P$5:$P$504,請求台帳!$C$5:$C$504,A13,請求台帳!$S$5:$S$504,">=61")) | I13: =IF(A13="","",COUNTIFS(請求台帳!$C$5:$C$504,A13,請求台帳!$B$5:$B$504,">="&チェック!$C$4,請求台帳!$B$5:$B$504,"<="&EOMONTH(チェック!$C$4,0),請求台帳!$Q$5:$Q$504,"<>取消")) | J13: =IF(A13="","",IF(AND(取引先マスタ!G13="有",I13=0),"請求漏れ候補",""))
A14: =IF(取引先マスタ!A14="","",取引先マスタ!A14) | B14: =IF(A14="","",取引先マスタ!B14) | C14: =IF(A14="","",取引先マスタ!J14&"") | D14: =IF(A14="","",SUMIFS(請求台帳!$P$5:$P$504,請求台帳!$C$5:$C$504,A14,請求台帳!$Q$5:$Q$504,"<>取消")) | E14: =IF(A14="","",D14-SUM(F14:H14)) | F14: =IF(A14="","",SUMIFS(請求台帳!$P$5:$P$504,請求台帳!$C$5:$C$504,A14,請求台帳!$S$5:$S$504,">=1",請求台帳!$S$5:$S$504,"<=30")) | G14: =IF(A14="","",SUMIFS(請求台帳!$P$5:$P$504,請求台帳!$C$5:$C$504,A14,請求台帳!$S$5:$S$504,">=31",請求台帳!$S$5:$S$504,"<=60")) | H14: =IF(A14="","",SUMIFS(請求台帳!$P$5:$P$504,請求台帳!$C$5:$C$504,A14,請求台帳!$S$5:$S$504,">=61")) | I14: =IF(A14="","",COUNTIFS(請求台帳!$C$5:$C$504,A14,請求台帳!$B$5:$B$504,">="&チェック!$C$4,請求台帳!$B$5:$B$504,"<="&EOMONTH(チェック!$C$4,0),請求台帳!$Q$5:$Q$504,"<>取消")) | J14: =IF(A14="","",IF(AND(取引先マスタ!G14="有",I14=0),"請求漏れ候補",""))
A15: =IF(取引先マスタ!A15="","",取引先マスタ!A15) | B15: =IF(A15="","",取引先マスタ!B15) | C15: =IF(A15="","",取引先マスタ!J15&"") | D15: =IF(A15="","",SUMIFS(請求台帳!$P$5:$P$504,請求台帳!$C$5:$C$504,A15,請求台帳!$Q$5:$Q$504,"<>取消")) | E15: =IF(A15="","",D15-SUM(F15:H15)) | F15: =IF(A15="","",SUMIFS(請求台帳!$P$5:$P$504,請求台帳!$C$5:$C$504,A15,請求台帳!$S$5:$S$504,">=1",請求台帳!$S$5:$S$504,"<=30")) | G15: =IF(A15="","",SUMIFS(請求台帳!$P$5:$P$504,請求台帳!$C$5:$C$504,A15,請求台帳!$S$5:$S$504,">=31",請求台帳!$S$5:$S$504,"<=60")) | H15: =IF(A15="","",SUMIFS(請求台帳!$P$5:$P$504,請求台帳!$C$5:$C$504,A15,請求台帳!$S$5:$S$504,">=61")) | I15: =IF(A15="","",COUNTIFS(請求台帳!$C$5:$C$504,A15,請求台帳!$B$5:$B$504,">="&チェック!$C$4,請求台帳!$B$5:$B$504,"<="&EOMONTH(チェック!$C$4,0),請求台帳!$Q$5:$Q$504,"<>取消")) | J15: =IF(A15="","",IF(AND(取引先マスタ!G15="有",I15=0),"請求漏れ候補",""))
A16: =IF(取引先マスタ!A16="","",取引先マスタ!A16) | B16: =IF(A16="","",取引先マスタ!B16) | C16: =IF(A16="","",取引先マスタ!J16&"") | D16: =IF(A16="","",SUMIFS(請求台帳!$P$5:$P$504,請求台帳!$C$5:$C$504,A16,請求台帳!$Q$5:$Q$504,"<>取消")) | E16: =IF(A16="","",D16-SUM(F16:H16)) | F16: =IF(A16="","",SUMIFS(請求台帳!$P$5:$P$504,請求台帳!$C$5:$C$504,A16,請求台帳!$S$5:$S$504,">=1",請求台帳!$S$5:$S$504,"<=30")) | G16: =IF(A16="","",SUMIFS(請求台帳!$P$5:$P$504,請求台帳!$C$5:$C$504,A16,請求台帳!$S$5:$S$504,">=31",請求台帳!$S$5:$S$504,"<=60")) | H16: =IF(A16="","",SUMIFS(請求台帳!$P$5:$P$504,請求台帳!$C$5:$C$504,A16,請求台帳!$S$5:$S$504,">=61")) | I16: =IF(A16="","",COUNTIFS(請求台帳!$C$5:$C$504,A16,請求台帳!$B$5:$B$504,">="&チェック!$C$4,請求台帳!$B$5:$B$504,"<="&EOMONTH(チェック!$C$4,0),請求台帳!$Q$5:$Q$504,"<>取消")) | J16: =IF(A16="","",IF(AND(取引先マスタ!G16="有",I16=0),"請求漏れ候補",""))
... A204: =IF(取引先マスタ!A204="","",取引先マスタ!A204) | B204: =IF(A204="","",取引先マスタ!B204) | C204: =IF(A204="","",取引先マスタ!J204&"") | D204: =IF(A204="","",SUMIFS(請求台帳!$P$5:$P$504,請求台帳!$C$5:$C$504,A204,請求台帳!$Q$5:$Q$504,"<>取消")) | E204: =IF(A204="","",D204-SUM(F204:H204)) | F204: =IF(A204="","",SUMIFS(請求台帳!$P$5:$P$504,請求台帳!$C$5:$C$504,A204,請求台帳!$S$5:$S$504,">=1",請求台帳!$S$5:$S$504,"<=30")) | G204: =IF(A204="","",SUMIFS(請求台帳!$P$5:$P$504,請求台帳!$C$5:$C$504,A204,請求台帳!$S$5:$S$504,">=31",請求台帳!$S$5:$S$504,"<=60")) | H204: =IF(A204="","",SUMIFS(請求台帳!$P$5:$P$504,請求台帳!$C$5:$C$504,A204,請求台帳!$S$5:$S$504,">=61")) | I204: =IF(A204="","",COUNTIFS(請求台帳!$C$5:$C$504,A204,請求台帳!$B$5:$B$504,">="&チェック!$C$4,請求台帳!$B$5:$B$504,"<="&EOMONTH(チェック!$C$4,0),請求台帳!$Q$5:$Q$504,"<>取消")) | J204: =IF(A204="","",IF(AND(取引先マスタ!G204="有",I204=0),"請求漏れ候補",""))
B205: 合計 | D205: =SUM(D5:D204) -> 349300 | E205: =SUM(E5:E204) -> 184300 | F205: =SUM(F5:F204) -> 0 | G205: =SUM(G5:G204) -> 165000 | H205: =SUM(H5:H204) -> 0

Sheet 月別集計
A1: 月別集計(取引先×月)
A2: 請求額=請求日の月で集計(取消除く)、入金額=入金日の月で集計。収支一覧表の収入欄と同じ形です。期首は「設定」で変更。
A3: 取引先コード | B3: 取引先名 | C3: =DATE(YEAR(設定!$C$7),MONTH(設定!$C$7)+0,1) -> 45931 | E3: =DATE(YEAR(設定!$C$7),MONTH(設定!$C$7)+1,1) -> 45962 | G3: =DATE(YEAR(設定!$C$7),MONTH(設定!$C$7)+2,1) -> 45992 | I3: =DATE(YEAR(設定!$C$7),MONTH(設定!$C$7)+3,1) -> 46023 | K3: =DATE(YEAR(設定!$C$7),MONTH(設定!$C$7)+4,1) -> 46054 | M3: =DATE(YEAR(設定!$C$7),MONTH(設定!$C$7)+5,1) -> 46082 | O3: =DATE(YEAR(設定!$C$7),MONTH(設定!$C$7)+6,1) -> 46113 | Q3: =DATE(YEAR(設定!$C$7),MONTH(設定!$C$7)+7,1) -> 46143 | S3: =DATE(YEAR(設定!$C$7),MONTH(設定!$C$7)+8,1) -> 46174 | U3: =DATE(YEAR(設定!$C$7),MONTH(設定!$C$7)+9,1) -> 46204 | W3: =DATE(YEAR(設定!$C$7),MONTH(設定!$C$7)+10,1) -> 46235 | Y3: =DATE(YEAR(設定!$C$7),MONTH(設定!$C$7)+11,1) -> 46266 | AA3: 年間合計
C4: 請求額 | D4: 入金額 | E4: 請求額 | F4: 入金額 | G4: 請求額 | H4: 入金額 | I4: 請求額 | J4: 入金額 | K4: 請求額 | L4: 入金額 | M4: 請求額 | N4: 入金額 | O4: 請求額 | P4: 入金額 | Q4: 請求額 | R4: 入金額 | S4: 請求額 | T4: 入金額 | U4: 請求額 | V4: 入金額 | W4: 請求額 | X4: 入金額 | Y4: 請求額 | Z4: 入金額 | AA4: 請求額 | AB4: 入金額
A5: =IF(取引先マスタ!A5="","",取引先マスタ!A5) -> C001 | B5: =IF(A5="","",取引先マスタ!B5) -> 株式会社サンプル商事 | C5: =IF($A5="","",SUMIFS(請求台帳!$F$5:$F$504,請求台帳!$C$5:$C$504,$A5,請求台帳!$B$5:$B$504,">="&C$3,請求台帳!$B$5:$B$504,"<"&DATE(YEAR(C$3),MONTH(C$3)+1,1),請求台帳!$Q$5:$Q$504,"<>取消")) -> 0 | D5: =IF($A5="","",SUMIFS(入金明細!$E$5:$E$1004,入金明細!$G$5:$G$1004,$A5,入金明細!$B$5:$B$1004,">="&C$3,入金明細!$B$5:$B$1004,"<"&DATE(YEAR(C$3),MONTH(C$3)+1,1))) -> 0 | E5: =IF($A5="","",SUMIFS(請求台帳!$F$5:$F$504,請求台帳!$C$5:$C$504,$A5,請求台帳!$B$5:$B$504,">="&E$3,請求台帳!$B$5:$B$504,"<"&DATE(YEAR(E$3),MONTH(E$3)+1,1),請求台帳!$Q$5:$Q$504,"<>取消")) -> 0 | F5: =IF($A5="","",SUMIFS(入金明細!$E$5:$E$1004,入金明細!$G$5:$G$1004,$A5,入金明細!$B$5:$B$1004,">="&E$3,入金明細!$B$5:$B$1004,"<"&DATE(YEAR(E$3),MONTH(E$3)+1,1))) -> 0 | G5: =IF($A5="","",SUMIFS(請求台帳!$F$5:$F$504,請求台帳!$C$5:$C$504,$A5,請求台帳!$B$5:$B$504,">="&G$3,請求台帳!$B$5:$B$504,"<"&DATE(YEAR(G$3),MONTH(G$3)+1,1),請求台帳!$Q$5:$Q$504,"<>取消")) -> 0 | H5: =IF($A5="","",SUMIFS(入金明細!$E$5:$E$1004,入金明細!$G$5:$G$1004,$A5,入金明細!$B$5:$B$1004,">="&G$3,入金明細!$B$5:$B$1004,"<"&DATE(YEAR(G$3),MONTH(G$3)+1,1))) -> 0 | I5: =IF($A5="","",SUMIFS(請求台帳!$F$5:$F$504,請求台帳!$C$5:$C$504,$A5,請求台帳!$B$5:$B$504,">="&I$3,請求台帳!$B$5:$B$504,"<"&DATE(YEAR(I$3),MONTH(I$3)+1,1),請求台帳!$Q$5:$Q$504,"<>取消")) -> 0 | J5: =IF($A5="","",SUMIFS(入金明細!$E$5:$E$1004,入金明細!$G$5:$G$1004,$A5,入金明細!$B$5:$B$1004,">="&I$3,入金明細!$B$5:$B$1004,"<"&DATE(YEAR(I$3),MONTH(I$3)+1,1))) -> 0 | K5: =IF($A5="","",SUMIFS(請求台帳!$F$5:$F$504,請求台帳!$C$5:$C$504,$A5,請求台帳!$B$5:$B$504,">="&K$3,請求台帳!$B$5:$B$504,"<"&DATE(YEAR(K$3),MONTH(K$3)+1,1),請求台帳!$Q$5:$Q$504,"<>取消")) -> 0 | L5: =IF($A5="","",SUMIFS(入金明細!$E$5:$E$1004,入金明細!$G$5:$G$1004,$A5,入金明細!$B$5:$B$1004,">="&K$3,入金明細!$B$5:$B$1004,"<"&DATE(YEAR(K$3),MONTH(K$3)+1,1))) -> 0 | M5: =IF($A5="","",SUMIFS(請求台帳!$F$5:$F$504,請求台帳!$C$5:$C$504,$A5,請求台帳!$B$5:$B$504,">="&M$3,請求台帳!$B$5:$B$504,"<"&DATE(YEAR(M$3),MONTH(M$3)+1,1),請求台帳!$Q$5:$Q$504,"<>取消")) -> 0 | N5: =IF($A5="","",SUMIFS(入金明細!$E$5:$E$1004,入金明細!$G$5:$G$1004,$A5,入金明細!$B$5:$B$1004,">="&M$3,入金明細!$B$5:$B$1004,"<"&DATE(YEAR(M$3),MONTH(M$3)+1,1))) -> 0 | O5: =IF($A5="","",SUMIFS(請求台帳!$F$5:$F$504,請求台帳!$C$5:$C$504,$A5,請求台帳!$B$5:$B$504,">="&O$3,請求台帳!$B$5:$B$504,"<"&DATE(YEAR(O$3),MONTH(O$3)+1,1),請求台帳!$Q$5:$Q$504,"<>取消")) -> 0 | P5: =IF($A5="","",SUMIFS(入金明細!$E$5:$E$1004,入金明細!$G$5:$G$1004,$A5,入金明細!$B$5:$B$1004,">="&O$3,入金明細!$B$5:$B$1004,"<"&DATE(YEAR(O$3),MONTH(O$3)+1,1))) -> 0 | Q5: =IF($A5="","",SUMIFS(請求台帳!$F$5:$F$504,請求台帳!$C$5:$C$504,$A5,請求台帳!$B$5:$B$504,">="&Q$3,請求台帳!$B$5:$B$504,"<"&DATE(YEAR(Q$3),MONTH(Q$3)+1,1),請求台帳!$Q$5:$Q$504,"<>取消")) -> 0 | R5: =IF($A5="","",SUMIFS(入金明細!$E$5:$E$1004,入金明細!$G$5:$G$1004,$A5,入金明細!$B$5:$B$1004,">="&Q$3,入金明細!$B$5:$B$1004,"<"&DATE(YEAR(Q$3),MONTH(Q$3)+1,1))) -> 0 | S5: =IF($A5="","",SUMIFS(請求台帳!$F$5:$F$504,請求台帳!$C$5:$C$504,$A5,請求台帳!$B$5:$B$504,">="&S$3,請求台帳!$B$5:$B$504,"<"&DATE(YEAR(S$3),MONTH(S$3)+1,1),請求台帳!$Q$5:$Q$504,"<>取消")) -> 0 | T5: =IF($A5="","",SUMIFS(入金明細!$E$5:$E$1004,入金明細!$G$5:$G$1004,$A5,入金明細!$B$5:$B$1004,">="&S$3,入金明細!$B$5:$B$1004,"<"&DATE(YEAR(S$3),MONTH(S$3)+1,1))) -> 0 | U5: =IF($A5="","",SUMIFS(請求台帳!$F$5:$F$504,請求台帳!$C$5:$C$504,$A5,請求台帳!$B$5:$B$504,">="&U$3,請求台帳!$B$5:$B$504,"<"&DATE(YEAR(U$3),MONTH(U$3)+1,1),請求台帳!$Q$5:$Q$504,"<>取消")) -> 110000 | V5: =IF($A5="","",SUMIFS(入金明細!$E$5:$E$1004,入金明細!$G$5:$G$1004,$A5,入金明細!$B$5:$B$1004,">="&U$3,入金明細!$B$5:$B$1004,"<"&DATE(YEAR(U$3),MONTH(U$3)+1,1))) -> 0 | W5: =IF($A5="","",SUMIFS(請求台帳!$F$5:$F$504,請求台帳!$C$5:$C$504,$A5,請求台帳!$B$5:$B$504,">="&W$3,請求台帳!$B$5:$B$504,"<"&DATE(YEAR(W$3),MONTH(W$3)+1,1),請求台帳!$Q$5:$Q$504,"<>取消")) -> 0 | X5: =IF($A5="","",SUMIFS(入金明細!$E$5:$E$1004,入金明細!$G$5:$G$1004,$A5,入金明細!$B$5:$B$1004,">="&W$3,入金明細!$B$5:$B$1004,"<"&DATE(YEAR(W$3),MONTH(W$3)+1,1))) -> 110000 | Y5: =IF($A5="","",SUMIFS(請求台帳!$F$5:$F$504,請求台帳!$C$5:$C$504,$A5,請求台帳!$B$5:$B$504,">="&Y$3,請求台帳!$B$5:$B$504,"<"&DATE(YEAR(Y$3),MONTH(Y$3)+1,1),請求台帳!$Q$5:$Q$504,"<>取消")) -> 110000 | Z5: =IF($A5="","",SUMIFS(入金明細!$E$5:$E$1004,入金明細!$G$5:$G$1004,$A5,入金明細!$B$5:$B$1004,">="&Y$3,入金明細!$B$5:$B$1004,"<"&DATE(YEAR(Y$3),MONTH(Y$3)+1,1))) -> 0 | AA5: =SUM(C5,E5,G5,I5,K5,M5,O5,Q5,S5,U5,W5,Y5) -> 220000 | AB5: =SUM(D5,F5,H5,J5,L5,N5,P5,R5,T5,V5,X5,Z5) -> 110000
A6: =IF(取引先マスタ!A6="","",取引先マスタ!A6) -> C002 | B6: =IF(A6="","",取引先マスタ!B6) -> 有限会社テスト工業 | C6: =IF($A6="","",SUMIFS(請求台帳!$F$5:$F$504,請求台帳!$C$5:$C$504,$A6,請求台帳!$B$5:$B$504,">="&C$3,請求台帳!$B$5:$B$504,"<"&DATE(YEAR(C$3),MONTH(C$3)+1,1),請求台帳!$Q$5:$Q$504,"<>取消")) -> 0 | D6: =IF($A6="","",SUMIFS(入金明細!$E$5:$E$1004,入金明細!$G$5:$G$1004,$A6,入金明細!$B$5:$B$1004,">="&C$3,入金明細!$B$5:$B$1004,"<"&DATE(YEAR(C$3),MONTH(C$3)+1,1))) -> 0 | E6: =IF($A6="","",SUMIFS(請求台帳!$F$5:$F$504,請求台帳!$C$5:$C$504,$A6,請求台帳!$B$5:$B$504,">="&E$3,請求台帳!$B$5:$B$504,"<"&DATE(YEAR(E$3),MONTH(E$3)+1,1),請求台帳!$Q$5:$Q$504,"<>取消")) -> 0 | F6: =IF($A6="","",SUMIFS(入金明細!$E$5:$E$1004,入金明細!$G$5:$G$1004,$A6,入金明細!$B$5:$B$1004,">="&E$3,入金明細!$B$5:$B$1004,"<"&DATE(YEAR(E$3),MONTH(E$3)+1,1))) -> 0 | G6: =IF($A6="","",SUMIFS(請求台帳!$F$5:$F$504,請求台帳!$C$5:$C$504,$A6,請求台帳!$B$5:$B$504,">="&G$3,請求台帳!$B$5:$B$504,"<"&DATE(YEAR(G$3),MONTH(G$3)+1,1),請求台帳!$Q$5:$Q$504,"<>取消")) -> 0 | H6: =IF($A6="","",SUMIFS(入金明細!$E$5:$E$1004,入金明細!$G$5:$G$1004,$A6,入金明細!$B$5:$B$1004,">="&G$3,入金明細!$B$5:$B$1004,"<"&DATE(YEAR(G$3),MONTH(G$3)+1,1))) -> 0 | I6: =IF($A6="","",SUMIFS(請求台帳!$F$5:$F$504,請求台帳!$C$5:$C$504,$A6,請求台帳!$B$5:$B$504,">="&I$3,請求台帳!$B$5:$B$504,"<"&DATE(YEAR(I$3),MONTH(I$3)+1,1),請求台帳!$Q$5:$Q$504,"<>取消")) -> 0 | J6: =IF($A6="","",SUMIFS(入金明細!$E$5:$E$1004,入金明細!$G$5:$G$1004,$A6,入金明細!$B$5:$B$1004,">="&I$3,入金明細!$B$5:$B$1004,"<"&DATE(YEAR(I$3),MONTH(I$3)+1,1))) -> 0 | K6: =IF($A6="","",SUMIFS(請求台帳!$F$5:$F$504,請求台帳!$C$5:$C$504,$A6,請求台帳!$B$5:$B$504,">="&K$3,請求台帳!$B$5:$B$504,"<"&DATE(YEAR(K$3),MONTH(K$3)+1,1),請求台帳!$Q$5:$Q$504,"<>取消")) -> 0 | L6: =IF($A6="","",SUMIFS(入金明細!$E$5:$E$1004,入金明細!$G$5:$G$1004,$A6,入金明細!$B$5:$B$1004,">="&K$3,入金明細!$B$5:$B$1004,"<"&DATE(YEAR(K$3),MONTH(K$3)+1,1))) -> 0 | M6: =IF($A6="","",SUMIFS(請求台帳!$F$5:$F$504,請求台帳!$C$5:$C$504,$A6,請求台帳!$B$5:$B$504,">="&M$3,請求台帳!$B$5:$B$504,"<"&DATE(YEAR(M$3),MONTH(M$3)+1,1),請求台帳!$Q$5:$Q$504,"<>取消")) -> 0 | N6: =IF($A6="","",SUMIFS(入金明細!$E$5:$E$1004,入金明細!$G$5:$G$1004,$A6,入金明細!$B$5:$B$1004,">="&M$3,入金明細!$B$5:$B$1004,"<"&DATE(YEAR(M$3),MONTH(M$3)+1,1))) -> 0 | O6: =IF($A6="","",SUMIFS(請求台帳!$F$5:$F$504,請求台帳!$C$5:$C$504,$A6,請求台帳!$B$5:$B$504,">="&O$3,請求台帳!$B$5:$B$504,"<"&DATE(YEAR(O$3),MONTH(O$3)+1,1),請求台帳!$Q$5:$Q$504,"<>取消")) -> 0 | P6: =IF($A6="","",SUMIFS(入金明細!$E$5:$E$1004,入金明細!$G$5:$G$1004,$A6,入金明細!$B$5:$B$1004,">="&O$3,入金明細!$B$5:$B$1004,"<"&DATE(YEAR(O$3),MONTH(O$3)+1,1))) -> 0 | Q6: =IF($A6="","",SUMIFS(請求台帳!$F$5:$F$504,請求台帳!$C$5:$C$504,$A6,請求台帳!$B$5:$B$504,">="&Q$3,請求台帳!$B$5:$B$504,"<"&DATE(YEAR(Q$3),MONTH(Q$3)+1,1),請求台帳!$Q$5:$Q$504,"<>取消")) -> 0 | R6: =IF($A6="","",SUMIFS(入金明細!$E$5:$E$1004,入金明細!$G$5:$G$1004,$A6,入金明細!$B$5:$B$1004,">="&Q$3,入金明細!$B$5:$B$1004,"<"&DATE(YEAR(Q$3),MONTH(Q$3)+1,1))) -> 0 | S6: =IF($A6="","",SUMIFS(請求台帳!$F$5:$F$504,請求台帳!$C$5:$C$504,$A6,請求台帳!$B$5:$B$504,">="&S$3,請求台帳!$B$5:$B$504,"<"&DATE(YEAR(S$3),MONTH(S$3)+1,1),請求台帳!$Q$5:$Q$504,"<>取消")) -> 165000 | T6: =IF($A6="","",SUMIFS(入金明細!$E$5:$E$1004,入金明細!$G$5:$G$1004,$A6,入金明細!$B$5:$B$1004,">="&S$3,入金明細!$B$5:$B$1004,"<"&DATE(YEAR(S$3),MONTH(S$3)+1,1))) -> 0 | U6: =IF($A6="","",SUMIFS(請求台帳!$F$5:$F$504,請求台帳!$C$5:$C$504,$A6,請求台帳!$B$5:$B$504,">="&U$3,請求台帳!$B$5:$B$504,"<"&DATE(YEAR(U$3),MONTH(U$3)+1,1),請求台帳!$Q$5:$Q$504,"<>取消")) -> 275000 | V6: =IF($A6="","",SUMIFS(入金明細!$E$5:$E$1004,入金明細!$G$5:$G$1004,$A6,入金明細!$B$5:$B$1004,">="&U$3,入金明細!$B$5:$B$1004,"<"&DATE(YEAR(U$3),MONTH(U$3)+1,1))) -> 0 | W6: =IF($A6="","",SUMIFS(請求台帳!$F$5:$F$504,請求台帳!$C$5:$C$504,$A6,請求台帳!$B$5:$B$504,">="&W$3,請求台帳!$B$5:$B$504,"<"&DATE(YEAR(W$3),MONTH(W$3)+1,1),請求台帳!$Q$5:$Q$504,"<>取消")) -> 0 | X6: =IF($A6="","",SUMIFS(入金明細!$E$5:$E$1004,入金明細!$G$5:$G$1004,$A6,入金明細!$B$5:$B$1004,">="&W$3,入金明細!$B$5:$B$1004,"<"&DATE(YEAR(W$3),MONTH(W$3)+1,1))) -> 0 | Y6: =IF($A6="","",SUMIFS(請求台帳!$F$5:$F$504,請求台帳!$C$5:$C$504,$A6,請求台帳!$B$5:$B$504,">="&Y$3,請求台帳!$B$5:$B$504,"<"&DATE(YEAR(Y$3),MONTH(Y$3)+1,1),請求台帳!$Q$5:$Q$504,"<>取消")) -> 0 | Z6: =IF($A6="","",SUMIFS(入金明細!$E$5:$E$1004,入金明細!$G$5:$G$1004,$A6,入金明細!$B$5:$B$1004,">="&Y$3,入金明細!$B$5:$B$1004,"<"&DATE(YEAR(Y$3),MONTH(Y$3)+1,1))) -> 274560 | AA6: =SUM(C6,E6,G6,I6,K6,M6,O6,Q6,S6,U6,W6,Y6) -> 440000 | AB6: =SUM(D6,F6,H6,J6,L6,N6,P6,R6,T6,V6,X6,Z6) -> 274560
A7: =IF(取引先マスタ!A7="","",取引先マスタ!A7) -> C003 | B7: =IF(A7="","",取引先マスタ!B7) -> 合同会社デモ | C7: =IF($A7="","",SUMIFS(請求台帳!$F$5:$F$504,請求台帳!$C$5:$C$504,$A7,請求台帳!$B$5:$B$504,">="&C$3,請求台帳!$B$5:$B$504,"<"&DATE(YEAR(C$3),MONTH(C$3)+1,1),請求台帳!$Q$5:$Q$504,"<>取消")) -> 0 | D7: =IF($A7="","",SUMIFS(入金明細!$E$5:$E$1004,入金明細!$G$5:$G$1004,$A7,入金明細!$B$5:$B$1004,">="&C$3,入金明細!$B$5:$B$1004,"<"&DATE(YEAR(C$3),MONTH(C$3)+1,1))) -> 0 | E7: =IF($A7="","",SUMIFS(請求台帳!$F$5:$F$504,請求台帳!$C$5:$C$504,$A7,請求台帳!$B$5:$B$504,">="&E$3,請求台帳!$B$5:$B$504,"<"&DATE(YEAR(E$3),MONTH(E$3)+1,1),請求台帳!$Q$5:$Q$504,"<>取消")) -> 0 | F7: =IF($A7="","",SUMIFS(入金明細!$E$5:$E$1004,入金明細!$G$5:$G$1004,$A7,入金明細!$B$5:$B$1004,">="&E$3,入金明細!$B$5:$B$1004,"<"&DATE(YEAR(E$3),MONTH(E$3)+1,1))) -> 0 | G7: =IF($A7="","",SUMIFS(請求台帳!$F$5:$F$504,請求台帳!$C$5:$C$504,$A7,請求台帳!$B$5:$B$504,">="&G$3,請求台帳!$B$5:$B$504,"<"&DATE(YEAR(G$3),MONTH(G$3)+1,1),請求台帳!$Q$5:$Q$504,"<>取消")) -> 0 | H7: =IF($A7="","",SUMIFS(入金明細!$E$5:$E$1004,入金明細!$G$5:$G$1004,$A7,入金明細!$B$5:$B$1004,">="&G$3,入金明細!$B$5:$B$1004,"<"&DATE(YEAR(G$3),MONTH(G$3)+1,1))) -> 0 | I7: =IF($A7="","",SUMIFS(請求台帳!$F$5:$F$504,請求台帳!$C$5:$C$504,$A7,請求台帳!$B$5:$B$504,">="&I$3,請求台帳!$B$5:$B$504,"<"&DATE(YEAR(I$3),MONTH(I$3)+1,1),請求台帳!$Q$5:$Q$504,"<>取消")) -> 0 | J7: =IF($A7="","",SUMIFS(入金明細!$E$5:$E$1004,入金明細!$G$5:$G$1004,$A7,入金明細!$B$5:$B$1004,">="&I$3,入金明細!$B$5:$B$1004,"<"&DATE(YEAR(I$3),MONTH(I$3)+1,1))) -> 0 | K7: =IF($A7="","",SUMIFS(請求台帳!$F$5:$F$504,請求台帳!$C$5:$C$504,$A7,請求台帳!$B$5:$B$504,">="&K$3,請求台帳!$B$5:$B$504,"<"&DATE(YEAR(K$3),MONTH(K$3)+1,1),請求台帳!$Q$5:$Q$504,"<>取消")) -> 0 | L7: =IF($A7="","",SUMIFS(入金明細!$E$5:$E$1004,入金明細!$G$5:$G$1004,$A7,入金明細!$B$5:$B$1004,">="&K$3,入金明細!$B$5:$B$1004,"<"&DATE(YEAR(K$3),MONTH(K$3)+1,1))) -> 0 | M7: =IF($A7="","",SUMIFS(請求台帳!$F$5:$F$504,請求台帳!$C$5:$C$504,$A7,請求台帳!$B$5:$B$504,">="&M$3,請求台帳!$B$5:$B$504,"<"&DATE(YEAR(M$3),MONTH(M$3)+1,1),請求台帳!$Q$5:$Q$504,"<>取消")) -> 0 | N7: =IF($A7="","",SUMIFS(入金明細!$E$5:$E$1004,入金明細!$G$5:$G$1004,$A7,入金明細!$B$5:$B$1004,">="&M$3,入金明細!$B$5:$B$1004,"<"&DATE(YEAR(M$3),MONTH(M$3)+1,1))) -> 0 | O7: =IF($A7="","",SUMIFS(請求台帳!$F$5:$F$504,請求台帳!$C$5:$C$504,$A7,請求台帳!$B$5:$B$504,">="&O$3,請求台帳!$B$5:$B$504,"<"&DATE(YEAR(O$3),MONTH(O$3)+1,1),請求台帳!$Q$5:$Q$504,"<>取消")) -> 0 | P7: =IF($A7="","",SUMIFS(入金明細!$E$5:$E$1004,入金明細!$G$5:$G$1004,$A7,入金明細!$B$5:$B$1004,">="&O$3,入金明細!$B$5:$B$1004,"<"&DATE(YEAR(O$3),MONTH(O$3)+1,1))) -> 0 | Q7: =IF($A7="","",SUMIFS(請求台帳!$F$5:$F$504,請求台帳!$C$5:$C$504,$A7,請求台帳!$B$5:$B$504,">="&Q$3,請求台帳!$B$5:$B$504,"<"&DATE(YEAR(Q$3),MONTH(Q$3)+1,1),請求台帳!$Q$5:$Q$504,"<>取消")) -> 0 | R7: =IF($A7="","",SUMIFS(入金明細!$E$5:$E$1004,入金明細!$G$5:$G$1004,$A7,入金明細!$B$5:$B$1004,">="&Q$3,入金明細!$B$5:$B$1004,"<"&DATE(YEAR(Q$3),MONTH(Q$3)+1,1))) -> 0 | S7: =IF($A7="","",SUMIFS(請求台帳!$F$5:$F$504,請求台帳!$C$5:$C$504,$A7,請求台帳!$B$5:$B$504,">="&S$3,請求台帳!$B$5:$B$504,"<"&DATE(YEAR(S$3),MONTH(S$3)+1,1),請求台帳!$Q$5:$Q$504,"<>取消")) -> 0 | T7: =IF($A7="","",SUMIFS(入金明細!$E$5:$E$1004,入金明細!$G$5:$G$1004,$A7,入金明細!$B$5:$B$1004,">="&S$3,入金明細!$B$5:$B$1004,"<"&DATE(YEAR(S$3),MONTH(S$3)+1,1))) -> 0 | U7: =IF($A7="","",SUMIFS(請求台帳!$F$5:$F$504,請求台帳!$C$5:$C$504,$A7,請求台帳!$B$5:$B$504,">="&U$3,請求台帳!$B$5:$B$504,"<"&DATE(YEAR(U$3),MONTH(U$3)+1,1),請求台帳!$Q$5:$Q$504,"<>取消")) -> 0 | V7: =IF($A7="","",SUMIFS(入金明細!$E$5:$E$1004,入金明細!$G$5:$G$1004,$A7,入金明細!$B$5:$B$1004,">="&U$3,入金明細!$B$5:$B$1004,"<"&DATE(YEAR(U$3),MONTH(U$3)+1,1))) -> 0 | W7: =IF($A7="","",SUMIFS(請求台帳!$F$5:$F$504,請求台帳!$C$5:$C$504,$A7,請求台帳!$B$5:$B$504,">="&W$3,請求台帳!$B$5:$B$504,"<"&DATE(YEAR(W$3),MONTH(W$3)+1,1),請求台帳!$Q$5:$Q$504,"<>取消")) -> 88000 | X7: =IF($A7="","",SUMIFS(入金明細!$E$5:$E$1004,入金明細!$G$5:$G$1004,$A7,入金明細!$B$5:$B$1004,">="&W$3,入金明細!$B$5:$B$1004,"<"&DATE(YEAR(W$3),MONTH(W$3)+1,1))) -> 0 | Y7: =IF($A7="","",SUMIFS(請求台帳!$F$5:$F$504,請求台帳!$C$5:$C$504,$A7,請求台帳!$B$5:$B$504,">="&Y$3,請求台帳!$B$5:$B$504,"<"&DATE(YEAR(Y$3),MONTH(Y$3)+1,1),請求台帳!$Q$5:$Q$504,"<>取消")) -> 36300 | Z7: =IF($A7="","",SUMIFS(入金明細!$E$5:$E$1004,入金明細!$G$5:$G$1004,$A7,入金明細!$B$5:$B$1004,">="&Y$3,入金明細!$B$5:$B$1004,"<"&DATE(YEAR(Y$3),MONTH(Y$3)+1,1))) -> 50000 | AA7: =SUM(C7,E7,G7,I7,K7,M7,O7,Q7,S7,U7,W7,Y7) -> 124300 | AB7: =SUM(D7,F7,H7,J7,L7,N7,P7,R7,T7,V7,X7,Z7) -> 50000
A8: =IF(取引先マスタ!A8="","",取引先マスタ!A8) | B8: =IF(A8="","",取引先マスタ!B8) | C8: =IF($A8="","",SUMIFS(請求台帳!$F$5:$F$504,請求台帳!$C$5:$C$504,$A8,請求台帳!$B$5:$B$504,">="&C$3,請求台帳!$B$5:$B$504,"<"&DATE(YEAR(C$3),MONTH(C$3)+1,1),請求台帳!$Q$5:$Q$504,"<>取消")) | D8: =IF($A8="","",SUMIFS(入金明細!$E$5:$E$1004,入金明細!$G$5:$G$1004,$A8,入金明細!$B$5:$B$1004,">="&C$3,入金明細!$B$5:$B$1004,"<"&DATE(YEAR(C$3),MONTH(C$3)+1,1))) | E8: =IF($A8="","",SUMIFS(請求台帳!$F$5:$F$504,請求台帳!$C$5:$C$504,$A8,請求台帳!$B$5:$B$504,">="&E$3,請求台帳!$B$5:$B$504,"<"&DATE(YEAR(E$3),MONTH(E$3)+1,1),請求台帳!$Q$5:$Q$504,"<>取消")) | F8: =IF($A8="","",SUMIFS(入金明細!$E$5:$E$1004,入金明細!$G$5:$G$1004,$A8,入金明細!$B$5:$B$1004,">="&E$3,入金明細!$B$5:$B$1004,"<"&DATE(YEAR(E$3),MONTH(E$3)+1,1))) | G8: =IF($A8="","",SUMIFS(請求台帳!$F$5:$F$504,請求台帳!$C$5:$C$504,$A8,請求台帳!$B$5:$B$504,">="&G$3,請求台帳!$B$5:$B$504,"<"&DATE(YEAR(G$3),MONTH(G$3)+1,1),請求台帳!$Q$5:$Q$504,"<>取消")) | H8: =IF($A8="","",SUMIFS(入金明細!$E$5:$E$1004,入金明細!$G$5:$G$1004,$A8,入金明細!$B$5:$B$1004,">="&G$3,入金明細!$B$5:$B$1004,"<"&DATE(YEAR(G$3),MONTH(G$3)+1,1))) | I8: =IF($A8="","",SUMIFS(請求台帳!$F$5:$F$504,請求台帳!$C$5:$C$504,$A8,請求台帳!$B$5:$B$504,">="&I$3,請求台帳!$B$5:$B$504,"<"&DATE(YEAR(I$3),MONTH(I$3)+1,1),請求台帳!$Q$5:$Q$504,"<>取消")) | J8: =IF($A8="","",SUMIFS(入金明細!$E$5:$E$1004,入金明細!$G$5:$G$1004,$A8,入金明細!$B$5:$B$1004,">="&I$3,入金明細!$B$5:$B$1004,"<"&DATE(YEAR(I$3),MONTH(I$3)+1,1))) | K8: =IF($A8="","",SUMIFS(請求台帳!$F$5:$F$504,請求台帳!$C$5:$C$504,$A8,請求台帳!$B$5:$B$504,">="&K$3,請求台帳!$B$5:$B$504,"<"&DATE(YEAR(K$3),MONTH(K$3)+1,1),請求台帳!$Q$5:$Q$504,"<>取消")) | L8: =IF($A8="","",SUMIFS(入金明細!$E$5:$E$1004,入金明細!$G$5:$G$1004,$A8,入金明細!$B$5:$B$1004,">="&K$3,入金明細!$B$5:$B$1004,"<"&DATE(YEAR(K$3),MONTH(K$3)+1,1))) | M8: =IF($A8="","",SUMIFS(請求台帳!$F$5:$F$504,請求台帳!$C$5:$C$504,$A8,請求台帳!$B$5:$B$504,">="&M$3,請求台帳!$B$5:$B$504,"<"&DATE(YEAR(M$3),MONTH(M$3)+1,1),請求台帳!$Q$5:$Q$504,"<>取消")) | N8: =IF($A8="","",SUMIFS(入金明細!$E$5:$E$1004,入金明細!$G$5:$G$1004,$A8,入金明細!$B$5:$B$1004,">="&M$3,入金明細!$B$5:$B$1004,"<"&DATE(YEAR(M$3),MONTH(M$3)+1,1))) | O8: =IF($A8="","",SUMIFS(請求台帳!$F$5:$F$504,請求台帳!$C$5:$C$504,$A8,請求台帳!$B$5:$B$504,">="&O$3,請求台帳!$B$5:$B$504,"<"&DATE(YEAR(O$3),MONTH(O$3)+1,1),請求台帳!$Q$5:$Q$504,"<>取消")) | P8: =IF($A8="","",SUMIFS(入金明細!$E$5:$E$1004,入金明細!$G$5:$G$1004,$A8,入金明細!$B$5:$B$1004,">="&O$3,入金明細!$B$5:$B$1004,"<"&DATE(YEAR(O$3),MONTH(O$3)+1,1))) | Q8: =IF($A8="","",SUMIFS(請求台帳!$F$5:$F$504,請求台帳!$C$5:$C$504,$A8,請求台帳!$B$5:$B$504,">="&Q$3,請求台帳!$B$5:$B$504,"<"&DATE(YEAR(Q$3),MONTH(Q$3)+1,1),請求台帳!$Q$5:$Q$504,"<>取消")) | R8: =IF($A8="","",SUMIFS(入金明細!$E$5:$E$1004,入金明細!$G$5:$G$1004,$A8,入金明細!$B$5:$B$1004,">="&Q$3,入金明細!$B$5:$B$1004,"<"&DATE(YEAR(Q$3),MONTH(Q$3)+1,1))) | S8: =IF($A8="","",SUMIFS(請求台帳!$F$5:$F$504,請求台帳!$C$5:$C$504,$A8,請求台帳!$B$5:$B$504,">="&S$3,請求台帳!$B$5:$B$504,"<"&DATE(YEAR(S$3),MONTH(S$3)+1,1),請求台帳!$Q$5:$Q$504,"<>取消")) | T8: =IF($A8="","",SUMIFS(入金明細!$E$5:$E$1004,入金明細!$G$5:$G$1004,$A8,入金明細!$B$5:$B$1004,">="&S$3,入金明細!$B$5:$B$1004,"<"&DATE(YEAR(S$3),MONTH(S$3)+1,1))) | U8: =IF($A8="","",SUMIFS(請求台帳!$F$5:$F$504,請求台帳!$C$5:$C$504,$A8,請求台帳!$B$5:$B$504,">="&U$3,請求台帳!$B$5:$B$504,"<"&DATE(YEAR(U$3),MONTH(U$3)+1,1),請求台帳!$Q$5:$Q$504,"<>取消")) | V8: =IF($A8="","",SUMIFS(入金明細!$E$5:$E$1004,入金明細!$G$5:$G$1004,$A8,入金明細!$B$5:$B$1004,">="&U$3,入金明細!$B$5:$B$1004,"<"&DATE(YEAR(U$3),MONTH(U$3)+1,1))) | W8: =IF($A8="","",SUMIFS(請求台帳!$F$5:$F$504,請求台帳!$C$5:$C$504,$A8,請求台帳!$B$5:$B$504,">="&W$3,請求台帳!$B$5:$B$504,"<"&DATE(YEAR(W$3),MONTH(W$3)+1,1),請求台帳!$Q$5:$Q$504,"<>取消")) | X8: =IF($A8="","",SUMIFS(入金明細!$E$5:$E$1004,入金明細!$G$5:$G$1004,$A8,入金明細!$B$5:$B$1004,">="&W$3,入金明細!$B$5:$B$1004,"<"&DATE(YEAR(W$3),MONTH(W$3)+1,1))) | Y8: =IF($A8="","",SUMIFS(請求台帳!$F$5:$F$504,請求台帳!$C$5:$C$504,$A8,請求台帳!$B$5:$B$504,">="&Y$3,請求台帳!$B$5:$B$504,"<"&DATE(YEAR(Y$3),MONTH(Y$3)+1,1),請求台帳!$Q$5:$Q$504,"<>取消")) | Z8: =IF($A8="","",SUMIFS(入金明細!$E$5:$E$1004,入金明細!$G$5:$G$1004,$A8,入金明細!$B$5:$B$1004,">="&Y$3,入金明細!$B$5:$B$1004,"<"&DATE(YEAR(Y$3),MONTH(Y$3)+1,1))) | AA8: =SUM(C8,E8,G8,I8,K8,M8,O8,Q8,S8,U8,W8,Y8) -> 0 | AB8: =SUM(D8,F8,H8,J8,L8,N8,P8,R8,T8,V8,X8,Z8) -> 0
A9: =IF(取引先マスタ!A9="","",取引先マスタ!A9) | B9: =IF(A9="","",取引先マスタ!B9) | C9: =IF($A9="","",SUMIFS(請求台帳!$F$5:$F$504,請求台帳!$C$5:$C$504,$A9,請求台帳!$B$5:$B$504,">="&C$3,請求台帳!$B$5:$B$504,"<"&DATE(YEAR(C$3),MONTH(C$3)+1,1),請求台帳!$Q$5:$Q$504,"<>取消")) | D9: =IF($A9="","",SUMIFS(入金明細!$E$5:$E$1004,入金明細!$G$5:$G$1004,$A9,入金明細!$B$5:$B$1004,">="&C$3,入金明細!$B$5:$B$1004,"<"&DATE(YEAR(C$3),MONTH(C$3)+1,1))) | E9: =IF($A9="","",SUMIFS(請求台帳!$F$5:$F$504,請求台帳!$C$5:$C$504,$A9,請求台帳!$B$5:$B$504,">="&E$3,請求台帳!$B$5:$B$504,"<"&DATE(YEAR(E$3),MONTH(E$3)+1,1),請求台帳!$Q$5:$Q$504,"<>取消")) | F9: =IF($A9="","",SUMIFS(入金明細!$E$5:$E$1004,入金明細!$G$5:$G$1004,$A9,入金明細!$B$5:$B$1004,">="&E$3,入金明細!$B$5:$B$1004,"<"&DATE(YEAR(E$3),MONTH(E$3)+1,1))) | G9: =IF($A9="","",SUMIFS(請求台帳!$F$5:$F$504,請求台帳!$C$5:$C$504,$A9,請求台帳!$B$5:$B$504,">="&G$3,請求台帳!$B$5:$B$504,"<"&DATE(YEAR(G$3),MONTH(G$3)+1,1),請求台帳!$Q$5:$Q$504,"<>取消")) | H9: =IF($A9="","",SUMIFS(入金明細!$E$5:$E$1004,入金明細!$G$5:$G$1004,$A9,入金明細!$B$5:$B$1004,">="&G$3,入金明細!$B$5:$B$1004,"<"&DATE(YEAR(G$3),MONTH(G$3)+1,1))) | I9: =IF($A9="","",SUMIFS(請求台帳!$F$5:$F$504,請求台帳!$C$5:$C$504,$A9,請求台帳!$B$5:$B$504,">="&I$3,請求台帳!$B$5:$B$504,"<"&DATE(YEAR(I$3),MONTH(I$3)+1,1),請求台帳!$Q$5:$Q$504,"<>取消")) | J9: =IF($A9="","",SUMIFS(入金明細!$E$5:$E$1004,入金明細!$G$5:$G$1004,$A9,入金明細!$B$5:$B$1004,">="&I$3,入金明細!$B$5:$B$1004,"<"&DATE(YEAR(I$3),MONTH(I$3)+1,1))) | K9: =IF($A9="","",SUMIFS(請求台帳!$F$5:$F$504,請求台帳!$C$5:$C$504,$A9,請求台帳!$B$5:$B$504,">="&K$3,請求台帳!$B$5:$B$504,"<"&DATE(YEAR(K$3),MONTH(K$3)+1,1),請求台帳!$Q$5:$Q$504,"<>取消")) | L9: =IF($A9="","",SUMIFS(入金明細!$E$5:$E$1004,入金明細!$G$5:$G$1004,$A9,入金明細!$B$5:$B$1004,">="&K$3,入金明細!$B$5:$B$1004,"<"&DATE(YEAR(K$3),MONTH(K$3)+1,1))) | M9: =IF($A9="","",SUMIFS(請求台帳!$F$5:$F$504,請求台帳!$C$5:$C$504,$A9,請求台帳!$B$5:$B$504,">="&M$3,請求台帳!$B$5:$B$504,"<"&DATE(YEAR(M$3),MONTH(M$3)+1,1),請求台帳!$Q$5:$Q$504,"<>取消")) | N9: =IF($A9="","",SUMIFS(入金明細!$E$5:$E$1004,入金明細!$G$5:$G$1004,$A9,入金明細!$B$5:$B$1004,">="&M$3,入金明細!$B$5:$B$1004,"<"&DATE(YEAR(M$3),MONTH(M$3)+1,1))) | O9: =IF($A9="","",SUMIFS(請求台帳!$F$5:$F$504,請求台帳!$C$5:$C$504,$A9,請求台帳!$B$5:$B$504,">="&O$3,請求台帳!$B$5:$B$504,"<"&DATE(YEAR(O$3),MONTH(O$3)+1,1),請求台帳!$Q$5:$Q$504,"<>取消")) | P9: =IF($A9="","",SUMIFS(入金明細!$E$5:$E$1004,入金明細!$G$5:$G$1004,$A9,入金明細!$B$5:$B$1004,">="&O$3,入金明細!$B$5:$B$1004,"<"&DATE(YEAR(O$3),MONTH(O$3)+1,1))) | Q9: =IF($A9="","",SUMIFS(請求台帳!$F$5:$F$504,請求台帳!$C$5:$C$504,$A9,請求台帳!$B$5:$B$504,">="&Q$3,請求台帳!$B$5:$B$504,"<"&DATE(YEAR(Q$3),MONTH(Q$3)+1,1),請求台帳!$Q$5:$Q$504,"<>取消")) | R9: =IF($A9="","",SUMIFS(入金明細!$E$5:$E$1004,入金明細!$G$5:$G$1004,$A9,入金明細!$B$5:$B$1004,">="&Q$3,入金明細!$B$5:$B$1004,"<"&DATE(YEAR(Q$3),MONTH(Q$3)+1,1))) | S9: =IF($A9="","",SUMIFS(請求台帳!$F$5:$F$504,請求台帳!$C$5:$C$504,$A9,請求台帳!$B$5:$B$504,">="&S$3,請求台帳!$B$5:$B$504,"<"&DATE(YEAR(S$3),MONTH(S$3)+1,1),請求台帳!$Q$5:$Q$504,"<>取消")) | T9: =IF($A9="","",SUMIFS(入金明細!$E$5:$E$1004,入金明細!$G$5:$G$1004,$A9,入金明細!$B$5:$B$1004,">="&S$3,入金明細!$B$5:$B$1004,"<"&DATE(YEAR(S$3),MONTH(S$3)+1,1))) | U9: =IF($A9="","",SUMIFS(請求台帳!$F$5:$F$504,請求台帳!$C$5:$C$504,$A9,請求台帳!$B$5:$B$504,">="&U$3,請求台帳!$B$5:$B$504,"<"&DATE(YEAR(U$3),MONTH(U$3)+1,1),請求台帳!$Q$5:$Q$504,"<>取消")) | V9: =IF($A9="","",SUMIFS(入金明細!$E$5:$E$1004,入金明細!$G$5:$G$1004,$A9,入金明細!$B$5:$B$1004,">="&U$3,入金明細!$B$5:$B$1004,"<"&DATE(YEAR(U$3),MONTH(U$3)+1,1))) | W9: =IF($A9="","",SUMIFS(請求台帳!$F$5:$F$504,請求台帳!$C$5:$C$504,$A9,請求台帳!$B$5:$B$504,">="&W$3,請求台帳!$B$5:$B$504,"<"&DATE(YEAR(W$3),MONTH(W$3)+1,1),請求台帳!$Q$5:$Q$504,"<>取消")) | X9: =IF($A9="","",SUMIFS(入金明細!$E$5:$E$1004,入金明細!$G$5:$G$1004,$A9,入金明細!$B$5:$B$1004,">="&W$3,入金明細!$B$5:$B$1004,"<"&DATE(YEAR(W$3),MONTH(W$3)+1,1))) | Y9: =IF($A9="","",SUMIFS(請求台帳!$F$5:$F$504,請求台帳!$C$5:$C$504,$A9,請求台帳!$B$5:$B$504,">="&Y$3,請求台帳!$B$5:$B$504,"<"&DATE(YEAR(Y$3),MONTH(Y$3)+1,1),請求台帳!$Q$5:$Q$504,"<>取消")) | Z9: =IF($A9="","",SUMIFS(入金明細!$E$5:$E$1004,入金明細!$G$5:$G$1004,$A9,入金明細!$B$5:$B$1004,">="&Y$3,入金明細!$B$5:$B$1004,"<"&DATE(YEAR(Y$3),MONTH(Y$3)+1,1))) | AA9: =SUM(C9,E9,G9,I9,K9,M9,O9,Q9,S9,U9,W9,Y9) -> 0 | AB9: =SUM(D9,F9,H9,J9,L9,N9,P9,R9,T9,V9,X9,Z9) -> 0
A10: =IF(取引先マスタ!A10="","",取引先マスタ!A10) | B10: =IF(A10="","",取引先マスタ!B10) | C10: =IF($A10="","",SUMIFS(請求台帳!$F$5:$F$504,請求台帳!$C$5:$C$504,$A10,請求台帳!$B$5:$B$504,">="&C$3,請求台帳!$B$5:$B$504,"<"&DATE(YEAR(C$3),MONTH(C$3)+1,1),請求台帳!$Q$5:$Q$504,"<>取消")) | D10: =IF($A10="","",SUMIFS(入金明細!$E$5:$E$1004,入金明細!$G$5:$G$1004,$A10,入金明細!$B$5:$B$1004,">="&C$3,入金明細!$B$5:$B$1004,"<"&DATE(YEAR(C$3),MONTH(C$3)+1,1))) | E10: =IF($A10="","",SUMIFS(請求台帳!$F$5:$F$504,請求台帳!$C$5:$C$504,$A10,請求台帳!$B$5:$B$504,">="&E$3,請求台帳!$B$5:$B$504,"<"&DATE(YEAR(E$3),MONTH(E$3)+1,1),請求台帳!$Q$5:$Q$504,"<>取消")) | F10: =IF($A10="","",SUMIFS(入金明細!$E$5:$E$1004,入金明細!$G$5:$G$1004,$A10,入金明細!$B$5:$B$1004,">="&E$3,入金明細!$B$5:$B$1004,"<"&DATE(YEAR(E$3),MONTH(E$3)+1,1))) | G10: =IF($A10="","",SUMIFS(請求台帳!$F$5:$F$504,請求台帳!$C$5:$C$504,$A10,請求台帳!$B$5:$B$504,">="&G$3,請求台帳!$B$5:$B$504,"<"&DATE(YEAR(G$3),MONTH(G$3)+1,1),請求台帳!$Q$5:$Q$504,"<>取消")) | H10: =IF($A10="","",SUMIFS(入金明細!$E$5:$E$1004,入金明細!$G$5:$G$1004,$A10,入金明細!$B$5:$B$1004,">="&G$3,入金明細!$B$5:$B$1004,"<"&DATE(YEAR(G$3),MONTH(G$3)+1,1))) | I10: =IF($A10="","",SUMIFS(請求台帳!$F$5:$F$504,請求台帳!$C$5:$C$504,$A10,請求台帳!$B$5:$B$504,">="&I$3,請求台帳!$B$5:$B$504,"<"&DATE(YEAR(I$3),MONTH(I$3)+1,1),請求台帳!$Q$5:$Q$504,"<>取消")) | J10: =IF($A10="","",SUMIFS(入金明細!$E$5:$E$1004,入金明細!$G$5:$G$1004,$A10,入金明細!$B$5:$B$1004,">="&I$3,入金明細!$B$5:$B$1004,"<"&DATE(YEAR(I$3),MONTH(I$3)+1,1))) | K10: =IF($A10="","",SUMIFS(請求台帳!$F$5:$F$504,請求台帳!$C$5:$C$504,$A10,請求台帳!$B$5:$B$504,">="&K$3,請求台帳!$B$5:$B$504,"<"&DATE(YEAR(K$3),MONTH(K$3)+1,1),請求台帳!$Q$5:$Q$504,"<>取消")) | L10: =IF($A10="","",SUMIFS(入金明細!$E$5:$E$1004,入金明細!$G$5:$G$1004,$A10,入金明細!$B$5:$B$1004,">="&K$3,入金明細!$B$5:$B$1004,"<"&DATE(YEAR(K$3),MONTH(K$3)+1,1))) | M10: =IF($A10="","",SUMIFS(請求台帳!$F$5:$F$504,請求台帳!$C$5:$C$504,$A10,請求台帳!$B$5:$B$504,">="&M$3,請求台帳!$B$5:$B$504,"<"&DATE(YEAR(M$3),MONTH(M$3)+1,1),請求台帳!$Q$5:$Q$504,"<>取消")) | N10: =IF($A10="","",SUMIFS(入金明細!$E$5:$E$1004,入金明細!$G$5:$G$1004,$A10,入金明細!$B$5:$B$1004,">="&M$3,入金明細!$B$5:$B$1004,"<"&DATE(YEAR(M$3),MONTH(M$3)+1,1))) | O10: =IF($A10="","",SUMIFS(請求台帳!$F$5:$F$504,請求台帳!$C$5:$C$504,$A10,請求台帳!$B$5:$B$504,">="&O$3,請求台帳!$B$5:$B$504,"<"&DATE(YEAR(O$3),MONTH(O$3)+1,1),請求台帳!$Q$5:$Q$504,"<>取消")) | P10: =IF($A10="","",SUMIFS(入金明細!$E$5:$E$1004,入金明細!$G$5:$G$1004,$A10,入金明細!$B$5:$B$1004,">="&O$3,入金明細!$B$5:$B$1004,"<"&DATE(YEAR(O$3),MONTH(O$3)+1,1))) | Q10: =IF($A10="","",SUMIFS(請求台帳!$F$5:$F$504,請求台帳!$C$5:$C$504,$A10,請求台帳!$B$5:$B$504,">="&Q$3,請求台帳!$B$5:$B$504,"<"&DATE(YEAR(Q$3),MONTH(Q$3)+1,1),請求台帳!$Q$5:$Q$504,"<>取消")) | R10: =IF($A10="","",SUMIFS(入金明細!$E$5:$E$1004,入金明細!$G$5:$G$1004,$A10,入金明細!$B$5:$B$1004,">="&Q$3,入金明細!$B$5:$B$1004,"<"&DATE(YEAR(Q$3),MONTH(Q$3)+1,1))) | S10: =IF($A10="","",SUMIFS(請求台帳!$F$5:$F$504,請求台帳!$C$5:$C$504,$A10,請求台帳!$B$5:$B$504,">="&S$3,請求台帳!$B$5:$B$504,"<"&DATE(YEAR(S$3),MONTH(S$3)+1,1),請求台帳!$Q$5:$Q$504,"<>取消")) | T10: =IF($A10="","",SUMIFS(入金明細!$E$5:$E$1004,入金明細!$G$5:$G$1004,$A10,入金明細!$B$5:$B$1004,">="&S$3,入金明細!$B$5:$B$1004,"<"&DATE(YEAR(S$3),MONTH(S$3)+1,1))) | U10: =IF($A10="","",SUMIFS(請求台帳!$F$5:$F$504,請求台帳!$C$5:$C$504,$A10,請求台帳!$B$5:$B$504,">="&U$3,請求台帳!$B$5:$B$504,"<"&DATE(YEAR(U$3),MONTH(U$3)+1,1),請求台帳!$Q$5:$Q$504,"<>取消")) | V10: =IF($A10="","",SUMIFS(入金明細!$E$5:$E$1004,入金明細!$G$5:$G$1004,$A10,入金明細!$B$5:$B$1004,">="&U$3,入金明細!$B$5:$B$1004,"<"&DATE(YEAR(U$3),MONTH(U$3)+1,1))) | W10: =IF($A10="","",SUMIFS(請求台帳!$F$5:$F$504,請求台帳!$C$5:$C$504,$A10,請求台帳!$B$5:$B$504,">="&W$3,請求台帳!$B$5:$B$504,"<"&DATE(YEAR(W$3),MONTH(W$3)+1,1),請求台帳!$Q$5:$Q$504,"<>取消")) | X10: =IF($A10="","",SUMIFS(入金明細!$E$5:$E$1004,入金明細!$G$5:$G$1004,$A10,入金明細!$B$5:$B$1004,">="&W$3,入金明細!$B$5:$B$1004,"<"&DATE(YEAR(W$3),MONTH(W$3)+1,1))) | Y10: =IF($A10="","",SUMIFS(請求台帳!$F$5:$F$504,請求台帳!$C$5:$C$504,$A10,請求台帳!$B$5:$B$504,">="&Y$3,請求台帳!$B$5:$B$504,"<"&DATE(YEAR(Y$3),MONTH(Y$3)+1,1),請求台帳!$Q$5:$Q$504,"<>取消")) | Z10: =IF($A10="","",SUMIFS(入金明細!$E$5:$E$1004,入金明細!$G$5:$G$1004,$A10,入金明細!$B$5:$B$1004,">="&Y$3,入金明細!$B$5:$B$1004,"<"&DATE(YEAR(Y$3),MONTH(Y$3)+1,1))) | AA10: =SUM(C10,E10,G10,I10,K10,M10,O10,Q10,S10,U10,W10,Y10) -> 0 | AB10: =SUM(D10,F10,H10,J10,L10,N10,P10,R10,T10,V10,X10,Z10) -> 0
A11: =IF(取引先マスタ!A11="","",取引先マスタ!A11) | B11: =IF(A11="","",取引先マスタ!B11) | C11: =IF($A11="","",SUMIFS(請求台帳!$F$5:$F$504,請求台帳!$C$5:$C$504,$A11,請求台帳!$B$5:$B$504,">="&C$3,請求台帳!$B$5:$B$504,"<"&DATE(YEAR(C$3),MONTH(C$3)+1,1),請求台帳!$Q$5:$Q$504,"<>取消")) | D11: =IF($A11="","",SUMIFS(入金明細!$E$5:$E$1004,入金明細!$G$5:$G$1004,$A11,入金明細!$B$5:$B$1004,">="&C$3,入金明細!$B$5:$B$1004,"<"&DATE(YEAR(C$3),MONTH(C$3)+1,1))) | E11: =IF($A11="","",SUMIFS(請求台帳!$F$5:$F$504,請求台帳!$C$5:$C$504,$A11,請求台帳!$B$5:$B$504,">="&E$3,請求台帳!$B$5:$B$504,"<"&DATE(YEAR(E$3),MONTH(E$3)+1,1),請求台帳!$Q$5:$Q$504,"<>取消")) | F11: =IF($A11="","",SUMIFS(入金明細!$E$5:$E$1004,入金明細!$G$5:$G$1004,$A11,入金明細!$B$5:$B$1004,">="&E$3,入金明細!$B$5:$B$1004,"<"&DATE(YEAR(E$3),MONTH(E$3)+1,1))) | G11: =IF($A11="","",SUMIFS(請求台帳!$F$5:$F$504,請求台帳!$C$5:$C$504,$A11,請求台帳!$B$5:$B$504,">="&G$3,請求台帳!$B$5:$B$504,"<"&DATE(YEAR(G$3),MONTH(G$3)+1,1),請求台帳!$Q$5:$Q$504,"<>取消")) | H11: =IF($A11="","",SUMIFS(入金明細!$E$5:$E$1004,入金明細!$G$5:$G$1004,$A11,入金明細!$B$5:$B$1004,">="&G$3,入金明細!$B$5:$B$1004,"<"&DATE(YEAR(G$3),MONTH(G$3)+1,1))) | I11: =IF($A11="","",SUMIFS(請求台帳!$F$5:$F$504,請求台帳!$C$5:$C$504,$A11,請求台帳!$B$5:$B$504,">="&I$3,請求台帳!$B$5:$B$504,"<"&DATE(YEAR(I$3),MONTH(I$3)+1,1),請求台帳!$Q$5:$Q$504,"<>取消")) | J11: =IF($A11="","",SUMIFS(入金明細!$E$5:$E$1004,入金明細!$G$5:$G$1004,$A11,入金明細!$B$5:$B$1004,">="&I$3,入金明細!$B$5:$B$1004,"<"&DATE(YEAR(I$3),MONTH(I$3)+1,1))) | K11: =IF($A11="","",SUMIFS(請求台帳!$F$5:$F$504,請求台帳!$C$5:$C$504,$A11,請求台帳!$B$5:$B$504,">="&K$3,請求台帳!$B$5:$B$504,"<"&DATE(YEAR(K$3),MONTH(K$3)+1,1),請求台帳!$Q$5:$Q$504,"<>取消")) | L11: =IF($A11="","",SUMIFS(入金明細!$E$5:$E$1004,入金明細!$G$5:$G$1004,$A11,入金明細!$B$5:$B$1004,">="&K$3,入金明細!$B$5:$B$1004,"<"&DATE(YEAR(K$3),MONTH(K$3)+1,1))) | M11: =IF($A11="","",SUMIFS(請求台帳!$F$5:$F$504,請求台帳!$C$5:$C$504,$A11,請求台帳!$B$5:$B$504,">="&M$3,請求台帳!$B$5:$B$504,"<"&DATE(YEAR(M$3),MONTH(M$3)+1,1),請求台帳!$Q$5:$Q$504,"<>取消")) | N11: =IF($A11="","",SUMIFS(入金明細!$E$5:$E$1004,入金明細!$G$5:$G$1004,$A11,入金明細!$B$5:$B$1004,">="&M$3,入金明細!$B$5:$B$1004,"<"&DATE(YEAR(M$3),MONTH(M$3)+1,1))) | O11: =IF($A11="","",SUMIFS(請求台帳!$F$5:$F$504,請求台帳!$C$5:$C$504,$A11,請求台帳!$B$5:$B$504,">="&O$3,請求台帳!$B$5:$B$504,"<"&DATE(YEAR(O$3),MONTH(O$3)+1,1),請求台帳!$Q$5:$Q$504,"<>取消")) | P11: =IF($A11="","",SUMIFS(入金明細!$E$5:$E$1004,入金明細!$G$5:$G$1004,$A11,入金明細!$B$5:$B$1004,">="&O$3,入金明細!$B$5:$B$1004,"<"&DATE(YEAR(O$3),MONTH(O$3)+1,1))) | Q11: =IF($A11="","",SUMIFS(請求台帳!$F$5:$F$504,請求台帳!$C$5:$C$504,$A11,請求台帳!$B$5:$B$504,">="&Q$3,請求台帳!$B$5:$B$504,"<"&DATE(YEAR(Q$3),MONTH(Q$3)+1,1),請求台帳!$Q$5:$Q$504,"<>取消")) | R11: =IF($A11="","",SUMIFS(入金明細!$E$5:$E$1004,入金明細!$G$5:$G$1004,$A11,入金明細!$B$5:$B$1004,">="&Q$3,入金明細!$B$5:$B$1004,"<"&DATE(YEAR(Q$3),MONTH(Q$3)+1,1))) | S11: =IF($A11="","",SUMIFS(請求台帳!$F$5:$F$504,請求台帳!$C$5:$C$504,$A11,請求台帳!$B$5:$B$504,">="&S$3,請求台帳!$B$5:$B$504,"<"&DATE(YEAR(S$3),MONTH(S$3)+1,1),請求台帳!$Q$5:$Q$504,"<>取消")) | T11: =IF($A11="","",SUMIFS(入金明細!$E$5:$E$1004,入金明細!$G$5:$G$1004,$A11,入金明細!$B$5:$B$1004,">="&S$3,入金明細!$B$5:$B$1004,"<"&DATE(YEAR(S$3),MONTH(S$3)+1,1))) | U11: =IF($A11="","",SUMIFS(請求台帳!$F$5:$F$504,請求台帳!$C$5:$C$504,$A11,請求台帳!$B$5:$B$504,">="&U$3,請求台帳!$B$5:$B$504,"<"&DATE(YEAR(U$3),MONTH(U$3)+1,1),請求台帳!$Q$5:$Q$504,"<>取消")) | V11: =IF($A11="","",SUMIFS(入金明細!$E$5:$E$1004,入金明細!$G$5:$G$1004,$A11,入金明細!$B$5:$B$1004,">="&U$3,入金明細!$B$5:$B$1004,"<"&DATE(YEAR(U$3),MONTH(U$3)+1,1))) | W11: =IF($A11="","",SUMIFS(請求台帳!$F$5:$F$504,請求台帳!$C$5:$C$504,$A11,請求台帳!$B$5:$B$504,">="&W$3,請求台帳!$B$5:$B$504,"<"&DATE(YEAR(W$3),MONTH(W$3)+1,1),請求台帳!$Q$5:$Q$504,"<>取消")) | X11: =IF($A11="","",SUMIFS(入金明細!$E$5:$E$1004,入金明細!$G$5:$G$1004,$A11,入金明細!$B$5:$B$1004,">="&W$3,入金明細!$B$5:$B$1004,"<"&DATE(YEAR(W$3),MONTH(W$3)+1,1))) | Y11: =IF($A11="","",SUMIFS(請求台帳!$F$5:$F$504,請求台帳!$C$5:$C$504,$A11,請求台帳!$B$5:$B$504,">="&Y$3,請求台帳!$B$5:$B$504,"<"&DATE(YEAR(Y$3),MONTH(Y$3)+1,1),請求台帳!$Q$5:$Q$504,"<>取消")) | Z11: =IF($A11="","",SUMIFS(入金明細!$E$5:$E$1004,入金明細!$G$5:$G$1004,$A11,入金明細!$B$5:$B$1004,">="&Y$3,入金明細!$B$5:$B$1004,"<"&DATE(YEAR(Y$3),MONTH(Y$3)+1,1))) | AA11: =SUM(C11,E11,G11,I11,K11,M11,O11,Q11,S11,U11,W11,Y11) -> 0 | AB11: =SUM(D11,F11,H11,J11,L11,N11,P11,R11,T11,V11,X11,Z11) -> 0
A12: =IF(取引先マスタ!A12="","",取引先マスタ!A12) | B12: =IF(A12="","",取引先マスタ!B12) | C12: =IF($A12="","",SUMIFS(請求台帳!$F$5:$F$504,請求台帳!$C$5:$C$504,$A12,請求台帳!$B$5:$B$504,">="&C$3,請求台帳!$B$5:$B$504,"<"&DATE(YEAR(C$3),MONTH(C$3)+1,1),請求台帳!$Q$5:$Q$504,"<>取消")) | D12: =IF($A12="","",SUMIFS(入金明細!$E$5:$E$1004,入金明細!$G$5:$G$1004,$A12,入金明細!$B$5:$B$1004,">="&C$3,入金明細!$B$5:$B$1004,"<"&DATE(YEAR(C$3),MONTH(C$3)+1,1))) | E12: =IF($A12="","",SUMIFS(請求台帳!$F$5:$F$504,請求台帳!$C$5:$C$504,$A12,請求台帳!$B$5:$B$504,">="&E$3,請求台帳!$B$5:$B$504,"<"&DATE(YEAR(E$3),MONTH(E$3)+1,1),請求台帳!$Q$5:$Q$504,"<>取消")) | F12: =IF($A12="","",SUMIFS(入金明細!$E$5:$E$1004,入金明細!$G$5:$G$1004,$A12,入金明細!$B$5:$B$1004,">="&E$3,入金明細!$B$5:$B$1004,"<"&DATE(YEAR(E$3),MONTH(E$3)+1,1))) | G12: =IF($A12="","",SUMIFS(請求台帳!$F$5:$F$504,請求台帳!$C$5:$C$504,$A12,請求台帳!$B$5:$B$504,">="&G$3,請求台帳!$B$5:$B$504,"<"&DATE(YEAR(G$3),MONTH(G$3)+1,1),請求台帳!$Q$5:$Q$504,"<>取消")) | H12: =IF($A12="","",SUMIFS(入金明細!$E$5:$E$1004,入金明細!$G$5:$G$1004,$A12,入金明細!$B$5:$B$1004,">="&G$3,入金明細!$B$5:$B$1004,"<"&DATE(YEAR(G$3),MONTH(G$3)+1,1))) | I12: =IF($A12="","",SUMIFS(請求台帳!$F$5:$F$504,請求台帳!$C$5:$C$504,$A12,請求台帳!$B$5:$B$504,">="&I$3,請求台帳!$B$5:$B$504,"<"&DATE(YEAR(I$3),MONTH(I$3)+1,1),請求台帳!$Q$5:$Q$504,"<>取消")) | J12: =IF($A12="","",SUMIFS(入金明細!$E$5:$E$1004,入金明細!$G$5:$G$1004,$A12,入金明細!$B$5:$B$1004,">="&I$3,入金明細!$B$5:$B$1004,"<"&DATE(YEAR(I$3),MONTH(I$3)+1,1))) | K12: =IF($A12="","",SUMIFS(請求台帳!$F$5:$F$504,請求台帳!$C$5:$C$504,$A12,請求台帳!$B$5:$B$504,">="&K$3,請求台帳!$B$5:$B$504,"<"&DATE(YEAR(K$3),MONTH(K$3)+1,1),請求台帳!$Q$5:$Q$504,"<>取消")) | L12: =IF($A12="","",SUMIFS(入金明細!$E$5:$E$1004,入金明細!$G$5:$G$1004,$A12,入金明細!$B$5:$B$1004,">="&K$3,入金明細!$B$5:$B$1004,"<"&DATE(YEAR(K$3),MONTH(K$3)+1,1))) | M12: =IF($A12="","",SUMIFS(請求台帳!$F$5:$F$504,請求台帳!$C$5:$C$504,$A12,請求台帳!$B$5:$B$504,">="&M$3,請求台帳!$B$5:$B$504,"<"&DATE(YEAR(M$3),MONTH(M$3)+1,1),請求台帳!$Q$5:$Q$504,"<>取消")) | N12: =IF($A12="","",SUMIFS(入金明細!$E$5:$E$1004,入金明細!$G$5:$G$1004,$A12,入金明細!$B$5:$B$1004,">="&M$3,入金明細!$B$5:$B$1004,"<"&DATE(YEAR(M$3),MONTH(M$3)+1,1))) | O12: =IF($A12="","",SUMIFS(請求台帳!$F$5:$F$504,請求台帳!$C$5:$C$504,$A12,請求台帳!$B$5:$B$504,">="&O$3,請求台帳!$B$5:$B$504,"<"&DATE(YEAR(O$3),MONTH(O$3)+1,1),請求台帳!$Q$5:$Q$504,"<>取消")) | P12: =IF($A12="","",SUMIFS(入金明細!$E$5:$E$1004,入金明細!$G$5:$G$1004,$A12,入金明細!$B$5:$B$1004,">="&O$3,入金明細!$B$5:$B$1004,"<"&DATE(YEAR(O$3),MONTH(O$3)+1,1))) | Q12: =IF($A12="","",SUMIFS(請求台帳!$F$5:$F$504,請求台帳!$C$5:$C$504,$A12,請求台帳!$B$5:$B$504,">="&Q$3,請求台帳!$B$5:$B$504,"<"&DATE(YEAR(Q$3),MONTH(Q$3)+1,1),請求台帳!$Q$5:$Q$504,"<>取消")) | R12: =IF($A12="","",SUMIFS(入金明細!$E$5:$E$1004,入金明細!$G$5:$G$1004,$A12,入金明細!$B$5:$B$1004,">="&Q$3,入金明細!$B$5:$B$1004,"<"&DATE(YEAR(Q$3),MONTH(Q$3)+1,1))) | S12: =IF($A12="","",SUMIFS(請求台帳!$F$5:$F$504,請求台帳!$C$5:$C$504,$A12,請求台帳!$B$5:$B$504,">="&S$3,請求台帳!$B$5:$B$504,"<"&DATE(YEAR(S$3),MONTH(S$3)+1,1),請求台帳!$Q$5:$Q$504,"<>取消")) | T12: =IF($A12="","",SUMIFS(入金明細!$E$5:$E$1004,入金明細!$G$5:$G$1004,$A12,入金明細!$B$5:$B$1004,">="&S$3,入金明細!$B$5:$B$1004,"<"&DATE(YEAR(S$3),MONTH(S$3)+1,1))) | U12: =IF($A12="","",SUMIFS(請求台帳!$F$5:$F$504,請求台帳!$C$5:$C$504,$A12,請求台帳!$B$5:$B$504,">="&U$3,請求台帳!$B$5:$B$504,"<"&DATE(YEAR(U$3),MONTH(U$3)+1,1),請求台帳!$Q$5:$Q$504,"<>取消")) | V12: =IF($A12="","",SUMIFS(入金明細!$E$5:$E$1004,入金明細!$G$5:$G$1004,$A12,入金明細!$B$5:$B$1004,">="&U$3,入金明細!$B$5:$B$1004,"<"&DATE(YEAR(U$3),MONTH(U$3)+1,1))) | W12: =IF($A12="","",SUMIFS(請求台帳!$F$5:$F$504,請求台帳!$C$5:$C$504,$A12,請求台帳!$B$5:$B$504,">="&W$3,請求台帳!$B$5:$B$504,"<"&DATE(YEAR(W$3),MONTH(W$3)+1,1),請求台帳!$Q$5:$Q$504,"<>取消")) | X12: =IF($A12="","",SUMIFS(入金明細!$E$5:$E$1004,入金明細!$G$5:$G$1004,$A12,入金明細!$B$5:$B$1004,">="&W$3,入金明細!$B$5:$B$1004,"<"&DATE(YEAR(W$3),MONTH(W$3)+1,1))) | Y12: =IF($A12="","",SUMIFS(請求台帳!$F$5:$F$504,請求台帳!$C$5:$C$504,$A12,請求台帳!$B$5:$B$504,">="&Y$3,請求台帳!$B$5:$B$504,"<"&DATE(YEAR(Y$3),MONTH(Y$3)+1,1),請求台帳!$Q$5:$Q$504,"<>取消")) | Z12: =IF($A12="","",SUMIFS(入金明細!$E$5:$E$1004,入金明細!$G$5:$G$1004,$A12,入金明細!$B$5:$B$1004,">="&Y$3,入金明細!$B$5:$B$1004,"<"&DATE(YEAR(Y$3),MONTH(Y$3)+1,1))) | AA12: =SUM(C12,E12,G12,I12,K12,M12,O12,Q12,S12,U12,W12,Y12) -> 0 | AB12: =SUM(D12,F12,H12,J12,L12,N12,P12,R12,T12,V12,X12,Z12) -> 0
A13: =IF(取引先マスタ!A13="","",取引先マスタ!A13) | B13: =IF(A13="","",取引先マスタ!B13) | C13: =IF($A13="","",SUMIFS(請求台帳!$F$5:$F$504,請求台帳!$C$5:$C$504,$A13,請求台帳!$B$5:$B$504,">="&C$3,請求台帳!$B$5:$B$504,"<"&DATE(YEAR(C$3),MONTH(C$3)+1,1),請求台帳!$Q$5:$Q$504,"<>取消")) | D13: =IF($A13="","",SUMIFS(入金明細!$E$5:$E$1004,入金明細!$G$5:$G$1004,$A13,入金明細!$B$5:$B$1004,">="&C$3,入金明細!$B$5:$B$1004,"<"&DATE(YEAR(C$3),MONTH(C$3)+1,1))) | E13: =IF($A13="","",SUMIFS(請求台帳!$F$5:$F$504,請求台帳!$C$5:$C$504,$A13,請求台帳!$B$5:$B$504,">="&E$3,請求台帳!$B$5:$B$504,"<"&DATE(YEAR(E$3),MONTH(E$3)+1,1),請求台帳!$Q$5:$Q$504,"<>取消")) | F13: =IF($A13="","",SUMIFS(入金明細!$E$5:$E$1004,入金明細!$G$5:$G$1004,$A13,入金明細!$B$5:$B$1004,">="&E$3,入金明細!$B$5:$B$1004,"<"&DATE(YEAR(E$3),MONTH(E$3)+1,1))) | G13: =IF($A13="","",SUMIFS(請求台帳!$F$5:$F$504,請求台帳!$C$5:$C$504,$A13,請求台帳!$B$5:$B$504,">="&G$3,請求台帳!$B$5:$B$504,"<"&DATE(YEAR(G$3),MONTH(G$3)+1,1),請求台帳!$Q$5:$Q$504,"<>取消")) | H13: =IF($A13="","",SUMIFS(入金明細!$E$5:$E$1004,入金明細!$G$5:$G$1004,$A13,入金明細!$B$5:$B$1004,">="&G$3,入金明細!$B$5:$B$1004,"<"&DATE(YEAR(G$3),MONTH(G$3)+1,1))) | I13: =IF($A13="","",SUMIFS(請求台帳!$F$5:$F$504,請求台帳!$C$5:$C$504,$A13,請求台帳!$B$5:$B$504,">="&I$3,請求台帳!$B$5:$B$504,"<"&DATE(YEAR(I$3),MONTH(I$3)+1,1),請求台帳!$Q$5:$Q$504,"<>取消")) | J13: =IF($A13="","",SUMIFS(入金明細!$E$5:$E$1004,入金明細!$G$5:$G$1004,$A13,入金明細!$B$5:$B$1004,">="&I$3,入金明細!$B$5:$B$1004,"<"&DATE(YEAR(I$3),MONTH(I$3)+1,1))) | K13: =IF($A13="","",SUMIFS(請求台帳!$F$5:$F$504,請求台帳!$C$5:$C$504,$A13,請求台帳!$B$5:$B$504,">="&K$3,請求台帳!$B$5:$B$504,"<"&DATE(YEAR(K$3),MONTH(K$3)+1,1),請求台帳!$Q$5:$Q$504,"<>取消")) | L13: =IF($A13="","",SUMIFS(入金明細!$E$5:$E$1004,入金明細!$G$5:$G$1004,$A13,入金明細!$B$5:$B$1004,">="&K$3,入金明細!$B$5:$B$1004,"<"&DATE(YEAR(K$3),MONTH(K$3)+1,1))) | M13: =IF($A13="","",SUMIFS(請求台帳!$F$5:$F$504,請求台帳!$C$5:$C$504,$A13,請求台帳!$B$5:$B$504,">="&M$3,請求台帳!$B$5:$B$504,"<"&DATE(YEAR(M$3),MONTH(M$3)+1,1),請求台帳!$Q$5:$Q$504,"<>取消")) | N13: =IF($A13="","",SUMIFS(入金明細!$E$5:$E$1004,入金明細!$G$5:$G$1004,$A13,入金明細!$B$5:$B$1004,">="&M$3,入金明細!$B$5:$B$1004,"<"&DATE(YEAR(M$3),MONTH(M$3)+1,1))) | O13: =IF($A13="","",SUMIFS(請求台帳!$F$5:$F$504,請求台帳!$C$5:$C$504,$A13,請求台帳!$B$5:$B$504,">="&O$3,請求台帳!$B$5:$B$504,"<"&DATE(YEAR(O$3),MONTH(O$3)+1,1),請求台帳!$Q$5:$Q$504,"<>取消")) | P13: =IF($A13="","",SUMIFS(入金明細!$E$5:$E$1004,入金明細!$G$5:$G$1004,$A13,入金明細!$B$5:$B$1004,">="&O$3,入金明細!$B$5:$B$1004,"<"&DATE(YEAR(O$3),MONTH(O$3)+1,1))) | Q13: =IF($A13="","",SUMIFS(請求台帳!$F$5:$F$504,請求台帳!$C$5:$C$504,$A13,請求台帳!$B$5:$B$504,">="&Q$3,請求台帳!$B$5:$B$504,"<"&DATE(YEAR(Q$3),MONTH(Q$3)+1,1),請求台帳!$Q$5:$Q$504,"<>取消")) | R13: =IF($A13="","",SUMIFS(入金明細!$E$5:$E$1004,入金明細!$G$5:$G$1004,$A13,入金明細!$B$5:$B$1004,">="&Q$3,入金明細!$B$5:$B$1004,"<"&DATE(YEAR(Q$3),MONTH(Q$3)+1,1))) | S13: =IF($A13="","",SUMIFS(請求台帳!$F$5:$F$504,請求台帳!$C$5:$C$504,$A13,請求台帳!$B$5:$B$504,">="&S$3,請求台帳!$B$5:$B$504,"<"&DATE(YEAR(S$3),MONTH(S$3)+1,1),請求台帳!$Q$5:$Q$504,"<>取消")) | T13: =IF($A13="","",SUMIFS(入金明細!$E$5:$E$1004,入金明細!$G$5:$G$1004,$A13,入金明細!$B$5:$B$1004,">="&S$3,入金明細!$B$5:$B$1004,"<"&DATE(YEAR(S$3),MONTH(S$3)+1,1))) | U13: =IF($A13="","",SUMIFS(請求台帳!$F$5:$F$504,請求台帳!$C$5:$C$504,$A13,請求台帳!$B$5:$B$504,">="&U$3,請求台帳!$B$5:$B$504,"<"&DATE(YEAR(U$3),MONTH(U$3)+1,1),請求台帳!$Q$5:$Q$504,"<>取消")) | V13: =IF($A13="","",SUMIFS(入金明細!$E$5:$E$1004,入金明細!$G$5:$G$1004,$A13,入金明細!$B$5:$B$1004,">="&U$3,入金明細!$B$5:$B$1004,"<"&DATE(YEAR(U$3),MONTH(U$3)+1,1))) | W13: =IF($A13="","",SUMIFS(請求台帳!$F$5:$F$504,請求台帳!$C$5:$C$504,$A13,請求台帳!$B$5:$B$504,">="&W$3,請求台帳!$B$5:$B$504,"<"&DATE(YEAR(W$3),MONTH(W$3)+1,1),請求台帳!$Q$5:$Q$504,"<>取消")) | X13: =IF($A13="","",SUMIFS(入金明細!$E$5:$E$1004,入金明細!$G$5:$G$1004,$A13,入金明細!$B$5:$B$1004,">="&W$3,入金明細!$B$5:$B$1004,"<"&DATE(YEAR(W$3),MONTH(W$3)+1,1))) | Y13: =IF($A13="","",SUMIFS(請求台帳!$F$5:$F$504,請求台帳!$C$5:$C$504,$A13,請求台帳!$B$5:$B$504,">="&Y$3,請求台帳!$B$5:$B$504,"<"&DATE(YEAR(Y$3),MONTH(Y$3)+1,1),請求台帳!$Q$5:$Q$504,"<>取消")) | Z13: =IF($A13="","",SUMIFS(入金明細!$E$5:$E$1004,入金明細!$G$5:$G$1004,$A13,入金明細!$B$5:$B$1004,">="&Y$3,入金明細!$B$5:$B$1004,"<"&DATE(YEAR(Y$3),MONTH(Y$3)+1,1))) | AA13: =SUM(C13,E13,G13,I13,K13,M13,O13,Q13,S13,U13,W13,Y13) -> 0 | AB13: =SUM(D13,F13,H13,J13,L13,N13,P13,R13,T13,V13,X13,Z13) -> 0
A14: =IF(取引先マスタ!A14="","",取引先マスタ!A14) | B14: =IF(A14="","",取引先マスタ!B14) | C14: =IF($A14="","",SUMIFS(請求台帳!$F$5:$F$504,請求台帳!$C$5:$C$504,$A14,請求台帳!$B$5:$B$504,">="&C$3,請求台帳!$B$5:$B$504,"<"&DATE(YEAR(C$3),MONTH(C$3)+1,1),請求台帳!$Q$5:$Q$504,"<>取消")) | D14: =IF($A14="","",SUMIFS(入金明細!$E$5:$E$1004,入金明細!$G$5:$G$1004,$A14,入金明細!$B$5:$B$1004,">="&C$3,入金明細!$B$5:$B$1004,"<"&DATE(YEAR(C$3),MONTH(C$3)+1,1))) | E14: =IF($A14="","",SUMIFS(請求台帳!$F$5:$F$504,請求台帳!$C$5:$C$504,$A14,請求台帳!$B$5:$B$504,">="&E$3,請求台帳!$B$5:$B$504,"<"&DATE(YEAR(E$3),MONTH(E$3)+1,1),請求台帳!$Q$5:$Q$504,"<>取消")) | F14: =IF($A14="","",SUMIFS(入金明細!$E$5:$E$1004,入金明細!$G$5:$G$1004,$A14,入金明細!$B$5:$B$1004,">="&E$3,入金明細!$B$5:$B$1004,"<"&DATE(YEAR(E$3),MONTH(E$3)+1,1))) | G14: =IF($A14="","",SUMIFS(請求台帳!$F$5:$F$504,請求台帳!$C$5:$C$504,$A14,請求台帳!$B$5:$B$504,">="&G$3,請求台帳!$B$5:$B$504,"<"&DATE(YEAR(G$3),MONTH(G$3)+1,1),請求台帳!$Q$5:$Q$504,"<>取消")) | H14: =IF($A14="","",SUMIFS(入金明細!$E$5:$E$1004,入金明細!$G$5:$G$1004,$A14,入金明細!$B$5:$B$1004,">="&G$3,入金明細!$B$5:$B$1004,"<"&DATE(YEAR(G$3),MONTH(G$3)+1,1))) | I14: =IF($A14="","",SUMIFS(請求台帳!$F$5:$F$504,請求台帳!$C$5:$C$504,$A14,請求台帳!$B$5:$B$504,">="&I$3,請求台帳!$B$5:$B$504,"<"&DATE(YEAR(I$3),MONTH(I$3)+1,1),請求台帳!$Q$5:$Q$504,"<>取消")) | J14: =IF($A14="","",SUMIFS(入金明細!$E$5:$E$1004,入金明細!$G$5:$G$1004,$A14,入金明細!$B$5:$B$1004,">="&I$3,入金明細!$B$5:$B$1004,"<"&DATE(YEAR(I$3),MONTH(I$3)+1,1))) | K14: =IF($A14="","",SUMIFS(請求台帳!$F$5:$F$504,請求台帳!$C$5:$C$504,$A14,請求台帳!$B$5:$B$504,">="&K$3,請求台帳!$B$5:$B$504,"<"&DATE(YEAR(K$3),MONTH(K$3)+1,1),請求台帳!$Q$5:$Q$504,"<>取消")) | L14: =IF($A14="","",SUMIFS(入金明細!$E$5:$E$1004,入金明細!$G$5:$G$1004,$A14,入金明細!$B$5:$B$1004,">="&K$3,入金明細!$B$5:$B$1004,"<"&DATE(YEAR(K$3),MONTH(K$3)+1,1))) | M14: =IF($A14="","",SUMIFS(請求台帳!$F$5:$F$504,請求台帳!$C$5:$C$504,$A14,請求台帳!$B$5:$B$504,">="&M$3,請求台帳!$B$5:$B$504,"<"&DATE(YEAR(M$3),MONTH(M$3)+1,1),請求台帳!$Q$5:$Q$504,"<>取消")) | N14: =IF($A14="","",SUMIFS(入金明細!$E$5:$E$1004,入金明細!$G$5:$G$1004,$A14,入金明細!$B$5:$B$1004,">="&M$3,入金明細!$B$5:$B$1004,"<"&DATE(YEAR(M$3),MONTH(M$3)+1,1))) | O14: =IF($A14="","",SUMIFS(請求台帳!$F$5:$F$504,請求台帳!$C$5:$C$504,$A14,請求台帳!$B$5:$B$504,">="&O$3,請求台帳!$B$5:$B$504,"<"&DATE(YEAR(O$3),MONTH(O$3)+1,1),請求台帳!$Q$5:$Q$504,"<>取消")) | P14: =IF($A14="","",SUMIFS(入金明細!$E$5:$E$1004,入金明細!$G$5:$G$1004,$A14,入金明細!$B$5:$B$1004,">="&O$3,入金明細!$B$5:$B$1004,"<"&DATE(YEAR(O$3),MONTH(O$3)+1,1))) | Q14: =IF($A14="","",SUMIFS(請求台帳!$F$5:$F$504,請求台帳!$C$5:$C$504,$A14,請求台帳!$B$5:$B$504,">="&Q$3,請求台帳!$B$5:$B$504,"<"&DATE(YEAR(Q$3),MONTH(Q$3)+1,1),請求台帳!$Q$5:$Q$504,"<>取消")) | R14: =IF($A14="","",SUMIFS(入金明細!$E$5:$E$1004,入金明細!$G$5:$G$1004,$A14,入金明細!$B$5:$B$1004,">="&Q$3,入金明細!$B$5:$B$1004,"<"&DATE(YEAR(Q$3),MONTH(Q$3)+1,1))) | S14: =IF($A14="","",SUMIFS(請求台帳!$F$5:$F$504,請求台帳!$C$5:$C$504,$A14,請求台帳!$B$5:$B$504,">="&S$3,請求台帳!$B$5:$B$504,"<"&DATE(YEAR(S$3),MONTH(S$3)+1,1),請求台帳!$Q$5:$Q$504,"<>取消")) | T14: =IF($A14="","",SUMIFS(入金明細!$E$5:$E$1004,入金明細!$G$5:$G$1004,$A14,入金明細!$B$5:$B$1004,">="&S$3,入金明細!$B$5:$B$1004,"<"&DATE(YEAR(S$3),MONTH(S$3)+1,1))) | U14: =IF($A14="","",SUMIFS(請求台帳!$F$5:$F$504,請求台帳!$C$5:$C$504,$A14,請求台帳!$B$5:$B$504,">="&U$3,請求台帳!$B$5:$B$504,"<"&DATE(YEAR(U$3),MONTH(U$3)+1,1),請求台帳!$Q$5:$Q$504,"<>取消")) | V14: =IF($A14="","",SUMIFS(入金明細!$E$5:$E$1004,入金明細!$G$5:$G$1004,$A14,入金明細!$B$5:$B$1004,">="&U$3,入金明細!$B$5:$B$1004,"<"&DATE(YEAR(U$3),MONTH(U$3)+1,1))) | W14: =IF($A14="","",SUMIFS(請求台帳!$F$5:$F$504,請求台帳!$C$5:$C$504,$A14,請求台帳!$B$5:$B$504,">="&W$3,請求台帳!$B$5:$B$504,"<"&DATE(YEAR(W$3),MONTH(W$3)+1,1),請求台帳!$Q$5:$Q$504,"<>取消")) | X14: =IF($A14="","",SUMIFS(入金明細!$E$5:$E$1004,入金明細!$G$5:$G$1004,$A14,入金明細!$B$5:$B$1004,">="&W$3,入金明細!$B$5:$B$1004,"<"&DATE(YEAR(W$3),MONTH(W$3)+1,1))) | Y14: =IF($A14="","",SUMIFS(請求台帳!$F$5:$F$504,請求台帳!$C$5:$C$504,$A14,請求台帳!$B$5:$B$504,">="&Y$3,請求台帳!$B$5:$B$504,"<"&DATE(YEAR(Y$3),MONTH(Y$3)+1,1),請求台帳!$Q$5:$Q$504,"<>取消")) | Z14: =IF($A14="","",SUMIFS(入金明細!$E$5:$E$1004,入金明細!$G$5:$G$1004,$A14,入金明細!$B$5:$B$1004,">="&Y$3,入金明細!$B$5:$B$1004,"<"&DATE(YEAR(Y$3),MONTH(Y$3)+1,1))) | AA14: =SUM(C14,E14,G14,I14,K14,M14,O14,Q14,S14,U14,W14,Y14) -> 0 | AB14: =SUM(D14,F14,H14,J14,L14,N14,P14,R14,T14,V14,X14,Z14) -> 0
A15: =IF(取引先マスタ!A15="","",取引先マスタ!A15) | B15: =IF(A15="","",取引先マスタ!B15) | C15: =IF($A15="","",SUMIFS(請求台帳!$F$5:$F$504,請求台帳!$C$5:$C$504,$A15,請求台帳!$B$5:$B$504,">="&C$3,請求台帳!$B$5:$B$504,"<"&DATE(YEAR(C$3),MONTH(C$3)+1,1),請求台帳!$Q$5:$Q$504,"<>取消")) | D15: =IF($A15="","",SUMIFS(入金明細!$E$5:$E$1004,入金明細!$G$5:$G$1004,$A15,入金明細!$B$5:$B$1004,">="&C$3,入金明細!$B$5:$B$1004,"<"&DATE(YEAR(C$3),MONTH(C$3)+1,1))) | E15: =IF($A15="","",SUMIFS(請求台帳!$F$5:$F$504,請求台帳!$C$5:$C$504,$A15,請求台帳!$B$5:$B$504,">="&E$3,請求台帳!$B$5:$B$504,"<"&DATE(YEAR(E$3),MONTH(E$3)+1,1),請求台帳!$Q$5:$Q$504,"<>取消")) | F15: =IF($A15="","",SUMIFS(入金明細!$E$5:$E$1004,入金明細!$G$5:$G$1004,$A15,入金明細!$B$5:$B$1004,">="&E$3,入金明細!$B$5:$B$1004,"<"&DATE(YEAR(E$3),MONTH(E$3)+1,1))) | G15: =IF($A15="","",SUMIFS(請求台帳!$F$5:$F$504,請求台帳!$C$5:$C$504,$A15,請求台帳!$B$5:$B$504,">="&G$3,請求台帳!$B$5:$B$504,"<"&DATE(YEAR(G$3),MONTH(G$3)+1,1),請求台帳!$Q$5:$Q$504,"<>取消")) | H15: =IF($A15="","",SUMIFS(入金明細!$E$5:$E$1004,入金明細!$G$5:$G$1004,$A15,入金明細!$B$5:$B$1004,">="&G$3,入金明細!$B$5:$B$1004,"<"&DATE(YEAR(G$3),MONTH(G$3)+1,1))) | I15: =IF($A15="","",SUMIFS(請求台帳!$F$5:$F$504,請求台帳!$C$5:$C$504,$A15,請求台帳!$B$5:$B$504,">="&I$3,請求台帳!$B$5:$B$504,"<"&DATE(YEAR(I$3),MONTH(I$3)+1,1),請求台帳!$Q$5:$Q$504,"<>取消")) | J15: =IF($A15="","",SUMIFS(入金明細!$E$5:$E$1004,入金明細!$G$5:$G$1004,$A15,入金明細!$B$5:$B$1004,">="&I$3,入金明細!$B$5:$B$1004,"<"&DATE(YEAR(I$3),MONTH(I$3)+1,1))) | K15: =IF($A15="","",SUMIFS(請求台帳!$F$5:$F$504,請求台帳!$C$5:$C$504,$A15,請求台帳!$B$5:$B$504,">="&K$3,請求台帳!$B$5:$B$504,"<"&DATE(YEAR(K$3),MONTH(K$3)+1,1),請求台帳!$Q$5:$Q$504,"<>取消")) | L15: =IF($A15="","",SUMIFS(入金明細!$E$5:$E$1004,入金明細!$G$5:$G$1004,$A15,入金明細!$B$5:$B$1004,">="&K$3,入金明細!$B$5:$B$1004,"<"&DATE(YEAR(K$3),MONTH(K$3)+1,1))) | M15: =IF($A15="","",SUMIFS(請求台帳!$F$5:$F$504,請求台帳!$C$5:$C$504,$A15,請求台帳!$B$5:$B$504,">="&M$3,請求台帳!$B$5:$B$504,"<"&DATE(YEAR(M$3),MONTH(M$3)+1,1),請求台帳!$Q$5:$Q$504,"<>取消")) | N15: =IF($A15="","",SUMIFS(入金明細!$E$5:$E$1004,入金明細!$G$5:$G$1004,$A15,入金明細!$B$5:$B$1004,">="&M$3,入金明細!$B$5:$B$1004,"<"&DATE(YEAR(M$3),MONTH(M$3)+1,1))) | O15: =IF($A15="","",SUMIFS(請求台帳!$F$5:$F$504,請求台帳!$C$5:$C$504,$A15,請求台帳!$B$5:$B$504,">="&O$3,請求台帳!$B$5:$B$504,"<"&DATE(YEAR(O$3),MONTH(O$3)+1,1),請求台帳!$Q$5:$Q$504,"<>取消")) | P15: =IF($A15="","",SUMIFS(入金明細!$E$5:$E$1004,入金明細!$G$5:$G$1004,$A15,入金明細!$B$5:$B$1004,">="&O$3,入金明細!$B$5:$B$1004,"<"&DATE(YEAR(O$3),MONTH(O$3)+1,1))) | Q15: =IF($A15="","",SUMIFS(請求台帳!$F$5:$F$504,請求台帳!$C$5:$C$504,$A15,請求台帳!$B$5:$B$504,">="&Q$3,請求台帳!$B$5:$B$504,"<"&DATE(YEAR(Q$3),MONTH(Q$3)+1,1),請求台帳!$Q$5:$Q$504,"<>取消")) | R15: =IF($A15="","",SUMIFS(入金明細!$E$5:$E$1004,入金明細!$G$5:$G$1004,$A15,入金明細!$B$5:$B$1004,">="&Q$3,入金明細!$B$5:$B$1004,"<"&DATE(YEAR(Q$3),MONTH(Q$3)+1,1))) | S15: =IF($A15="","",SUMIFS(請求台帳!$F$5:$F$504,請求台帳!$C$5:$C$504,$A15,請求台帳!$B$5:$B$504,">="&S$3,請求台帳!$B$5:$B$504,"<"&DATE(YEAR(S$3),MONTH(S$3)+1,1),請求台帳!$Q$5:$Q$504,"<>取消")) | T15: =IF($A15="","",SUMIFS(入金明細!$E$5:$E$1004,入金明細!$G$5:$G$1004,$A15,入金明細!$B$5:$B$1004,">="&S$3,入金明細!$B$5:$B$1004,"<"&DATE(YEAR(S$3),MONTH(S$3)+1,1))) | U15: =IF($A15="","",SUMIFS(請求台帳!$F$5:$F$504,請求台帳!$C$5:$C$504,$A15,請求台帳!$B$5:$B$504,">="&U$3,請求台帳!$B$5:$B$504,"<"&DATE(YEAR(U$3),MONTH(U$3)+1,1),請求台帳!$Q$5:$Q$504,"<>取消")) | V15: =IF($A15="","",SUMIFS(入金明細!$E$5:$E$1004,入金明細!$G$5:$G$1004,$A15,入金明細!$B$5:$B$1004,">="&U$3,入金明細!$B$5:$B$1004,"<"&DATE(YEAR(U$3),MONTH(U$3)+1,1))) | W15: =IF($A15="","",SUMIFS(請求台帳!$F$5:$F$504,請求台帳!$C$5:$C$504,$A15,請求台帳!$B$5:$B$504,">="&W$3,請求台帳!$B$5:$B$504,"<"&DATE(YEAR(W$3),MONTH(W$3)+1,1),請求台帳!$Q$5:$Q$504,"<>取消")) | X15: =IF($A15="","",SUMIFS(入金明細!$E$5:$E$1004,入金明細!$G$5:$G$1004,$A15,入金明細!$B$5:$B$1004,">="&W$3,入金明細!$B$5:$B$1004,"<"&DATE(YEAR(W$3),MONTH(W$3)+1,1))) | Y15: =IF($A15="","",SUMIFS(請求台帳!$F$5:$F$504,請求台帳!$C$5:$C$504,$A15,請求台帳!$B$5:$B$504,">="&Y$3,請求台帳!$B$5:$B$504,"<"&DATE(YEAR(Y$3),MONTH(Y$3)+1,1),請求台帳!$Q$5:$Q$504,"<>取消")) | Z15: =IF($A15="","",SUMIFS(入金明細!$E$5:$E$1004,入金明細!$G$5:$G$1004,$A15,入金明細!$B$5:$B$1004,">="&Y$3,入金明細!$B$5:$B$1004,"<"&DATE(YEAR(Y$3),MONTH(Y$3)+1,1))) | AA15: =SUM(C15,E15,G15,I15,K15,M15,O15,Q15,S15,U15,W15,Y15) -> 0 | AB15: =SUM(D15,F15,H15,J15,L15,N15,P15,R15,T15,V15,X15,Z15) -> 0
A16: =IF(取引先マスタ!A16="","",取引先マスタ!A16) | B16: =IF(A16="","",取引先マスタ!B16) | C16: =IF($A16="","",SUMIFS(請求台帳!$F$5:$F$504,請求台帳!$C$5:$C$504,$A16,請求台帳!$B$5:$B$504,">="&C$3,請求台帳!$B$5:$B$504,"<"&DATE(YEAR(C$3),MONTH(C$3)+1,1),請求台帳!$Q$5:$Q$504,"<>取消")) | D16: =IF($A16="","",SUMIFS(入金明細!$E$5:$E$1004,入金明細!$G$5:$G$1004,$A16,入金明細!$B$5:$B$1004,">="&C$3,入金明細!$B$5:$B$1004,"<"&DATE(YEAR(C$3),MONTH(C$3)+1,1))) | E16: =IF($A16="","",SUMIFS(請求台帳!$F$5:$F$504,請求台帳!$C$5:$C$504,$A16,請求台帳!$B$5:$B$504,">="&E$3,請求台帳!$B$5:$B$504,"<"&DATE(YEAR(E$3),MONTH(E$3)+1,1),請求台帳!$Q$5:$Q$504,"<>取消")) | F16: =IF($A16="","",SUMIFS(入金明細!$E$5:$E$1004,入金明細!$G$5:$G$1004,$A16,入金明細!$B$5:$B$1004,">="&E$3,入金明細!$B$5:$B$1004,"<"&DATE(YEAR(E$3),MONTH(E$3)+1,1))) | G16: =IF($A16="","",SUMIFS(請求台帳!$F$5:$F$504,請求台帳!$C$5:$C$504,$A16,請求台帳!$B$5:$B$504,">="&G$3,請求台帳!$B$5:$B$504,"<"&DATE(YEAR(G$3),MONTH(G$3)+1,1),請求台帳!$Q$5:$Q$504,"<>取消")) | H16: =IF($A16="","",SUMIFS(入金明細!$E$5:$E$1004,入金明細!$G$5:$G$1004,$A16,入金明細!$B$5:$B$1004,">="&G$3,入金明細!$B$5:$B$1004,"<"&DATE(YEAR(G$3),MONTH(G$3)+1,1))) | I16: =IF($A16="","",SUMIFS(請求台帳!$F$5:$F$504,請求台帳!$C$5:$C$504,$A16,請求台帳!$B$5:$B$504,">="&I$3,請求台帳!$B$5:$B$504,"<"&DATE(YEAR(I$3),MONTH(I$3)+1,1),請求台帳!$Q$5:$Q$504,"<>取消")) | J16: =IF($A16="","",SUMIFS(入金明細!$E$5:$E$1004,入金明細!$G$5:$G$1004,$A16,入金明細!$B$5:$B$1004,">="&I$3,入金明細!$B$5:$B$1004,"<"&DATE(YEAR(I$3),MONTH(I$3)+1,1))) | K16: =IF($A16="","",SUMIFS(請求台帳!$F$5:$F$504,請求台帳!$C$5:$C$504,$A16,請求台帳!$B$5:$B$504,">="&K$3,請求台帳!$B$5:$B$504,"<"&DATE(YEAR(K$3),MONTH(K$3)+1,1),請求台帳!$Q$5:$Q$504,"<>取消")) | L16: =IF($A16="","",SUMIFS(入金明細!$E$5:$E$1004,入金明細!$G$5:$G$1004,$A16,入金明細!$B$5:$B$1004,">="&K$3,入金明細!$B$5:$B$1004,"<"&DATE(YEAR(K$3),MONTH(K$3)+1,1))) | M16: =IF($A16="","",SUMIFS(請求台帳!$F$5:$F$504,請求台帳!$C$5:$C$504,$A16,請求台帳!$B$5:$B$504,">="&M$3,請求台帳!$B$5:$B$504,"<"&DATE(YEAR(M$3),MONTH(M$3)+1,1),請求台帳!$Q$5:$Q$504,"<>取消")) | N16: =IF($A16="","",SUMIFS(入金明細!$E$5:$E$1004,入金明細!$G$5:$G$1004,$A16,入金明細!$B$5:$B$1004,">="&M$3,入金明細!$B$5:$B$1004,"<"&DATE(YEAR(M$3),MONTH(M$3)+1,1))) | O16: =IF($A16="","",SUMIFS(請求台帳!$F$5:$F$504,請求台帳!$C$5:$C$504,$A16,請求台帳!$B$5:$B$504,">="&O$3,請求台帳!$B$5:$B$504,"<"&DATE(YEAR(O$3),MONTH(O$3)+1,1),請求台帳!$Q$5:$Q$504,"<>取消")) | P16: =IF($A16="","",SUMIFS(入金明細!$E$5:$E$1004,入金明細!$G$5:$G$1004,$A16,入金明細!$B$5:$B$1004,">="&O$3,入金明細!$B$5:$B$1004,"<"&DATE(YEAR(O$3),MONTH(O$3)+1,1))) | Q16: =IF($A16="","",SUMIFS(請求台帳!$F$5:$F$504,請求台帳!$C$5:$C$504,$A16,請求台帳!$B$5:$B$504,">="&Q$3,請求台帳!$B$5:$B$504,"<"&DATE(YEAR(Q$3),MONTH(Q$3)+1,1),請求台帳!$Q$5:$Q$504,"<>取消")) | R16: =IF($A16="","",SUMIFS(入金明細!$E$5:$E$1004,入金明細!$G$5:$G$1004,$A16,入金明細!$B$5:$B$1004,">="&Q$3,入金明細!$B$5:$B$1004,"<"&DATE(YEAR(Q$3),MONTH(Q$3)+1,1))) | S16: =IF($A16="","",SUMIFS(請求台帳!$F$5:$F$504,請求台帳!$C$5:$C$504,$A16,請求台帳!$B$5:$B$504,">="&S$3,請求台帳!$B$5:$B$504,"<"&DATE(YEAR(S$3),MONTH(S$3)+1,1),請求台帳!$Q$5:$Q$504,"<>取消")) | T16: =IF($A16="","",SUMIFS(入金明細!$E$5:$E$1004,入金明細!$G$5:$G$1004,$A16,入金明細!$B$5:$B$1004,">="&S$3,入金明細!$B$5:$B$1004,"<"&DATE(YEAR(S$3),MONTH(S$3)+1,1))) | U16: =IF($A16="","",SUMIFS(請求台帳!$F$5:$F$504,請求台帳!$C$5:$C$504,$A16,請求台帳!$B$5:$B$504,">="&U$3,請求台帳!$B$5:$B$504,"<"&DATE(YEAR(U$3),MONTH(U$3)+1,1),請求台帳!$Q$5:$Q$504,"<>取消")) | V16: =IF($A16="","",SUMIFS(入金明細!$E$5:$E$1004,入金明細!$G$5:$G$1004,$A16,入金明細!$B$5:$B$1004,">="&U$3,入金明細!$B$5:$B$1004,"<"&DATE(YEAR(U$3),MONTH(U$3)+1,1))) | W16: =IF($A16="","",SUMIFS(請求台帳!$F$5:$F$504,請求台帳!$C$5:$C$504,$A16,請求台帳!$B$5:$B$504,">="&W$3,請求台帳!$B$5:$B$504,"<"&DATE(YEAR(W$3),MONTH(W$3)+1,1),請求台帳!$Q$5:$Q$504,"<>取消")) | X16: =IF($A16="","",SUMIFS(入金明細!$E$5:$E$1004,入金明細!$G$5:$G$1004,$A16,入金明細!$B$5:$B$1004,">="&W$3,入金明細!$B$5:$B$1004,"<"&DATE(YEAR(W$3),MONTH(W$3)+1,1))) | Y16: =IF($A16="","",SUMIFS(請求台帳!$F$5:$F$504,請求台帳!$C$5:$C$504,$A16,請求台帳!$B$5:$B$504,">="&Y$3,請求台帳!$B$5:$B$504,"<"&DATE(YEAR(Y$3),MONTH(Y$3)+1,1),請求台帳!$Q$5:$Q$504,"<>取消")) | Z16: =IF($A16="","",SUMIFS(入金明細!$E$5:$E$1004,入金明細!$G$5:$G$1004,$A16,入金明細!$B$5:$B$1004,">="&Y$3,入金明細!$B$5:$B$1004,"<"&DATE(YEAR(Y$3),MONTH(Y$3)+1,1))) | AA16: =SUM(C16,E16,G16,I16,K16,M16,O16,Q16,S16,U16,W16,Y16) -> 0 | AB16: =SUM(D16,F16,H16,J16,L16,N16,P16,R16,T16,V16,X16,Z16) -> 0
... A204: =IF(取引先マスタ!A204="","",取引先マスタ!A204) | B204: =IF(A204="","",取引先マスタ!B204) | C204: =IF($A204="","",SUMIFS(請求台帳!$F$5:$F$504,請求台帳!$C$5:$C$504,$A204,請求台帳!$B$5:$B$504,">="&C$3,請求台帳!$B$5:$B$504,"<"&DATE(YEAR(C$3),MONTH(C$3)+1,1),請求台帳!$Q$5:$Q$504,"<>取消")) | D204: =IF($A204="","",SUMIFS(入金明細!$E$5:$E$1004,入金明細!$G$5:$G$1004,$A204,入金明細!$B$5:$B$1004,">="&C$3,入金明細!$B$5:$B$1004,"<"&DATE(YEAR(C$3),MONTH(C$3)+1,1))) | E204: =IF($A204="","",SUMIFS(請求台帳!$F$5:$F$504,請求台帳!$C$5:$C$504,$A204,請求台帳!$B$5:$B$504,">="&E$3,請求台帳!$B$5:$B$504,"<"&DATE(YEAR(E$3),MONTH(E$3)+1,1),請求台帳!$Q$5:$Q$504,"<>取消")) | F204: =IF($A204="","",SUMIFS(入金明細!$E$5:$E$1004,入金明細!$G$5:$G$1004,$A204,入金明細!$B$5:$B$1004,">="&E$3,入金明細!$B$5:$B$1004,"<"&DATE(YEAR(E$3),MONTH(E$3)+1,1))) | G204: =IF($A204="","",SUMIFS(請求台帳!$F$5:$F$504,請求台帳!$C$5:$C$504,$A204,請求台帳!$B$5:$B$504,">="&G$3,請求台帳!$B$5:$B$504,"<"&DATE(YEAR(G$3),MONTH(G$3)+1,1),請求台帳!$Q$5:$Q$504,"<>取消")) | H204: =IF($A204="","",SUMIFS(入金明細!$E$5:$E$1004,入金明細!$G$5:$G$1004,$A204,入金明細!$B$5:$B$1004,">="&G$3,入金明細!$B$5:$B$1004,"<"&DATE(YEAR(G$3),MONTH(G$3)+1,1))) | I204: =IF($A204="","",SUMIFS(請求台帳!$F$5:$F$504,請求台帳!$C$5:$C$504,$A204,請求台帳!$B$5:$B$504,">="&I$3,請求台帳!$B$5:$B$504,"<"&DATE(YEAR(I$3),MONTH(I$3)+1,1),請求台帳!$Q$5:$Q$504,"<>取消")) | J204: =IF($A204="","",SUMIFS(入金明細!$E$5:$E$1004,入金明細!$G$5:$G$1004,$A204,入金明細!$B$5:$B$1004,">="&I$3,入金明細!$B$5:$B$1004,"<"&DATE(YEAR(I$3),MONTH(I$3)+1,1))) | K204: =IF($A204="","",SUMIFS(請求台帳!$F$5:$F$504,請求台帳!$C$5:$C$504,$A204,請求台帳!$B$5:$B$504,">="&K$3,請求台帳!$B$5:$B$504,"<"&DATE(YEAR(K$3),MONTH(K$3)+1,1),請求台帳!$Q$5:$Q$504,"<>取消")) | L204: =IF($A204="","",SUMIFS(入金明細!$E$5:$E$1004,入金明細!$G$5:$G$1004,$A204,入金明細!$B$5:$B$1004,">="&K$3,入金明細!$B$5:$B$1004,"<"&DATE(YEAR(K$3),MONTH(K$3)+1,1))) | M204: =IF($A204="","",SUMIFS(請求台帳!$F$5:$F$504,請求台帳!$C$5:$C$504,$A204,請求台帳!$B$5:$B$504,">="&M$3,請求台帳!$B$5:$B$504,"<"&DATE(YEAR(M$3),MONTH(M$3)+1,1),請求台帳!$Q$5:$Q$504,"<>取消")) | N204: =IF($A204="","",SUMIFS(入金明細!$E$5:$E$1004,入金明細!$G$5:$G$1004,$A204,入金明細!$B$5:$B$1004,">="&M$3,入金明細!$B$5:$B$1004,"<"&DATE(YEAR(M$3),MONTH(M$3)+1,1))) | O204: =IF($A204="","",SUMIFS(請求台帳!$F$5:$F$504,請求台帳!$C$5:$C$504,$A204,請求台帳!$B$5:$B$504,">="&O$3,請求台帳!$B$5:$B$504,"<"&DATE(YEAR(O$3),MONTH(O$3)+1,1),請求台帳!$Q$5:$Q$504,"<>取消")) | P204: =IF($A204="","",SUMIFS(入金明細!$E$5:$E$1004,入金明細!$G$5:$G$1004,$A204,入金明細!$B$5:$B$1004,">="&O$3,入金明細!$B$5:$B$1004,"<"&DATE(YEAR(O$3),MONTH(O$3)+1,1))) | Q204: =IF($A204="","",SUMIFS(請求台帳!$F$5:$F$504,請求台帳!$C$5:$C$504,$A204,請求台帳!$B$5:$B$504,">="&Q$3,請求台帳!$B$5:$B$504,"<"&DATE(YEAR(Q$3),MONTH(Q$3)+1,1),請求台帳!$Q$5:$Q$504,"<>取消")) | R204: =IF($A204="","",SUMIFS(入金明細!$E$5:$E$1004,入金明細!$G$5:$G$1004,$A204,入金明細!$B$5:$B$1004,">="&Q$3,入金明細!$B$5:$B$1004,"<"&DATE(YEAR(Q$3),MONTH(Q$3)+1,1))) | S204: =IF($A204="","",SUMIFS(請求台帳!$F$5:$F$504,請求台帳!$C$5:$C$504,$A204,請求台帳!$B$5:$B$504,">="&S$3,請求台帳!$B$5:$B$504,"<"&DATE(YEAR(S$3),MONTH(S$3)+1,1),請求台帳!$Q$5:$Q$504,"<>取消")) | T204: =IF($A204="","",SUMIFS(入金明細!$E$5:$E$1004,入金明細!$G$5:$G$1004,$A204,入金明細!$B$5:$B$1004,">="&S$3,入金明細!$B$5:$B$1004,"<"&DATE(YEAR(S$3),MONTH(S$3)+1,1))) | U204: =IF($A204="","",SUMIFS(請求台帳!$F$5:$F$504,請求台帳!$C$5:$C$504,$A204,請求台帳!$B$5:$B$504,">="&U$3,請求台帳!$B$5:$B$504,"<"&DATE(YEAR(U$3),MONTH(U$3)+1,1),請求台帳!$Q$5:$Q$504,"<>取消")) | V204: =IF($A204="","",SUMIFS(入金明細!$E$5:$E$1004,入金明細!$G$5:$G$1004,$A204,入金明細!$B$5:$B$1004,">="&U$3,入金明細!$B$5:$B$1004,"<"&DATE(YEAR(U$3),MONTH(U$3)+1,1))) | W204: =IF($A204="","",SUMIFS(請求台帳!$F$5:$F$504,請求台帳!$C$5:$C$504,$A204,請求台帳!$B$5:$B$504,">="&W$3,請求台帳!$B$5:$B$504,"<"&DATE(YEAR(W$3),MONTH(W$3)+1,1),請求台帳!$Q$5:$Q$504,"<>取消")) | X204: =IF($A204="","",SUMIFS(入金明細!$E$5:$E$1004,入金明細!$G$5:$G$1004,$A204,入金明細!$B$5:$B$1004,">="&W$3,入金明細!$B$5:$B$1004,"<"&DATE(YEAR(W$3),MONTH(W$3)+1,1))) | Y204: =IF($A204="","",SUMIFS(請求台帳!$F$5:$F$504,請求台帳!$C$5:$C$504,$A204,請求台帳!$B$5:$B$504,">="&Y$3,請求台帳!$B$5:$B$504,"<"&DATE(YEAR(Y$3),MONTH(Y$3)+1,1),請求台帳!$Q$5:$Q$504,"<>取消")) | Z204: =IF($A204="","",SUMIFS(入金明細!$E$5:$E$1004,入金明細!$G$5:$G$1004,$A204,入金明細!$B$5:$B$1004,">="&Y$3,入金明細!$B$5:$B$1004,"<"&DATE(YEAR(Y$3),MONTH(Y$3)+1,1))) | AA204: =SUM(C204,E204,G204,I204,K204,M204,O204,Q204,S204,U204,W204,Y204) -> 0 | AB204: =SUM(D204,F204,H204,J204,L204,N204,P204,R204,T204,V204,X204,Z204) -> 0
B205: 未消込・番号誤りの入金 | D205: =SUMPRODUCT((入金明細!$G$5:$G$1004="")*(入金明細!$B$5:$B$1004>=C$3)*(入金明細!$B$5:$B$1004<DATE(YEAR(C$3),MONTH(C$3)+1,1)),入金明細!$E$5:$E$1004) -> 0 | F205: =SUMPRODUCT((入金明細!$G$5:$G$1004="")*(入金明細!$B$5:$B$1004>=E$3)*(入金明細!$B$5:$B$1004<DATE(YEAR(E$3),MONTH(E$3)+1,1)),入金明細!$E$5:$E$1004) -> 0 | H205: =SUMPRODUCT((入金明細!$G$5:$G$1004="")*(入金明細!$B$5:$B$1004>=G$3)*(入金明細!$B$5:$B$1004<DATE(YEAR(G$3),MONTH(G$3)+1,1)),入金明細!$E$5:$E$1004) -> 0 | J205: =SUMPRODUCT((入金明細!$G$5:$G$1004="")*(入金明細!$B$5:$B$1004>=I$3)*(入金明細!$B$5:$B$1004<DATE(YEAR(I$3),MONTH(I$3)+1,1)),入金明細!$E$5:$E$1004) -> 0 | L205: =SUMPRODUCT((入金明細!$G$5:$G$1004="")*(入金明細!$B$5:$B$1004>=K$3)*(入金明細!$B$5:$B$1004<DATE(YEAR(K$3),MONTH(K$3)+1,1)),入金明細!$E$5:$E$1004) -> 0 | N205: =SUMPRODUCT((入金明細!$G$5:$G$1004="")*(入金明細!$B$5:$B$1004>=M$3)*(入金明細!$B$5:$B$1004<DATE(YEAR(M$3),MONTH(M$3)+1,1)),入金明細!$E$5:$E$1004) -> 0 | P205: =SUMPRODUCT((入金明細!$G$5:$G$1004="")*(入金明細!$B$5:$B$1004>=O$3)*(入金明細!$B$5:$B$1004<DATE(YEAR(O$3),MONTH(O$3)+1,1)),入金明細!$E$5:$E$1004) -> 0 | R205: =SUMPRODUCT((入金明細!$G$5:$G$1004="")*(入金明細!$B$5:$B$1004>=Q$3)*(入金明細!$B$5:$B$1004<DATE(YEAR(Q$3),MONTH(Q$3)+1,1)),入金明細!$E$5:$E$1004) -> 0 | T205: =SUMPRODUCT((入金明細!$G$5:$G$1004="")*(入金明細!$B$5:$B$1004>=S$3)*(入金明細!$B$5:$B$1004<DATE(YEAR(S$3),MONTH(S$3)+1,1)),入金明細!$E$5:$E$1004) -> 0 | V205: =SUMPRODUCT((入金明細!$G$5:$G$1004="")*(入金明細!$B$5:$B$1004>=U$3)*(入金明細!$B$5:$B$1004<DATE(YEAR(U$3),MONTH(U$3)+1,1)),入金明細!$E$5:$E$1004) -> 0 | X205: =SUMPRODUCT((入金明細!$G$5:$G$1004="")*(入金明細!$B$5:$B$1004>=W$3)*(入金明細!$B$5:$B$1004<DATE(YEAR(W$3),MONTH(W$3)+1,1)),入金明細!$E$5:$E$1004) -> 0 | Z205: =SUMPRODUCT((入金明細!$G$5:$G$1004="")*(入金明細!$B$5:$B$1004>=Y$3)*(入金明細!$B$5:$B$1004<DATE(YEAR(Y$3),MONTH(Y$3)+1,1)),入金明細!$E$5:$E$1004) -> 5500 | AA205: =SUM(C205,E205,G205,I205,K205,M205,O205,Q205,S205,U205,W205,Y205) -> 0 | AB205: =SUM(D205,F205,H205,J205,L205,N205,P205,R205,T205,V205,X205,Z205) -> 5500
B206: 合計 | C206: =SUM(C5:C205) -> 0 | D206: =SUM(D5:D205) -> 0 | E206: =SUM(E5:E205) -> 0 | F206: =SUM(F5:F205) -> 0 | G206: =SUM(G5:G205) -> 0 | H206: =SUM(H5:H205) -> 0 | I206: =SUM(I5:I205) -> 0 | J206: =SUM(J5:J205) -> 0 | ... Z206: =SUM(Z5:Z205) -> 330060 | AA206: =SUM(C206,E206,G206,I206,K206,M206,O206,Q206,S206,U206,W206,Y206) -> 784300 | AB206: =SUM(D206,F206,H206,J206,L206,N206,P206,R206,T206,V206,X206,Z206) -> 440060

Sheet 取引先マスタ
A1: 取引先マスタ
A2: 取引先ごとの支払条件を登録します。請求台帳の入金期日は「支払サイト」「支払日」から自動計算。未登録だと請求が「要入力」になります。
A4: 取引先コード | B4: 取引先名 | C4: 振込名義(カナ) | D4: 締日(参考) | E4: 支払サイト(月) | F4: 支払日 | G4: 毎月請求 | H4: 既定の送付方法 | I4: 送付先(メール/住所/システム) | J4: 担当者 | K4: 備考 | L4: 重複チェック
A5: C001 | B5: 株式会社サンプル商事 | C5: カ)サンプルシヨウジ | D5: 末日 | E5: 1 | F5: 31 | G5: 有 | H5: メール(PDF) | I5: keiri@sample.example | J5: 山田 | K5: サンプル(運用前に削除) | L5: =IF(A5="","",IF(COUNTIF(取引先マスタ!$A$5:$A$204,A5)>1,"コード重複",""))
A6: C002 | B6: 有限会社テスト工業 | C6: ユ)テストコウギヨウ | D6: 末日 | E6: 2 | F6: 10 | G6: 無 | H6: 郵送 | I6: 東京都○○区… | J6: 佐藤 | K6: サンプル(運用前に削除) | L6: =IF(A6="","",IF(COUNTIF(取引先マスタ!$A$5:$A$204,A6)>1,"コード重複",""))
A7: C003 | B7: 合同会社デモ | C7: ド)デモ | D7: 20日 | E7: 1 | F7: 31 | G7: 有 | H7: 請求書発行システム | J7: 山田 | K7: サンプル(運用前に削除) | L7: =IF(A7="","",IF(COUNTIF(取引先マスタ!$A$5:$A$204,A7)>1,"コード重複",""))
L8: =IF(A8="","",IF(COUNTIF(取引先マスタ!$A$5:$A$204,A8)>1,"コード重複",""))
L9: =IF(A9="","",IF(COUNTIF(取引先マスタ!$A$5:$A$204,A9)>1,"コード重複",""))
L10: =IF(A10="","",IF(COUNTIF(取引先マスタ!$A$5:$A$204,A10)>1,"コード重複",""))
L11: =IF(A11="","",IF(COUNTIF(取引先マスタ!$A$5:$A$204,A11)>1,"コード重複",""))
L12: =IF(A12="","",IF(COUNTIF(取引先マスタ!$A$5:$A$204,A12)>1,"コード重複",""))
L13: =IF(A13="","",IF(COUNTIF(取引先マスタ!$A$5:$A$204,A13)>1,"コード重複",""))
L14: =IF(A14="","",IF(COUNTIF(取引先マスタ!$A$5:$A$204,A14)>1,"コード重複",""))
L15: =IF(A15="","",IF(COUNTIF(取引先マスタ!$A$5:$A$204,A15)>1,"コード重複",""))
L16: =IF(A16="","",IF(COUNTIF(取引先マスタ!$A$5:$A$204,A16)>1,"コード重複",""))
L17: =IF(A17="","",IF(COUNTIF(取引先マスタ!$A$5:$A$204,A17)>1,"コード重複",""))
L18: =IF(A18="","",IF(COUNTIF(取引先マスタ!$A$5:$A$204,A18)>1,"コード重複",""))
L19: =IF(A19="","",IF(COUNTIF(取引先マスタ!$A$5:$A$204,A19)>1,"コード重複",""))
... L204: =IF(A204="","",IF(COUNTIF(取引先マスタ!$A$5:$A$204,A204)>1,"コード重複",""))

Sheet 月次チェック記録
A1: 月次チェック記録
A2: 毎月、締め後(例: 翌月5営業日以内)に実施。各項目を確認したら「済」を選択し、実施者・承認者を記入します。
A4: 対象月 | B4: ①請求漏れ突合 (工事・検査の完了と台帳) | C4: ②未送付 0件 | D4: ③要入力 0件 | E4: ④未消込入金 0件 (番号誤り含む) | F4: ⑤期日超過の督促・ 状況確認 | G4: ⑥会計ソフト残高 との照合(差額0) | H4: ⑦毎月請求先の 請求漏れ候補 0件 | I4: 実施者 | J4: 実施日 | K4: 承認者(責任者) | L4: 承認日 | M4: 期日超過の件数・金額 / 特記事項 | N4: ※ 対象月までの行で承認日が空欄の行はオレンジ表示
A5: 45931
A6: 45962
A7: 45992
A8: 46023
A9: 46054
A10: 46082
A11: 46113
A12: 46143
A13: 46174
A14: 46204
A15: 46235
A16: 46266
... A40: 46997

Sheet 設定
A1: 設定
A2: 黄色のセルを必要に応じて変更してください。プルダウンの選択肢は各リストの空欄に追記できます。 | F2: ▼ プルダウンの選択肢(空欄に追記すると選択肢に増えます)
B4: 請求番号の接頭辞 | C4: INV- | D4: 請求番号 = 接頭辞 + 5桁の連番(例: INV-00001) | F4: 送付方法 | G4: 入金口座 | H4: 取消 | I4: 有無 | J4: 実施
B5: 基準日 | C5: =TODAY() -> 46294 | D5: 通常は =TODAY() のまま。過去時点で確認したい場合のみ日付を直接入力 | F5: メール(PDF) | G5: 平塚信用金庫 | H5: 取消 | I5: 有 | J5: 済
B6: 期日間近とする日数 | C6: 7 | D6: 入金期日まで何日以内を「期日間近」とするか | F6: 郵送 | G6: (口座名を入力) | I6: 無 | J6: 該当なし
B7: 月別集計の期首 | C7: 45931 | D7: 月別集計シートの1か月目(例: 2026/10/1 = 3期) | F7: 請求書発行システム
F8: 先方システムへ登録
F9: 手渡し
F10: その他
