Workbook

Sheet はじめに
B1: 請求・入金管理表 ― 使い方
B2: 請求書の「発行漏れ」「送付漏れ」「入金確認漏れ」「記入漏れ」を仕組みで防ぐための管理表です。
B4: 1. 色の見方
B5: 黄色のセル | C5: 入力するセル(ここだけ入力します)
B6: 灰色のセル | C6: 自動計算(入力不要。シート保護で上書きできないようにしています)
B8: 2. シート構成
B9: 請求台帳 | C9: 請求書1枚=1行。請求番号は台帳が自動採番します。ステータス・入力漏れを自動判定。
B10: 入金明細 | C10: 通帳/ネットバンキングの入金を【全件】転記し、消込先の請求番号を入れます。
B11: 取引先マスタ | C11: 取引先コード・支払条件(サイト/支払日)・毎月請求の有無を登録します。
B12: チェック | C12: 未送付/期日超過/未消込/要入力などの件数を一覧表示。0件でない項目が「要対応」です。
B13: 取引先別残高 | C13: 取引先ごとの未回収残高と超過日数の内訳、毎月請求先の請求漏れ候補を表示します。
B14: 月次チェック記録 | C14: 月次締めのチェック結果と承認を記録します(誰がいつ確認したかを残す)。
B15: 設定 | C15: 請求番号の接頭辞、基準日、期日間近の日数、プルダウンの選択肢。
B17: 3. 基本の流れ
B18: ① 請求書を作る前 | C18: 請求台帳に1行追加(請求日・取引先・件名・金額・税率・送付方法)→ 採番された請求番号を請求書に記載。
B19: ② 請求書を送ったら | C19: 送付日・送付者を入力。未入力の間はステータスが「未送付」のまま残ります。
B20: ③ 入金があったら | C20: 入金明細に入金日・名義・金額を転記し、消込先の請求番号を入力。台帳の入金額・残高が自動更新されます。
B21: ④ 消込を確認したら | C21: 残高が0になった請求は、別の人が確認して「消込確認者」に名前を入れます(未入力だと「要入力」)。
B22: ⑤ 毎週 | C22: チェックシートで「期日超過」「期日間近」を確認し、担当者から督促・状況確認。
B23: ⑥ 毎月(締め後) | C23: チェックシートの全項目が「OK」になることを確認し、月次チェック記録に実施者・承認者を記入。
B25: 4. ステータスの意味(請求台帳)
B26: 要入力 | C26: 必須項目の漏れ、取引先コード誤り、送付者・消込確認者の未入力がある。「入力漏れ」列に項目名を表示。
B27: 未送付 | C27: 台帳登録済みだが送付日が空欄。請求書の出し忘れ・送り忘れの可能性。
B28: 入金待ち / 期日間近 | C28: 送付済みで期日前。期日まで「設定」の日数以内なら期日間近。
B29: 期日超過 | C29: 入金期日を過ぎても未回収残高がある。督促が必要。
B30: 一部入金 / 一部入金・超過 | C30: 入金額が請求額に足りない(振込手数料の差引なら「手数料・値引等」に入力)。
B31: 過入金 | C31: 請求額より多く入金されている(二重振込・消込先誤りの可能性)。
B32: 入金済 | C32: 未回収残高が0。
B33: 取消 | C33: 「取消」列で取消した請求。行は削除せず残します(番号の欠番を作らないため)。
B35: 5. 守るルール
B36: 行を削除しない | C36: 間違えた請求は「取消」を選び、備考に理由を書く。番号の連続性が発行漏れチェックの根拠になります。
B37: 並べ替えをしない | C37: 請求番号は行位置から採番されるため、並べ替えは不可(シート保護で制限)。絞り込みはフィルタで。
B38: 入金は全件転記 | C38: 請求に対応しない入金も含めて全件入力。「未消込」が残っていれば消込漏れか不明入金です。
B39: 1入金で複数請求 | C39: 入金明細を請求の数だけ行に分け、金額を按分して各請求番号を入力。
B40: 振込手数料の差引 | C40: 先方負担の手数料が差し引かれた場合、請求台帳の「手数料・値引等」に差額を入力。
B41: サンプルデータ | C41: 各シートの「サンプル」「SAMPLE」行は動作確認用です。運用開始前に入力セルの内容を消去してください。
B42: シート保護 | C42: パスワードなしで保護しています。列の追加などが必要な場合は[校閲]→[シート保護の解除]。

Sheet チェック
A1: チェック(ダッシュボード)
A2: 判定が「要対応」の項目を解消してください。月次締めでは全項目「OK」を確認して「月次チェック記録」に記入します。
B4: 対象月(月次チェック用) | C4: =DATE(YEAR(設定!$C$5),MONTH(設定!$C$5)-1,1) -> 46235 | D4: 既定は基準日の前月。確認したい月の1日を入力(例: 2026/9/1)
B5: 基準日 | C5: =設定!$C$5 -> 46294 | D5: 「設定」シートで変更
B7: チェック項目 | C7: 件数 | D7: 金額 | E7: 判定 | F7: 対応方法
B8: ■ 請求(請求台帳)
B9: 要入力(入力漏れ) | C9: =COUNTIF(請求台帳!$U$5:$U$504,"要入力") -> 1 | E9: =IF(C9=0,"OK","要対応") -> 要対応 | F9: 請求台帳を「ステータス=要入力」で絞り込み、「入力漏れ」列の項目を入力
B10: 未送付 | C10: =COUNTIF(請求台帳!$U$5:$U$504,"未送付") -> 1 | D10: =SUMIF(請求台帳!$U$5:$U$504,"未送付",請求台帳!$I$5:$I$504) -> 110000 | E10: =IF(C10=0,"OK","要対応") -> 要対応 | F10: 請求書を送付し送付日・送付者を入力。不要な請求なら「取消」
B11: 期日超過(一部入金含む) | C11: =COUNTIF(請求台帳!$U$5:$U$504,"期日超過")+COUNTIF(請求台帳!$U$5:$U$504,"一部入金・超過") -> 1 | D11: =SUMIF(請求台帳!$U$5:$U$504,"期日超過",請求台帳!$S$5:$S$504)+SUMIF(請求台帳!$U$5:$U$504,"一部入金・超過",請求台帳!$S$5:$S$504) -> 165000 | E11: =IF(C11=0,"OK","要対応") -> 要対応 | F11: 営業担当から先方へ確認・督促。入金済なら入金明細の転記・消込漏れを確認
B12: 過入金 | C12: =COUNTIF(請求台帳!$U$5:$U$504,"過入金") -> 0 | D12: =SUMIF(請求台帳!$U$5:$U$504,"過入金",請求台帳!$S$5:$S$504) -> 0 | E12: =IF(C12=0,"OK","要対応") -> OK | F12: 二重振込・消込先の誤りを確認。返金または次回請求と相殺し備考に記録
B13: 期日間近(参考) | C13: =COUNTIF(請求台帳!$U$5:$U$504,"期日間近") -> 1 | D13: =SUMIF(請求台帳!$U$5:$U$504,"期日間近",請求台帳!$S$5:$S$504) -> 36300 | E13: 参考 | F13: 期日前の確認・リマインド(任意)
B14: 入金待ち(参考) | C14: =COUNTIF(請求台帳!$U$5:$U$504,"入金待ち")+COUNTIF(請求台帳!$U$5:$U$504,"一部入金") -> 1 | D14: =SUMIF(請求台帳!$U$5:$U$504,"入金待ち",請求台帳!$S$5:$S$504)+SUMIF(請求台帳!$U$5:$U$504,"一部入金",請求台帳!$S$5:$S$504) -> 38000 | E14: 参考 | F14: 対応不要
B15: ■ 入金(入金明細)
B16: 未消込の入金 | C16: =COUNTIF(入金明細!$I$5:$I$1004,"未消込") -> 1 | D16: =SUMIF(入金明細!$I$5:$I$1004,"未消込",入金明細!$E$5:$E$1004) -> 5500 | E16: =IF(C16=0,"OK","要対応") -> 要対応 | F16: 振込名義・金額から該当請求を探して請求番号を入力。不明なら先方・営業に確認
B17: 消込先の請求番号誤り | C17: =COUNTIF(入金明細!$I$5:$I$1004,"番号誤り") -> 0 | D17: =SUMIF(入金明細!$I$5:$I$1004,"番号誤り",入金明細!$E$5:$E$1004) -> 0 | E17: =IF(C17=0,"OK","要対応") -> OK | F17: 請求番号を正しく入力し直す
B18: 取消した請求への消込 | C18: =COUNTIF(入金明細!$I$5:$I$1004,"取消請求へ消込") -> 0 | D18: =SUMIF(入金明細!$I$5:$I$1004,"取消請求へ消込",入金明細!$E$5:$E$1004) -> 0 | E18: =IF(C18=0,"OK","要対応") -> OK | F18: 再発行後の請求番号へ付け替える
B19: 入金明細の入力漏れ | C19: =COUNTIF(入金明細!$I$5:$I$1004,"要入力") -> 0 | E19: =IF(C19=0,"OK","要対応") -> OK | F19: 入金日・入金額を入力
B20: ■ 請求漏れ(対象月)
B21: 毎月請求先で対象月の請求が未登録 | C21: =COUNTIF(取引先別残高!$J$5:$J$204,"請求漏れ候補") -> 1 | E21: =IF(C21=0,"OK","要対応") -> 要対応 | F21: 「取引先別残高」の請求漏れ候補を確認し、請求するか理由を備考に記録
B22: マスタの取引先コード重複 | C22: =COUNTIF(取引先マスタ!$L$5:$L$204,"コード重複") -> 0 | E22: =IF(C22=0,"OK","要対応") -> OK | F22: 取引先マスタを修正
B23: ■ 月次の数字(対象月)
B24: 対象月の請求(取消除く) | C24: =COUNTIFS(請求台帳!$B$5:$B$504,">="&チェック!$C$4,請求台帳!$B$5:$B$504,"<="&EOMONTH(チェック!$C$4,0),請求台帳!$T$5:$T$504,"<>取消") -> 1 | D24: =SUMIFS(請求台帳!$I$5:$I$504,請求台帳!$B$5:$B$504,">="&チェック!$C$4,請求台帳!$B$5:$B$504,"<="&EOMONTH(チェック!$C$4,0),請求台帳!$T$5:$T$504,"<>取消") -> 88000 | F24: 契約・受注・納品の一覧と件数を突合し、請求漏れがないか確認
B25: 対象月の入金 | C25: =SUMPRODUCT((入金明細!$B$5:$B$1004>=チェック!$C$4)*(入金明細!$B$5:$B$1004<=EOMONTH(チェック!$C$4,0))*(入金明細!$E$5:$E$1004<>"")) -> 1 | D25: =SUMIFS(入金明細!$E$5:$E$1004,入金明細!$B$5:$B$1004,">="&チェック!$C$4,入金明細!$B$5:$B$1004,"<="&EOMONTH(チェック!$C$4,0)) -> 110000 | F25: 通帳の対象月入金合計(請求入金分)と一致するか確認
B26: 未回収残高 合計(基準日時点) | C26: =COUNTIFS(請求台帳!$S$5:$S$504,">0",請求台帳!$T$5:$T$504,"<>取消")+COUNTIFS(請求台帳!$S$5:$S$504,"<0",請求台帳!$T$5:$T$504,"<>取消") -> 4 | D26: =SUMIF(請求台帳!$T$5:$T$504,"<>取消",請求台帳!$S$5:$S$504) -> 349300 | F26: 下の会計ソフトの売掛金残高と照合
B28: ■ 会計ソフトとの残高照合(月次)
B29: 会計ソフトの売掛金残高(基準日時点) | F29: 会計ソフトの売掛金残高を入力(基準日と同じ日付時点)
B30: 差額(台帳 − 会計ソフト) | D30: =IF(D29="","",D26-D29) | E30: =IF(D29="","未入力",IF(D30=0,"OK","要対応")) -> 未入力 | F30: 差額があれば、台帳への登録漏れ・会計側の計上漏れ・消込漏れのいずれかを調査
B32: 総合判定 | C32: =IF(COUNTIF(E8:E30,"要対応")+COUNTIF(E8:E30,"未入力")=0,"すべてOK","要対応あり") -> 要対応あり

Sheet 請求台帳
A1: 請求台帳
A2: 請求書を作る前にここへ登録 → 採番された請求番号を請求書に記載。黄色=入力 / 灰色=自動。行は削除せず、誤りは「取消」を選択。
A4: 請求番号 | B4: 請求日 | C4: 取引先コード | D4: 取引先名 | E4: 件名 | F4: 税抜金額 | G4: 税率 | H4: 消費税 | I4: 請求額(税込) | J4: 入金期日(自動) | K4: 入金期日(個別) | L4: 入金期日 | M4: 送付方法 | N4: 送付日 | O4: 送付者 | P4: 入金額 | Q4: 最終入金日 | R4: 手数料・値引等 | S4: 未回収残高 | T4: 取消 | U4: ステータス | V4: 超過日数 | W4: 入力漏れ | X4: 消込確認者 | Y4: 備考
A5: =IF(COUNTA(B5,C5,E5,F5)=0,"",設定!$C$4&TEXT(ROW()-4,"00000")) -> INV-00001 | B5: 46234 | C5: C001 | D5: =IF(C5="","",IFERROR(INDEX(取引先マスタ!$B$5:$B$204,MATCH($C5,取引先マスタ!$A$5:$A$204,0)),"コード誤り")) -> 株式会社サンプル商事 | E5: 2026年7月分 保守料 | F5: 100000 | G5: 0.1 | H5: =IF(OR(F5="",G5=""),"",ROUNDDOWN(F5*G5,0)) -> 10000 | I5: =IF(OR(F5="",G5=""),"",F5+H5) -> 110000 | J5: =IF(OR(B5="",C5="",D5="コード誤り"),"",IFERROR(DATE(YEAR(B5),MONTH(B5)+INDEX(取引先マスタ!$E$5:$E$204,MATCH($C5,取引先マスタ!$A$5:$A$204,0)),MIN(INDEX(取引先マスタ!$F$5:$F$204,MATCH($C5,取引先マスタ!$A$5:$A$204,0)),DAY(EOMONTH(B5,INDEX(取引先マスタ!$E$5:$E$204,MATCH($C5,取引先マスタ!$A$5:$A$204,0)))))),"")) -> 46265 | L5: =IF(K5<>"",K5,J5) -> 46265 | M5: メール(PDF) | N5: 46234 | O5: 鈴木 | P5: =IF(A5="","",SUMIF(入金明細!$F$5:$F$1004,A5,入金明細!$E$5:$E$1004)) -> 110000 | Q5: =IF(OR(A5="",N(P5)=0),"",SUMPRODUCT(MAX((入金明細!$F$5:$F$1004=A5)*入金明細!$B$5:$B$1004))) -> 46265 | S5: =IF(OR(A5="",I5=""),"",I5-N(P5)-N(R5)) -> 0 | U5: =IF(A5="","",IF(T5="取消","取消",IF(W5<>"","要入力",IF(N5="","未送付",IF(S5=0,"入金済",IF(S5<0,"過入金",IF(設定!$C$5>L5,IF(P5>0,"一部入金・超過","期日超過"),IF(P5>0,"一部入金",IF(L5-設定!$C$5<=設定!$C$6,"期日間近","入金待ち"))))))))) -> 入金済 | V5: =IF(OR(U5="期日超過",U5="一部入金・超過"),設定!$C$5-L5,"") | W5: =IF(A5="","",TRIM(IF(B5="","請求日 ","")&IF(C5="","取引先 ",IF(D5="コード誤り","取引先コード誤り ",""))&IF(E5="","件名 ","")&IF(F5="","税抜金額 ","")&IF(G5="","税率 ","")&IF(M5="","送付方法 ","")&IF(AND(N5<>"",O5=""),"送付者 ","")&IF(AND(I5<>"",L5=""),"入金期日 ","")&IF(AND(N5<>"",P5>0,S5<=0,X5=""),"消込確認者 ",""))) | X5: 田中 | Y5: SAMPLE: 入金済
A6: =IF(COUNTA(B6,C6,E6,F6)=0,"",設定!$C$4&TEXT(ROW()-4,"00000")) -> INV-00002 | B6: 46234 | C6: C002 | D6: =IF(C6="","",IFERROR(INDEX(取引先マスタ!$B$5:$B$204,MATCH($C6,取引先マスタ!$A$5:$A$204,0)),"コード誤り")) -> 有限会社テスト工業 | E6: ○○部品 納品分 | F6: 250000 | G6: 0.1 | H6: =IF(OR(F6="",G6=""),"",ROUNDDOWN(F6*G6,0)) -> 25000 | I6: =IF(OR(F6="",G6=""),"",F6+H6) -> 275000 | J6: =IF(OR(B6="",C6="",D6="コード誤り"),"",IFERROR(DATE(YEAR(B6),MONTH(B6)+INDEX(取引先マスタ!$E$5:$E$204,MATCH($C6,取引先マスタ!$A$5:$A$204,0)),MIN(INDEX(取引先マスタ!$F$5:$F$204,MATCH($C6,取引先マスタ!$A$5:$A$204,0)),DAY(EOMONTH(B6,INDEX(取引先マスタ!$E$5:$E$204,MATCH($C6,取引先マスタ!$A$5:$A$204,0)))))),"")) -> 46275 | L6: =IF(K6<>"",K6,J6) -> 46275 | M6: 郵送 | N6: 46237 | O6: 鈴木 | P6: =IF(A6="","",SUMIF(入金明細!$F$5:$F$1004,A6,入金明細!$E$5:$E$1004)) -> 274560 | Q6: =IF(OR(A6="",N(P6)=0),"",SUMPRODUCT(MAX((入金明細!$F$5:$F$1004=A6)*入金明細!$B$5:$B$1004))) -> 46275 | R6: 440 | S6: =IF(OR(A6="",I6=""),"",I6-N(P6)-N(R6)) -> 0 | U6: =IF(A6="","",IF(T6="取消","取消",IF(W6<>"","要入力",IF(N6="","未送付",IF(S6=0,"入金済",IF(S6<0,"過入金",IF(設定!$C$5>L6,IF(P6>0,"一部入金・超過","期日超過"),IF(P6>0,"一部入金",IF(L6-設定!$C$5<=設定!$C$6,"期日間近","入金待ち"))))))))) -> 要入力 | V6: =IF(OR(U6="期日超過",U6="一部入金・超過"),設定!$C$5-L6,"") | W6: =IF(A6="","",TRIM(IF(B6="","請求日 ","")&IF(C6="","取引先 ",IF(D6="コード誤り","取引先コード誤り ",""))&IF(E6="","件名 ","")&IF(F6="","税抜金額 ","")&IF(G6="","税率 ","")&IF(M6="","送付方法 ","")&IF(AND(N6<>"",O6=""),"送付者 ","")&IF(AND(I6<>"",L6=""),"入金期日 ","")&IF(AND(N6<>"",P6>0,S6<=0,X6=""),"消込確認者 ",""))) -> 消込確認者 | Y6: SAMPLE: 手数料差引で入金(確認者未入力→要入力)
A7: =IF(COUNTA(B7,C7,E7,F7)=0,"",設定!$C$4&TEXT(ROW()-4,"00000")) -> INV-00003 | B7: 46203 | C7: C002 | D7: =IF(C7="","",IFERROR(INDEX(取引先マスタ!$B$5:$B$204,MATCH($C7,取引先マスタ!$A$5:$A$204,0)),"コード誤り")) -> 有限会社テスト工業 | E7: ○○部品 6月納品分 | F7: 150000 | G7: 0.1 | H7: =IF(OR(F7="",G7=""),"",ROUNDDOWN(F7*G7,0)) -> 15000 | I7: =IF(OR(F7="",G7=""),"",F7+H7) -> 165000 | J7: =IF(OR(B7="",C7="",D7="コード誤り"),"",IFERROR(DATE(YEAR(B7),MONTH(B7)+INDEX(取引先マスタ!$E$5:$E$204,MATCH($C7,取引先マスタ!$A$5:$A$204,0)),MIN(INDEX(取引先マスタ!$F$5:$F$204,MATCH($C7,取引先マスタ!$A$5:$A$204,0)),DAY(EOMONTH(B7,INDEX(取引先マスタ!$E$5:$E$204,MATCH($C7,取引先マスタ!$A$5:$A$204,0)))))),"")) -> 46244 | L7: =IF(K7<>"",K7,J7) -> 46244 | M7: 郵送 | N7: 46204 | O7: 鈴木 | P7: =IF(A7="","",SUMIF(入金明細!$F$5:$F$1004,A7,入金明細!$E$5:$E$1004)) -> 0 | Q7: =IF(OR(A7="",N(P7)=0),"",SUMPRODUCT(MAX((入金明細!$F$5:$F$1004=A7)*入金明細!$B$5:$B$1004))) | S7: =IF(OR(A7="",I7=""),"",I7-N(P7)-N(R7)) -> 165000 | U7: =IF(A7="","",IF(T7="取消","取消",IF(W7<>"","要入力",IF(N7="","未送付",IF(S7=0,"入金済",IF(S7<0,"過入金",IF(設定!$C$5>L7,IF(P7>0,"一部入金・超過","期日超過"),IF(P7>0,"一部入金",IF(L7-設定!$C$5<=設定!$C$6,"期日間近","入金待ち"))))))))) -> 期日超過 | V7: =IF(OR(U7="期日超過",U7="一部入金・超過"),設定!$C$5-L7,"") -> 50 | W7: =IF(A7="","",TRIM(IF(B7="","請求日 ","")&IF(C7="","取引先 ",IF(D7="コード誤り","取引先コード誤り ",""))&IF(E7="","件名 ","")&IF(F7="","税抜金額 ","")&IF(G7="","税率 ","")&IF(M7="","送付方法 ","")&IF(AND(N7<>"",O7=""),"送付者 ","")&IF(AND(I7<>"",L7=""),"入金期日 ","")&IF(AND(N7<>"",P7>0,S7<=0,X7=""),"消込確認者 ",""))) | Y7: SAMPLE: 期日超過
A8: =IF(COUNTA(B8,C8,E8,F8)=0,"",設定!$C$4&TEXT(ROW()-4,"00000")) -> INV-00004 | B8: 46265 | C8: C003 | D8: =IF(C8="","",IFERROR(INDEX(取引先マスタ!$B$5:$B$204,MATCH($C8,取引先マスタ!$A$5:$A$204,0)),"コード誤り")) -> 合同会社デモ | E8: 8月分 業務委託料 | F8: 80000 | G8: 0.1 | H8: =IF(OR(F8="",G8=""),"",ROUNDDOWN(F8*G8,0)) -> 8000 | I8: =IF(OR(F8="",G8=""),"",F8+H8) -> 88000 | J8: =IF(OR(B8="",C8="",D8="コード誤り"),"",IFERROR(DATE(YEAR(B8),MONTH(B8)+INDEX(取引先マスタ!$E$5:$E$204,MATCH($C8,取引先マスタ!$A$5:$A$204,0)),MIN(INDEX(取引先マスタ!$F$5:$F$204,MATCH($C8,取引先マスタ!$A$5:$A$204,0)),DAY(EOMONTH(B8,INDEX(取引先マスタ!$E$5:$E$204,MATCH($C8,取引先マスタ!$A$5:$A$204,0)))))),"")) -> 46295 | L8: =IF(K8<>"",K8,J8) -> 46295 | M8: 請求書発行システム | N8: 46266 | O8: 鈴木 | P8: =IF(A8="","",SUMIF(入金明細!$F$5:$F$1004,A8,入金明細!$E$5:$E$1004)) -> 50000 | Q8: =IF(OR(A8="",N(P8)=0),"",SUMPRODUCT(MAX((入金明細!$F$5:$F$1004=A8)*入金明細!$B$5:$B$1004))) -> 46295 | S8: =IF(OR(A8="",I8=""),"",I8-N(P8)-N(R8)) -> 38000 | U8: =IF(A8="","",IF(T8="取消","取消",IF(W8<>"","要入力",IF(N8="","未送付",IF(S8=0,"入金済",IF(S8<0,"過入金",IF(設定!$C$5>L8,IF(P8>0,"一部入金・超過","期日超過"),IF(P8>0,"一部入金",IF(L8-設定!$C$5<=設定!$C$6,"期日間近","入金待ち"))))))))) -> 一部入金 | V8: =IF(OR(U8="期日超過",U8="一部入金・超過"),設定!$C$5-L8,"") | W8: =IF(A8="","",TRIM(IF(B8="","請求日 ","")&IF(C8="","取引先 ",IF(D8="コード誤り","取引先コード誤り ",""))&IF(E8="","件名 ","")&IF(F8="","税抜金額 ","")&IF(G8="","税率 ","")&IF(M8="","送付方法 ","")&IF(AND(N8<>"",O8=""),"送付者 ","")&IF(AND(I8<>"",L8=""),"入金期日 ","")&IF(AND(N8<>"",P8>0,S8<=0,X8=""),"消込確認者 ",""))) | Y8: SAMPLE: 一部入金
A9: =IF(COUNTA(B9,C9,E9,F9)=0,"",設定!$C$4&TEXT(ROW()-4,"00000")) -> INV-00005 | B9: 46295 | C9: C001 | D9: =IF(C9="","",IFERROR(INDEX(取引先マスタ!$B$5:$B$204,MATCH($C9,取引先マスタ!$A$5:$A$204,0)),"コード誤り")) -> 株式会社サンプル商事 | E9: 2026年9月分 保守料 | F9: 100000 | G9: 0.1 | H9: =IF(OR(F9="",G9=""),"",ROUNDDOWN(F9*G9,0)) -> 10000 | I9: =IF(OR(F9="",G9=""),"",F9+H9) -> 110000 | J9: =IF(OR(B9="",C9="",D9="コード誤り"),"",IFERROR(DATE(YEAR(B9),MONTH(B9)+INDEX(取引先マスタ!$E$5:$E$204,MATCH($C9,取引先マスタ!$A$5:$A$204,0)),MIN(INDEX(取引先マスタ!$F$5:$F$204,MATCH($C9,取引先マスタ!$A$5:$A$204,0)),DAY(EOMONTH(B9,INDEX(取引先マスタ!$E$5:$E$204,MATCH($C9,取引先マスタ!$A$5:$A$204,0)))))),"")) -> 46326 | L9: =IF(K9<>"",K9,J9) -> 46326 | M9: メール(PDF) | P9: =IF(A9="","",SUMIF(入金明細!$F$5:$F$1004,A9,入金明細!$E$5:$E$1004)) -> 0 | Q9: =IF(OR(A9="",N(P9)=0),"",SUMPRODUCT(MAX((入金明細!$F$5:$F$1004=A9)*入金明細!$B$5:$B$1004))) | S9: =IF(OR(A9="",I9=""),"",I9-N(P9)-N(R9)) -> 110000 | U9: =IF(A9="","",IF(T9="取消","取消",IF(W9<>"","要入力",IF(N9="","未送付",IF(S9=0,"入金済",IF(S9<0,"過入金",IF(設定!$C$5>L9,IF(P9>0,"一部入金・超過","期日超過"),IF(P9>0,"一部入金",IF(L9-設定!$C$5<=設定!$C$6,"期日間近","入金待ち"))))))))) -> 未送付 | V9: =IF(OR(U9="期日超過",U9="一部入金・超過"),設定!$C$5-L9,"") | W9: =IF(A9="","",TRIM(IF(B9="","請求日 ","")&IF(C9="","取引先 ",IF(D9="コード誤り","取引先コード誤り ",""))&IF(E9="","件名 ","")&IF(F9="","税抜金額 ","")&IF(G9="","税率 ","")&IF(M9="","送付方法 ","")&IF(AND(N9<>"",O9=""),"送付者 ","")&IF(AND(I9<>"",L9=""),"入金期日 ","")&IF(AND(N9<>"",P9>0,S9<=0,X9=""),"消込確認者 ",""))) | Y9: SAMPLE: 未送付
A10: =IF(COUNTA(B10,C10,E10,F10)=0,"",設定!$C$4&TEXT(ROW()-4,"00000")) -> INV-00006 | B10: 46280 | C10: C003 | D10: =IF(C10="","",IFERROR(INDEX(取引先マスタ!$B$5:$B$204,MATCH($C10,取引先マスタ!$A$5:$A$204,0)),"コード誤り")) -> 合同会社デモ | E10: 追加作業費 | F10: 30000 | G10: 0.1 | H10: =IF(OR(F10="",G10=""),"",ROUNDDOWN(F10*G10,0)) -> 3000 | I10: =IF(OR(F10="",G10=""),"",F10+H10) -> 33000 | J10: =IF(OR(B10="",C10="",D10="コード誤り"),"",IFERROR(DATE(YEAR(B10),MONTH(B10)+INDEX(取引先マスタ!$E$5:$E$204,MATCH($C10,取引先マスタ!$A$5:$A$204,0)),MIN(INDEX(取引先マスタ!$F$5:$F$204,MATCH($C10,取引先マスタ!$A$5:$A$204,0)),DAY(EOMONTH(B10,INDEX(取引先マスタ!$E$5:$E$204,MATCH($C10,取引先マスタ!$A$5:$A$204,0)))))),"")) -> 46326 | L10: =IF(K10<>"",K10,J10) -> 46326 | M10: 請求書発行システム | N10: 46280 | O10: 鈴木 | P10: =IF(A10="","",SUMIF(入金明細!$F$5:$F$1004,A10,入金明細!$E$5:$E$1004)) -> 0 | Q10: =IF(OR(A10="",N(P10)=0),"",SUMPRODUCT(MAX((入金明細!$F$5:$F$1004=A10)*入金明細!$B$5:$B$1004))) | S10: =IF(OR(A10="",I10=""),"",I10-N(P10)-N(R10)) -> 33000 | T10: 取消 | U10: =IF(A10="","",IF(T10="取消","取消",IF(W10<>"","要入力",IF(N10="","未送付",IF(S10=0,"入金済",IF(S10<0,"過入金",IF(設定!$C$5>L10,IF(P10>0,"一部入金・超過","期日超過"),IF(P10>0,"一部入金",IF(L10-設定!$C$5<=設定!$C$6,"期日間近","入金待ち"))))))))) -> 取消 | V10: =IF(OR(U10="期日超過",U10="一部入金・超過"),設定!$C$5-L10,"") | W10: =IF(A10="","",TRIM(IF(B10="","請求日 ","")&IF(C10="","取引先 ",IF(D10="コード誤り","取引先コード誤り ",""))&IF(E10="","件名 ","")&IF(F10="","税抜金額 ","")&IF(G10="","税率 ","")&IF(M10="","送付方法 ","")&IF(AND(N10<>"",O10=""),"送付者 ","")&IF(AND(I10<>"",L10=""),"入金期日 ","")&IF(AND(N10<>"",P10>0,S10<=0,X10=""),"消込確認者 ",""))) | Y10: SAMPLE: 金額誤りのため取消→次行で再発行
A11: =IF(COUNTA(B11,C11,E11,F11)=0,"",設定!$C$4&TEXT(ROW()-4,"00000")) -> INV-00007 | B11: 46280 | C11: C003 | D11: =IF(C11="","",IFERROR(INDEX(取引先マスタ!$B$5:$B$204,MATCH($C11,取引先マスタ!$A$5:$A$204,0)),"コード誤り")) -> 合同会社デモ | E11: 追加作業費(再発行) | F11: 33000 | G11: 0.1 | H11: =IF(OR(F11="",G11=""),"",ROUNDDOWN(F11*G11,0)) -> 3300 | I11: =IF(OR(F11="",G11=""),"",F11+H11) -> 36300 | J11: =IF(OR(B11="",C11="",D11="コード誤り"),"",IFERROR(DATE(YEAR(B11),MONTH(B11)+INDEX(取引先マスタ!$E$5:$E$204,MATCH($C11,取引先マスタ!$A$5:$A$204,0)),MIN(INDEX(取引先マスタ!$F$5:$F$204,MATCH($C11,取引先マスタ!$A$5:$A$204,0)),DAY(EOMONTH(B11,INDEX(取引先マスタ!$E$5:$E$204,MATCH($C11,取引先マスタ!$A$5:$A$204,0)))))),"")) -> 46326 | K11: 46300 | L11: =IF(K11<>"",K11,J11) -> 46300 | M11: 請求書発行システム | N11: 46281 | O11: 鈴木 | P11: =IF(A11="","",SUMIF(入金明細!$F$5:$F$1004,A11,入金明細!$E$5:$E$1004)) -> 0 | Q11: =IF(OR(A11="",N(P11)=0),"",SUMPRODUCT(MAX((入金明細!$F$5:$F$1004=A11)*入金明細!$B$5:$B$1004))) | S11: =IF(OR(A11="",I11=""),"",I11-N(P11)-N(R11)) -> 36300 | U11: =IF(A11="","",IF(T11="取消","取消",IF(W11<>"","要入力",IF(N11="","未送付",IF(S11=0,"入金済",IF(S11<0,"過入金",IF(設定!$C$5>L11,IF(P11>0,"一部入金・超過","期日超過"),IF(P11>0,"一部入金",IF(L11-設定!$C$5<=設定!$C$6,"期日間近","入金待ち"))))))))) -> 期日間近 | V11: =IF(OR(U11="期日超過",U11="一部入金・超過"),設定!$C$5-L11,"") | W11: =IF(A11="","",TRIM(IF(B11="","請求日 ","")&IF(C11="","取引先 ",IF(D11="コード誤り","取引先コード誤り ",""))&IF(E11="","件名 ","")&IF(F11="","税抜金額 ","")&IF(G11="","税率 ","")&IF(M11="","送付方法 ","")&IF(AND(N11<>"",O11=""),"送付者 ","")&IF(AND(I11<>"",L11=""),"入金期日 ","")&IF(AND(N11<>"",P11>0,S11<=0,X11=""),"消込確認者 ",""))) | Y11: SAMPLE: 個別期日・期日間近
A12: =IF(COUNTA(B12,C12,E12,F12)=0,"",設定!$C$4&TEXT(ROW()-4,"00000")) | D12: =IF(C12="","",IFERROR(INDEX(取引先マスタ!$B$5:$B$204,MATCH($C12,取引先マスタ!$A$5:$A$204,0)),"コード誤り")) | H12: =IF(OR(F12="",G12=""),"",ROUNDDOWN(F12*G12,0)) | I12: =IF(OR(F12="",G12=""),"",F12+H12) | J12: =IF(OR(B12="",C12="",D12="コード誤り"),"",IFERROR(DATE(YEAR(B12),MONTH(B12)+INDEX(取引先マスタ!$E$5:$E$204,MATCH($C12,取引先マスタ!$A$5:$A$204,0)),MIN(INDEX(取引先マスタ!$F$5:$F$204,MATCH($C12,取引先マスタ!$A$5:$A$204,0)),DAY(EOMONTH(B12,INDEX(取引先マスタ!$E$5:$E$204,MATCH($C12,取引先マスタ!$A$5:$A$204,0)))))),"")) | L12: =IF(K12<>"",K12,J12) | P12: =IF(A12="","",SUMIF(入金明細!$F$5:$F$1004,A12,入金明細!$E$5:$E$1004)) | Q12: =IF(OR(A12="",N(P12)=0),"",SUMPRODUCT(MAX((入金明細!$F$5:$F$1004=A12)*入金明細!$B$5:$B$1004))) | S12: =IF(OR(A12="",I12=""),"",I12-N(P12)-N(R12)) | U12: =IF(A12="","",IF(T12="取消","取消",IF(W12<>"","要入力",IF(N12="","未送付",IF(S12=0,"入金済",IF(S12<0,"過入金",IF(設定!$C$5>L12,IF(P12>0,"一部入金・超過","期日超過"),IF(P12>0,"一部入金",IF(L12-設定!$C$5<=設定!$C$6,"期日間近","入金待ち"))))))))) | V12: =IF(OR(U12="期日超過",U12="一部入金・超過"),設定!$C$5-L12,"") | W12: =IF(A12="","",TRIM(IF(B12="","請求日 ","")&IF(C12="","取引先 ",IF(D12="コード誤り","取引先コード誤り ",""))&IF(E12="","件名 ","")&IF(F12="","税抜金額 ","")&IF(G12="","税率 ","")&IF(M12="","送付方法 ","")&IF(AND(N12<>"",O12=""),"送付者 ","")&IF(AND(I12<>"",L12=""),"入金期日 ","")&IF(AND(N12<>"",P12>0,S12<=0,X12=""),"消込確認者 ","")))
A13: =IF(COUNTA(B13,C13,E13,F13)=0,"",設定!$C$4&TEXT(ROW()-4,"00000")) | D13: =IF(C13="","",IFERROR(INDEX(取引先マスタ!$B$5:$B$204,MATCH($C13,取引先マスタ!$A$5:$A$204,0)),"コード誤り")) | H13: =IF(OR(F13="",G13=""),"",ROUNDDOWN(F13*G13,0)) | I13: =IF(OR(F13="",G13=""),"",F13+H13) | J13: =IF(OR(B13="",C13="",D13="コード誤り"),"",IFERROR(DATE(YEAR(B13),MONTH(B13)+INDEX(取引先マスタ!$E$5:$E$204,MATCH($C13,取引先マスタ!$A$5:$A$204,0)),MIN(INDEX(取引先マスタ!$F$5:$F$204,MATCH($C13,取引先マスタ!$A$5:$A$204,0)),DAY(EOMONTH(B13,INDEX(取引先マスタ!$E$5:$E$204,MATCH($C13,取引先マスタ!$A$5:$A$204,0)))))),"")) | L13: =IF(K13<>"",K13,J13) | P13: =IF(A13="","",SUMIF(入金明細!$F$5:$F$1004,A13,入金明細!$E$5:$E$1004)) | Q13: =IF(OR(A13="",N(P13)=0),"",SUMPRODUCT(MAX((入金明細!$F$5:$F$1004=A13)*入金明細!$B$5:$B$1004))) | S13: =IF(OR(A13="",I13=""),"",I13-N(P13)-N(R13)) | U13: =IF(A13="","",IF(T13="取消","取消",IF(W13<>"","要入力",IF(N13="","未送付",IF(S13=0,"入金済",IF(S13<0,"過入金",IF(設定!$C$5>L13,IF(P13>0,"一部入金・超過","期日超過"),IF(P13>0,"一部入金",IF(L13-設定!$C$5<=設定!$C$6,"期日間近","入金待ち"))))))))) | V13: =IF(OR(U13="期日超過",U13="一部入金・超過"),設定!$C$5-L13,"") | W13: =IF(A13="","",TRIM(IF(B13="","請求日 ","")&IF(C13="","取引先 ",IF(D13="コード誤り","取引先コード誤り ",""))&IF(E13="","件名 ","")&IF(F13="","税抜金額 ","")&IF(G13="","税率 ","")&IF(M13="","送付方法 ","")&IF(AND(N13<>"",O13=""),"送付者 ","")&IF(AND(I13<>"",L13=""),"入金期日 ","")&IF(AND(N13<>"",P13>0,S13<=0,X13=""),"消込確認者 ","")))
A14: =IF(COUNTA(B14,C14,E14,F14)=0,"",設定!$C$4&TEXT(ROW()-4,"00000")) | D14: =IF(C14="","",IFERROR(INDEX(取引先マスタ!$B$5:$B$204,MATCH($C14,取引先マスタ!$A$5:$A$204,0)),"コード誤り")) | H14: =IF(OR(F14="",G14=""),"",ROUNDDOWN(F14*G14,0)) | I14: =IF(OR(F14="",G14=""),"",F14+H14) | J14: =IF(OR(B14="",C14="",D14="コード誤り"),"",IFERROR(DATE(YEAR(B14),MONTH(B14)+INDEX(取引先マスタ!$E$5:$E$204,MATCH($C14,取引先マスタ!$A$5:$A$204,0)),MIN(INDEX(取引先マスタ!$F$5:$F$204,MATCH($C14,取引先マスタ!$A$5:$A$204,0)),DAY(EOMONTH(B14,INDEX(取引先マスタ!$E$5:$E$204,MATCH($C14,取引先マスタ!$A$5:$A$204,0)))))),"")) | L14: =IF(K14<>"",K14,J14) | P14: =IF(A14="","",SUMIF(入金明細!$F$5:$F$1004,A14,入金明細!$E$5:$E$1004)) | Q14: =IF(OR(A14="",N(P14)=0),"",SUMPRODUCT(MAX((入金明細!$F$5:$F$1004=A14)*入金明細!$B$5:$B$1004))) | S14: =IF(OR(A14="",I14=""),"",I14-N(P14)-N(R14)) | U14: =IF(A14="","",IF(T14="取消","取消",IF(W14<>"","要入力",IF(N14="","未送付",IF(S14=0,"入金済",IF(S14<0,"過入金",IF(設定!$C$5>L14,IF(P14>0,"一部入金・超過","期日超過"),IF(P14>0,"一部入金",IF(L14-設定!$C$5<=設定!$C$6,"期日間近","入金待ち"))))))))) | V14: =IF(OR(U14="期日超過",U14="一部入金・超過"),設定!$C$5-L14,"") | W14: =IF(A14="","",TRIM(IF(B14="","請求日 ","")&IF(C14="","取引先 ",IF(D14="コード誤り","取引先コード誤り ",""))&IF(E14="","件名 ","")&IF(F14="","税抜金額 ","")&IF(G14="","税率 ","")&IF(M14="","送付方法 ","")&IF(AND(N14<>"",O14=""),"送付者 ","")&IF(AND(I14<>"",L14=""),"入金期日 ","")&IF(AND(N14<>"",P14>0,S14<=0,X14=""),"消込確認者 ","")))
A15: =IF(COUNTA(B15,C15,E15,F15)=0,"",設定!$C$4&TEXT(ROW()-4,"00000")) | D15: =IF(C15="","",IFERROR(INDEX(取引先マスタ!$B$5:$B$204,MATCH($C15,取引先マスタ!$A$5:$A$204,0)),"コード誤り")) | H15: =IF(OR(F15="",G15=""),"",ROUNDDOWN(F15*G15,0)) | I15: =IF(OR(F15="",G15=""),"",F15+H15) | J15: =IF(OR(B15="",C15="",D15="コード誤り"),"",IFERROR(DATE(YEAR(B15),MONTH(B15)+INDEX(取引先マスタ!$E$5:$E$204,MATCH($C15,取引先マスタ!$A$5:$A$204,0)),MIN(INDEX(取引先マスタ!$F$5:$F$204,MATCH($C15,取引先マスタ!$A$5:$A$204,0)),DAY(EOMONTH(B15,INDEX(取引先マスタ!$E$5:$E$204,MATCH($C15,取引先マスタ!$A$5:$A$204,0)))))),"")) | L15: =IF(K15<>"",K15,J15) | P15: =IF(A15="","",SUMIF(入金明細!$F$5:$F$1004,A15,入金明細!$E$5:$E$1004)) | Q15: =IF(OR(A15="",N(P15)=0),"",SUMPRODUCT(MAX((入金明細!$F$5:$F$1004=A15)*入金明細!$B$5:$B$1004))) | S15: =IF(OR(A15="",I15=""),"",I15-N(P15)-N(R15)) | U15: =IF(A15="","",IF(T15="取消","取消",IF(W15<>"","要入力",IF(N15="","未送付",IF(S15=0,"入金済",IF(S15<0,"過入金",IF(設定!$C$5>L15,IF(P15>0,"一部入金・超過","期日超過"),IF(P15>0,"一部入金",IF(L15-設定!$C$5<=設定!$C$6,"期日間近","入金待ち"))))))))) | V15: =IF(OR(U15="期日超過",U15="一部入金・超過"),設定!$C$5-L15,"") | W15: =IF(A15="","",TRIM(IF(B15="","請求日 ","")&IF(C15="","取引先 ",IF(D15="コード誤り","取引先コード誤り ",""))&IF(E15="","件名 ","")&IF(F15="","税抜金額 ","")&IF(G15="","税率 ","")&IF(M15="","送付方法 ","")&IF(AND(N15<>"",O15=""),"送付者 ","")&IF(AND(I15<>"",L15=""),"入金期日 ","")&IF(AND(N15<>"",P15>0,S15<=0,X15=""),"消込確認者 ","")))
A16: =IF(COUNTA(B16,C16,E16,F16)=0,"",設定!$C$4&TEXT(ROW()-4,"00000")) | D16: =IF(C16="","",IFERROR(INDEX(取引先マスタ!$B$5:$B$204,MATCH($C16,取引先マスタ!$A$5:$A$204,0)),"コード誤り")) | H16: =IF(OR(F16="",G16=""),"",ROUNDDOWN(F16*G16,0)) | I16: =IF(OR(F16="",G16=""),"",F16+H16) | J16: =IF(OR(B16="",C16="",D16="コード誤り"),"",IFERROR(DATE(YEAR(B16),MONTH(B16)+INDEX(取引先マスタ!$E$5:$E$204,MATCH($C16,取引先マスタ!$A$5:$A$204,0)),MIN(INDEX(取引先マスタ!$F$5:$F$204,MATCH($C16,取引先マスタ!$A$5:$A$204,0)),DAY(EOMONTH(B16,INDEX(取引先マスタ!$E$5:$E$204,MATCH($C16,取引先マスタ!$A$5:$A$204,0)))))),"")) | L16: =IF(K16<>"",K16,J16) | P16: =IF(A16="","",SUMIF(入金明細!$F$5:$F$1004,A16,入金明細!$E$5:$E$1004)) | Q16: =IF(OR(A16="",N(P16)=0),"",SUMPRODUCT(MAX((入金明細!$F$5:$F$1004=A16)*入金明細!$B$5:$B$1004))) | S16: =IF(OR(A16="",I16=""),"",I16-N(P16)-N(R16)) | U16: =IF(A16="","",IF(T16="取消","取消",IF(W16<>"","要入力",IF(N16="","未送付",IF(S16=0,"入金済",IF(S16<0,"過入金",IF(設定!$C$5>L16,IF(P16>0,"一部入金・超過","期日超過"),IF(P16>0,"一部入金",IF(L16-設定!$C$5<=設定!$C$6,"期日間近","入金待ち"))))))))) | V16: =IF(OR(U16="期日超過",U16="一部入金・超過"),設定!$C$5-L16,"") | W16: =IF(A16="","",TRIM(IF(B16="","請求日 ","")&IF(C16="","取引先 ",IF(D16="コード誤り","取引先コード誤り ",""))&IF(E16="","件名 ","")&IF(F16="","税抜金額 ","")&IF(G16="","税率 ","")&IF(M16="","送付方法 ","")&IF(AND(N16<>"",O16=""),"送付者 ","")&IF(AND(I16<>"",L16=""),"入金期日 ","")&IF(AND(N16<>"",P16>0,S16<=0,X16=""),"消込確認者 ","")))
A17: =IF(COUNTA(B17,C17,E17,F17)=0,"",設定!$C$4&TEXT(ROW()-4,"00000")) | D17: =IF(C17="","",IFERROR(INDEX(取引先マスタ!$B$5:$B$204,MATCH($C17,取引先マスタ!$A$5:$A$204,0)),"コード誤り")) | H17: =IF(OR(F17="",G17=""),"",ROUNDDOWN(F17*G17,0)) | I17: =IF(OR(F17="",G17=""),"",F17+H17) | J17: =IF(OR(B17="",C17="",D17="コード誤り"),"",IFERROR(DATE(YEAR(B17),MONTH(B17)+INDEX(取引先マスタ!$E$5:$E$204,MATCH($C17,取引先マスタ!$A$5:$A$204,0)),MIN(INDEX(取引先マスタ!$F$5:$F$204,MATCH($C17,取引先マスタ!$A$5:$A$204,0)),DAY(EOMONTH(B17,INDEX(取引先マスタ!$E$5:$E$204,MATCH($C17,取引先マスタ!$A$5:$A$204,0)))))),"")) | L17: =IF(K17<>"",K17,J17) | P17: =IF(A17="","",SUMIF(入金明細!$F$5:$F$1004,A17,入金明細!$E$5:$E$1004)) | Q17: =IF(OR(A17="",N(P17)=0),"",SUMPRODUCT(MAX((入金明細!$F$5:$F$1004=A17)*入金明細!$B$5:$B$1004))) | S17: =IF(OR(A17="",I17=""),"",I17-N(P17)-N(R17)) | U17: =IF(A17="","",IF(T17="取消","取消",IF(W17<>"","要入力",IF(N17="","未送付",IF(S17=0,"入金済",IF(S17<0,"過入金",IF(設定!$C$5>L17,IF(P17>0,"一部入金・超過","期日超過"),IF(P17>0,"一部入金",IF(L17-設定!$C$5<=設定!$C$6,"期日間近","入金待ち"))))))))) | V17: =IF(OR(U17="期日超過",U17="一部入金・超過"),設定!$C$5-L17,"") | W17: =IF(A17="","",TRIM(IF(B17="","請求日 ","")&IF(C17="","取引先 ",IF(D17="コード誤り","取引先コード誤り ",""))&IF(E17="","件名 ","")&IF(F17="","税抜金額 ","")&IF(G17="","税率 ","")&IF(M17="","送付方法 ","")&IF(AND(N17<>"",O17=""),"送付者 ","")&IF(AND(I17<>"",L17=""),"入金期日 ","")&IF(AND(N17<>"",P17>0,S17<=0,X17=""),"消込確認者 ","")))
A18: =IF(COUNTA(B18,C18,E18,F18)=0,"",設定!$C$4&TEXT(ROW()-4,"00000")) | D18: =IF(C18="","",IFERROR(INDEX(取引先マスタ!$B$5:$B$204,MATCH($C18,取引先マスタ!$A$5:$A$204,0)),"コード誤り")) | H18: =IF(OR(F18="",G18=""),"",ROUNDDOWN(F18*G18,0)) | I18: =IF(OR(F18="",G18=""),"",F18+H18) | J18: =IF(OR(B18="",C18="",D18="コード誤り"),"",IFERROR(DATE(YEAR(B18),MONTH(B18)+INDEX(取引先マスタ!$E$5:$E$204,MATCH($C18,取引先マスタ!$A$5:$A$204,0)),MIN(INDEX(取引先マスタ!$F$5:$F$204,MATCH($C18,取引先マスタ!$A$5:$A$204,0)),DAY(EOMONTH(B18,INDEX(取引先マスタ!$E$5:$E$204,MATCH($C18,取引先マスタ!$A$5:$A$204,0)))))),"")) | L18: =IF(K18<>"",K18,J18) | P18: =IF(A18="","",SUMIF(入金明細!$F$5:$F$1004,A18,入金明細!$E$5:$E$1004)) | Q18: =IF(OR(A18="",N(P18)=0),"",SUMPRODUCT(MAX((入金明細!$F$5:$F$1004=A18)*入金明細!$B$5:$B$1004))) | S18: =IF(OR(A18="",I18=""),"",I18-N(P18)-N(R18)) | U18: =IF(A18="","",IF(T18="取消","取消",IF(W18<>"","要入力",IF(N18="","未送付",IF(S18=0,"入金済",IF(S18<0,"過入金",IF(設定!$C$5>L18,IF(P18>0,"一部入金・超過","期日超過"),IF(P18>0,"一部入金",IF(L18-設定!$C$5<=設定!$C$6,"期日間近","入金待ち"))))))))) | V18: =IF(OR(U18="期日超過",U18="一部入金・超過"),設定!$C$5-L18,"") | W18: =IF(A18="","",TRIM(IF(B18="","請求日 ","")&IF(C18="","取引先 ",IF(D18="コード誤り","取引先コード誤り ",""))&IF(E18="","件名 ","")&IF(F18="","税抜金額 ","")&IF(G18="","税率 ","")&IF(M18="","送付方法 ","")&IF(AND(N18<>"",O18=""),"送付者 ","")&IF(AND(I18<>"",L18=""),"入金期日 ","")&IF(AND(N18<>"",P18>0,S18<=0,X18=""),"消込確認者 ","")))
A19: =IF(COUNTA(B19,C19,E19,F19)=0,"",設定!$C$4&TEXT(ROW()-4,"00000")) | D19: =IF(C19="","",IFERROR(INDEX(取引先マスタ!$B$5:$B$204,MATCH($C19,取引先マスタ!$A$5:$A$204,0)),"コード誤り")) | H19: =IF(OR(F19="",G19=""),"",ROUNDDOWN(F19*G19,0)) | I19: =IF(OR(F19="",G19=""),"",F19+H19) | J19: =IF(OR(B19="",C19="",D19="コード誤り"),"",IFERROR(DATE(YEAR(B19),MONTH(B19)+INDEX(取引先マスタ!$E$5:$E$204,MATCH($C19,取引先マスタ!$A$5:$A$204,0)),MIN(INDEX(取引先マスタ!$F$5:$F$204,MATCH($C19,取引先マスタ!$A$5:$A$204,0)),DAY(EOMONTH(B19,INDEX(取引先マスタ!$E$5:$E$204,MATCH($C19,取引先マスタ!$A$5:$A$204,0)))))),"")) | L19: =IF(K19<>"",K19,J19) | P19: =IF(A19="","",SUMIF(入金明細!$F$5:$F$1004,A19,入金明細!$E$5:$E$1004)) | Q19: =IF(OR(A19="",N(P19)=0),"",SUMPRODUCT(MAX((入金明細!$F$5:$F$1004=A19)*入金明細!$B$5:$B$1004))) | S19: =IF(OR(A19="",I19=""),"",I19-N(P19)-N(R19)) | U19: =IF(A19="","",IF(T19="取消","取消",IF(W19<>"","要入力",IF(N19="","未送付",IF(S19=0,"入金済",IF(S19<0,"過入金",IF(設定!$C$5>L19,IF(P19>0,"一部入金・超過","期日超過"),IF(P19>0,"一部入金",IF(L19-設定!$C$5<=設定!$C$6,"期日間近","入金待ち"))))))))) | V19: =IF(OR(U19="期日超過",U19="一部入金・超過"),設定!$C$5-L19,"") | W19: =IF(A19="","",TRIM(IF(B19="","請求日 ","")&IF(C19="","取引先 ",IF(D19="コード誤り","取引先コード誤り ",""))&IF(E19="","件名 ","")&IF(F19="","税抜金額 ","")&IF(G19="","税率 ","")&IF(M19="","送付方法 ","")&IF(AND(N19<>"",O19=""),"送付者 ","")&IF(AND(I19<>"",L19=""),"入金期日 ","")&IF(AND(N19<>"",P19>0,S19<=0,X19=""),"消込確認者 ","")))
A20: =IF(COUNTA(B20,C20,E20,F20)=0,"",設定!$C$4&TEXT(ROW()-4,"00000")) | D20: =IF(C20="","",IFERROR(INDEX(取引先マスタ!$B$5:$B$204,MATCH($C20,取引先マスタ!$A$5:$A$204,0)),"コード誤り")) | H20: =IF(OR(F20="",G20=""),"",ROUNDDOWN(F20*G20,0)) | I20: =IF(OR(F20="",G20=""),"",F20+H20) | J20: =IF(OR(B20="",C20="",D20="コード誤り"),"",IFERROR(DATE(YEAR(B20),MONTH(B20)+INDEX(取引先マスタ!$E$5:$E$204,MATCH($C20,取引先マスタ!$A$5:$A$204,0)),MIN(INDEX(取引先マスタ!$F$5:$F$204,MATCH($C20,取引先マスタ!$A$5:$A$204,0)),DAY(EOMONTH(B20,INDEX(取引先マスタ!$E$5:$E$204,MATCH($C20,取引先マスタ!$A$5:$A$204,0)))))),"")) | L20: =IF(K20<>"",K20,J20) | P20: =IF(A20="","",SUMIF(入金明細!$F$5:$F$1004,A20,入金明細!$E$5:$E$1004)) | Q20: =IF(OR(A20="",N(P20)=0),"",SUMPRODUCT(MAX((入金明細!$F$5:$F$1004=A20)*入金明細!$B$5:$B$1004))) | S20: =IF(OR(A20="",I20=""),"",I20-N(P20)-N(R20)) | U20: =IF(A20="","",IF(T20="取消","取消",IF(W20<>"","要入力",IF(N20="","未送付",IF(S20=0,"入金済",IF(S20<0,"過入金",IF(設定!$C$5>L20,IF(P20>0,"一部入金・超過","期日超過"),IF(P20>0,"一部入金",IF(L20-設定!$C$5<=設定!$C$6,"期日間近","入金待ち"))))))))) | V20: =IF(OR(U20="期日超過",U20="一部入金・超過"),設定!$C$5-L20,"") | W20: =IF(A20="","",TRIM(IF(B20="","請求日 ","")&IF(C20="","取引先 ",IF(D20="コード誤り","取引先コード誤り ",""))&IF(E20="","件名 ","")&IF(F20="","税抜金額 ","")&IF(G20="","税率 ","")&IF(M20="","送付方法 ","")&IF(AND(N20<>"",O20=""),"送付者 ","")&IF(AND(I20<>"",L20=""),"入金期日 ","")&IF(AND(N20<>"",P20>0,S20<=0,X20=""),"消込確認者 ","")))
A21: =IF(COUNTA(B21,C21,E21,F21)=0,"",設定!$C$4&TEXT(ROW()-4,"00000")) | D21: =IF(C21="","",IFERROR(INDEX(取引先マスタ!$B$5:$B$204,MATCH($C21,取引先マスタ!$A$5:$A$204,0)),"コード誤り")) | H21: =IF(OR(F21="",G21=""),"",ROUNDDOWN(F21*G21,0)) | I21: =IF(OR(F21="",G21=""),"",F21+H21) | J21: =IF(OR(B21="",C21="",D21="コード誤り"),"",IFERROR(DATE(YEAR(B21),MONTH(B21)+INDEX(取引先マスタ!$E$5:$E$204,MATCH($C21,取引先マスタ!$A$5:$A$204,0)),MIN(INDEX(取引先マスタ!$F$5:$F$204,MATCH($C21,取引先マスタ!$A$5:$A$204,0)),DAY(EOMONTH(B21,INDEX(取引先マスタ!$E$5:$E$204,MATCH($C21,取引先マスタ!$A$5:$A$204,0)))))),"")) | L21: =IF(K21<>"",K21,J21) | P21: =IF(A21="","",SUMIF(入金明細!$F$5:$F$1004,A21,入金明細!$E$5:$E$1004)) | Q21: =IF(OR(A21="",N(P21)=0),"",SUMPRODUCT(MAX((入金明細!$F$5:$F$1004=A21)*入金明細!$B$5:$B$1004))) | S21: =IF(OR(A21="",I21=""),"",I21-N(P21)-N(R21)) | U21: =IF(A21="","",IF(T21="取消","取消",IF(W21<>"","要入力",IF(N21="","未送付",IF(S21=0,"入金済",IF(S21<0,"過入金",IF(設定!$C$5>L21,IF(P21>0,"一部入金・超過","期日超過"),IF(P21>0,"一部入金",IF(L21-設定!$C$5<=設定!$C$6,"期日間近","入金待ち"))))))))) | V21: =IF(OR(U21="期日超過",U21="一部入金・超過"),設定!$C$5-L21,"") | W21: =IF(A21="","",TRIM(IF(B21="","請求日 ","")&IF(C21="","取引先 ",IF(D21="コード誤り","取引先コード誤り ",""))&IF(E21="","件名 ","")&IF(F21="","税抜金額 ","")&IF(G21="","税率 ","")&IF(M21="","送付方法 ","")&IF(AND(N21<>"",O21=""),"送付者 ","")&IF(AND(I21<>"",L21=""),"入金期日 ","")&IF(AND(N21<>"",P21>0,S21<=0,X21=""),"消込確認者 ","")))
A22: =IF(COUNTA(B22,C22,E22,F22)=0,"",設定!$C$4&TEXT(ROW()-4,"00000")) | D22: =IF(C22="","",IFERROR(INDEX(取引先マスタ!$B$5:$B$204,MATCH($C22,取引先マスタ!$A$5:$A$204,0)),"コード誤り")) | H22: =IF(OR(F22="",G22=""),"",ROUNDDOWN(F22*G22,0)) | I22: =IF(OR(F22="",G22=""),"",F22+H22) | J22: =IF(OR(B22="",C22="",D22="コード誤り"),"",IFERROR(DATE(YEAR(B22),MONTH(B22)+INDEX(取引先マスタ!$E$5:$E$204,MATCH($C22,取引先マスタ!$A$5:$A$204,0)),MIN(INDEX(取引先マスタ!$F$5:$F$204,MATCH($C22,取引先マスタ!$A$5:$A$204,0)),DAY(EOMONTH(B22,INDEX(取引先マスタ!$E$5:$E$204,MATCH($C22,取引先マスタ!$A$5:$A$204,0)))))),"")) | L22: =IF(K22<>"",K22,J22) | P22: =IF(A22="","",SUMIF(入金明細!$F$5:$F$1004,A22,入金明細!$E$5:$E$1004)) | Q22: =IF(OR(A22="",N(P22)=0),"",SUMPRODUCT(MAX((入金明細!$F$5:$F$1004=A22)*入金明細!$B$5:$B$1004))) | S22: =IF(OR(A22="",I22=""),"",I22-N(P22)-N(R22)) | U22: =IF(A22="","",IF(T22="取消","取消",IF(W22<>"","要入力",IF(N22="","未送付",IF(S22=0,"入金済",IF(S22<0,"過入金",IF(設定!$C$5>L22,IF(P22>0,"一部入金・超過","期日超過"),IF(P22>0,"一部入金",IF(L22-設定!$C$5<=設定!$C$6,"期日間近","入金待ち"))))))))) | V22: =IF(OR(U22="期日超過",U22="一部入金・超過"),設定!$C$5-L22,"") | W22: =IF(A22="","",TRIM(IF(B22="","請求日 ","")&IF(C22="","取引先 ",IF(D22="コード誤り","取引先コード誤り ",""))&IF(E22="","件名 ","")&IF(F22="","税抜金額 ","")&IF(G22="","税率 ","")&IF(M22="","送付方法 ","")&IF(AND(N22<>"",O22=""),"送付者 ","")&IF(AND(I22<>"",L22=""),"入金期日 ","")&IF(AND(N22<>"",P22>0,S22<=0,X22=""),"消込確認者 ","")))
A23: =IF(COUNTA(B23,C23,E23,F23)=0,"",設定!$C$4&TEXT(ROW()-4,"00000")) | D23: =IF(C23="","",IFERROR(INDEX(取引先マスタ!$B$5:$B$204,MATCH($C23,取引先マスタ!$A$5:$A$204,0)),"コード誤り")) | H23: =IF(OR(F23="",G23=""),"",ROUNDDOWN(F23*G23,0)) | I23: =IF(OR(F23="",G23=""),"",F23+H23) | J23: =IF(OR(B23="",C23="",D23="コード誤り"),"",IFERROR(DATE(YEAR(B23),MONTH(B23)+INDEX(取引先マスタ!$E$5:$E$204,MATCH($C23,取引先マスタ!$A$5:$A$204,0)),MIN(INDEX(取引先マスタ!$F$5:$F$204,MATCH($C23,取引先マスタ!$A$5:$A$204,0)),DAY(EOMONTH(B23,INDEX(取引先マスタ!$E$5:$E$204,MATCH($C23,取引先マスタ!$A$5:$A$204,0)))))),"")) | L23: =IF(K23<>"",K23,J23) | P23: =IF(A23="","",SUMIF(入金明細!$F$5:$F$1004,A23,入金明細!$E$5:$E$1004)) | Q23: =IF(OR(A23="",N(P23)=0),"",SUMPRODUCT(MAX((入金明細!$F$5:$F$1004=A23)*入金明細!$B$5:$B$1004))) | S23: =IF(OR(A23="",I23=""),"",I23-N(P23)-N(R23)) | U23: =IF(A23="","",IF(T23="取消","取消",IF(W23<>"","要入力",IF(N23="","未送付",IF(S23=0,"入金済",IF(S23<0,"過入金",IF(設定!$C$5>L23,IF(P23>0,"一部入金・超過","期日超過"),IF(P23>0,"一部入金",IF(L23-設定!$C$5<=設定!$C$6,"期日間近","入金待ち"))))))))) | V23: =IF(OR(U23="期日超過",U23="一部入金・超過"),設定!$C$5-L23,"") | W23: =IF(A23="","",TRIM(IF(B23="","請求日 ","")&IF(C23="","取引先 ",IF(D23="コード誤り","取引先コード誤り ",""))&IF(E23="","件名 ","")&IF(F23="","税抜金額 ","")&IF(G23="","税率 ","")&IF(M23="","送付方法 ","")&IF(AND(N23<>"",O23=""),"送付者 ","")&IF(AND(I23<>"",L23=""),"入金期日 ","")&IF(AND(N23<>"",P23>0,S23<=0,X23=""),"消込確認者 ","")))
... A504: =IF(COUNTA(B504,C504,E504,F504)=0,"",設定!$C$4&TEXT(ROW()-4,"00000")) | D504: =IF(C504="","",IFERROR(INDEX(取引先マスタ!$B$5:$B$204,MATCH($C504,取引先マスタ!$A$5:$A$204,0)),"コード誤り")) | H504: =IF(OR(F504="",G504=""),"",ROUNDDOWN(F504*G504,0)) | I504: =IF(OR(F504="",G504=""),"",F504+H504) | J504: =IF(OR(B504="",C504="",D504="コード誤り"),"",IFERROR(DATE(YEAR(B504),MONTH(B504)+INDEX(取引先マスタ!$E$5:$E$204,MATCH($C504,取引先マスタ!$A$5:$A$204,0)),MIN(INDEX(取引先マスタ!$F$5:$F$204,MATCH($C504,取引先マスタ!$A$5:$A$204,0)),DAY(EOMONTH(B504,INDEX(取引先マスタ!$E$5:$E$204,MATCH($C504,取引先マスタ!$A$5:$A$204,0)))))),"")) | L504: =IF(K504<>"",K504,J504) | P504: =IF(A504="","",SUMIF(入金明細!$F$5:$F$1004,A504,入金明細!$E$5:$E$1004)) | Q504: =IF(OR(A504="",N(P504)=0),"",SUMPRODUCT(MAX((入金明細!$F$5:$F$1004=A504)*入金明細!$B$5:$B$1004))) | S504: =IF(OR(A504="",I504=""),"",I504-N(P504)-N(R504)) | U504: =IF(A504="","",IF(T504="取消","取消",IF(W504<>"","要入力",IF(N504="","未送付",IF(S504=0,"入金済",IF(S504<0,"過入金",IF(設定!$C$5>L504,IF(P504>0,"一部入金・超過","期日超過"),IF(P504>0,"一部入金",IF(L504-設定!$C$5<=設定!$C$6,"期日間近","入金待ち"))))))))) | V504: =IF(OR(U504="期日超過",U504="一部入金・超過"),設定!$C$5-L504,"") | W504: =IF(A504="","",TRIM(IF(B504="","請求日 ","")&IF(C504="","取引先 ",IF(D504="コード誤り","取引先コード誤り ",""))&IF(E504="","件名 ","")&IF(F504="","税抜金額 ","")&IF(G504="","税率 ","")&IF(M504="","送付方法 ","")&IF(AND(N504<>"",O504=""),"送付者 ","")&IF(AND(I504<>"",L504=""),"入金期日 ","")&IF(AND(N504<>"",P504>0,S504<=0,X504=""),"消込確認者 ","")))

Sheet 入金明細
A1: 入金明細
A2: 通帳・ネットバンキングの入金を全件転記し、「消込先請求番号」を入力します。1つの入金で複数請求を払われた場合は行を分けて金額を按分。
A4: No | B4: 入金日 | C4: 入金口座 | D4: 振込名義 | E4: 入金額 | F4: 消込先請求番号 | G4: 取引先名(請求) | H4: 請求額(税込) | I4: 消込状態 | J4: 記帳者 | K4: 備考
A5: =IF(COUNTA(B5,D5,E5,F5)=0,"",ROW()-4) -> 1 | B5: 46265 | C5: ○○銀行 本店 普通 | D5: カ)サンプルシヨウジ | E5: 110000 | F5: INV-00001 | G5: =IF(F5="","",IFERROR(INDEX(請求台帳!$D$5:$D$504,MATCH(F5,請求台帳!$A$5:$A$504,0)),"")) -> 株式会社サンプル商事 | H5: =IF(F5="","",IFERROR(INDEX(請求台帳!$I$5:$I$504,MATCH(F5,請求台帳!$A$5:$A$504,0)),"")) -> 110000 | I5: =IF(COUNTA(B5,D5,E5,F5)=0,"",IF(OR(B5="",E5=""),"要入力",IF(F5="","未消込",IF(ISNA(MATCH(F5,請求台帳!$A$5:$A$504,0)),"番号誤り",IF(INDEX(請求台帳!$T$5:$T$504,MATCH(F5,請求台帳!$A$5:$A$504,0))="取消","取消請求へ消込","消込済"))))) -> 消込済 | J5: 佐々木 | K5: SAMPLE
A6: =IF(COUNTA(B6,D6,E6,F6)=0,"",ROW()-4) -> 2 | B6: 46275 | C6: ○○銀行 本店 普通 | D6: ユ)テストコウギヨウ | E6: 274560 | F6: INV-00002 | G6: =IF(F6="","",IFERROR(INDEX(請求台帳!$D$5:$D$504,MATCH(F6,請求台帳!$A$5:$A$504,0)),"")) -> 有限会社テスト工業 | H6: =IF(F6="","",IFERROR(INDEX(請求台帳!$I$5:$I$504,MATCH(F6,請求台帳!$A$5:$A$504,0)),"")) -> 275000 | I6: =IF(COUNTA(B6,D6,E6,F6)=0,"",IF(OR(B6="",E6=""),"要入力",IF(F6="","未消込",IF(ISNA(MATCH(F6,請求台帳!$A$5:$A$504,0)),"番号誤り",IF(INDEX(請求台帳!$T$5:$T$504,MATCH(F6,請求台帳!$A$5:$A$504,0))="取消","取消請求へ消込","消込済"))))) -> 消込済 | J6: 佐々木 | K6: SAMPLE: 振込手数料440円差引
A7: =IF(COUNTA(B7,D7,E7,F7)=0,"",ROW()-4) -> 3 | B7: 46295 | C7: ○○銀行 本店 普通 | D7: ド)デモ | E7: 50000 | F7: INV-00004 | G7: =IF(F7="","",IFERROR(INDEX(請求台帳!$D$5:$D$504,MATCH(F7,請求台帳!$A$5:$A$504,0)),"")) -> 合同会社デモ | H7: =IF(F7="","",IFERROR(INDEX(請求台帳!$I$5:$I$504,MATCH(F7,請求台帳!$A$5:$A$504,0)),"")) -> 88000 | I7: =IF(COUNTA(B7,D7,E7,F7)=0,"",IF(OR(B7="",E7=""),"要入力",IF(F7="","未消込",IF(ISNA(MATCH(F7,請求台帳!$A$5:$A$504,0)),"番号誤り",IF(INDEX(請求台帳!$T$5:$T$504,MATCH(F7,請求台帳!$A$5:$A$504,0))="取消","取消請求へ消込","消込済"))))) -> 消込済 | J7: 佐々木 | K7: SAMPLE: 一部入金
A8: =IF(COUNTA(B8,D8,E8,F8)=0,"",ROW()-4) -> 4 | B8: 46293 | C8: △△信用金庫 普通 | D8: ヤマダ タロウ | E8: 5500 | G8: =IF(F8="","",IFERROR(INDEX(請求台帳!$D$5:$D$504,MATCH(F8,請求台帳!$A$5:$A$504,0)),"")) | H8: =IF(F8="","",IFERROR(INDEX(請求台帳!$I$5:$I$504,MATCH(F8,請求台帳!$A$5:$A$504,0)),"")) | I8: =IF(COUNTA(B8,D8,E8,F8)=0,"",IF(OR(B8="",E8=""),"要入力",IF(F8="","未消込",IF(ISNA(MATCH(F8,請求台帳!$A$5:$A$504,0)),"番号誤り",IF(INDEX(請求台帳!$T$5:$T$504,MATCH(F8,請求台帳!$A$5:$A$504,0))="取消","取消請求へ消込","消込済"))))) -> 未消込 | J8: 佐々木 | K8: SAMPLE: 不明入金(未消込)
A9: =IF(COUNTA(B9,D9,E9,F9)=0,"",ROW()-4) | G9: =IF(F9="","",IFERROR(INDEX(請求台帳!$D$5:$D$504,MATCH(F9,請求台帳!$A$5:$A$504,0)),"")) | H9: =IF(F9="","",IFERROR(INDEX(請求台帳!$I$5:$I$504,MATCH(F9,請求台帳!$A$5:$A$504,0)),"")) | I9: =IF(COUNTA(B9,D9,E9,F9)=0,"",IF(OR(B9="",E9=""),"要入力",IF(F9="","未消込",IF(ISNA(MATCH(F9,請求台帳!$A$5:$A$504,0)),"番号誤り",IF(INDEX(請求台帳!$T$5:$T$504,MATCH(F9,請求台帳!$A$5:$A$504,0))="取消","取消請求へ消込","消込済")))))
A10: =IF(COUNTA(B10,D10,E10,F10)=0,"",ROW()-4) | G10: =IF(F10="","",IFERROR(INDEX(請求台帳!$D$5:$D$504,MATCH(F10,請求台帳!$A$5:$A$504,0)),"")) | H10: =IF(F10="","",IFERROR(INDEX(請求台帳!$I$5:$I$504,MATCH(F10,請求台帳!$A$5:$A$504,0)),"")) | I10: =IF(COUNTA(B10,D10,E10,F10)=0,"",IF(OR(B10="",E10=""),"要入力",IF(F10="","未消込",IF(ISNA(MATCH(F10,請求台帳!$A$5:$A$504,0)),"番号誤り",IF(INDEX(請求台帳!$T$5:$T$504,MATCH(F10,請求台帳!$A$5:$A$504,0))="取消","取消請求へ消込","消込済")))))
A11: =IF(COUNTA(B11,D11,E11,F11)=0,"",ROW()-4) | G11: =IF(F11="","",IFERROR(INDEX(請求台帳!$D$5:$D$504,MATCH(F11,請求台帳!$A$5:$A$504,0)),"")) | H11: =IF(F11="","",IFERROR(INDEX(請求台帳!$I$5:$I$504,MATCH(F11,請求台帳!$A$5:$A$504,0)),"")) | I11: =IF(COUNTA(B11,D11,E11,F11)=0,"",IF(OR(B11="",E11=""),"要入力",IF(F11="","未消込",IF(ISNA(MATCH(F11,請求台帳!$A$5:$A$504,0)),"番号誤り",IF(INDEX(請求台帳!$T$5:$T$504,MATCH(F11,請求台帳!$A$5:$A$504,0))="取消","取消請求へ消込","消込済")))))
A12: =IF(COUNTA(B12,D12,E12,F12)=0,"",ROW()-4) | G12: =IF(F12="","",IFERROR(INDEX(請求台帳!$D$5:$D$504,MATCH(F12,請求台帳!$A$5:$A$504,0)),"")) | H12: =IF(F12="","",IFERROR(INDEX(請求台帳!$I$5:$I$504,MATCH(F12,請求台帳!$A$5:$A$504,0)),"")) | I12: =IF(COUNTA(B12,D12,E12,F12)=0,"",IF(OR(B12="",E12=""),"要入力",IF(F12="","未消込",IF(ISNA(MATCH(F12,請求台帳!$A$5:$A$504,0)),"番号誤り",IF(INDEX(請求台帳!$T$5:$T$504,MATCH(F12,請求台帳!$A$5:$A$504,0))="取消","取消請求へ消込","消込済")))))
A13: =IF(COUNTA(B13,D13,E13,F13)=0,"",ROW()-4) | G13: =IF(F13="","",IFERROR(INDEX(請求台帳!$D$5:$D$504,MATCH(F13,請求台帳!$A$5:$A$504,0)),"")) | H13: =IF(F13="","",IFERROR(INDEX(請求台帳!$I$5:$I$504,MATCH(F13,請求台帳!$A$5:$A$504,0)),"")) | I13: =IF(COUNTA(B13,D13,E13,F13)=0,"",IF(OR(B13="",E13=""),"要入力",IF(F13="","未消込",IF(ISNA(MATCH(F13,請求台帳!$A$5:$A$504,0)),"番号誤り",IF(INDEX(請求台帳!$T$5:$T$504,MATCH(F13,請求台帳!$A$5:$A$504,0))="取消","取消請求へ消込","消込済")))))
A14: =IF(COUNTA(B14,D14,E14,F14)=0,"",ROW()-4) | G14: =IF(F14="","",IFERROR(INDEX(請求台帳!$D$5:$D$504,MATCH(F14,請求台帳!$A$5:$A$504,0)),"")) | H14: =IF(F14="","",IFERROR(INDEX(請求台帳!$I$5:$I$504,MATCH(F14,請求台帳!$A$5:$A$504,0)),"")) | I14: =IF(COUNTA(B14,D14,E14,F14)=0,"",IF(OR(B14="",E14=""),"要入力",IF(F14="","未消込",IF(ISNA(MATCH(F14,請求台帳!$A$5:$A$504,0)),"番号誤り",IF(INDEX(請求台帳!$T$5:$T$504,MATCH(F14,請求台帳!$A$5:$A$504,0))="取消","取消請求へ消込","消込済")))))
A15: =IF(COUNTA(B15,D15,E15,F15)=0,"",ROW()-4) | G15: =IF(F15="","",IFERROR(INDEX(請求台帳!$D$5:$D$504,MATCH(F15,請求台帳!$A$5:$A$504,0)),"")) | H15: =IF(F15="","",IFERROR(INDEX(請求台帳!$I$5:$I$504,MATCH(F15,請求台帳!$A$5:$A$504,0)),"")) | I15: =IF(COUNTA(B15,D15,E15,F15)=0,"",IF(OR(B15="",E15=""),"要入力",IF(F15="","未消込",IF(ISNA(MATCH(F15,請求台帳!$A$5:$A$504,0)),"番号誤り",IF(INDEX(請求台帳!$T$5:$T$504,MATCH(F15,請求台帳!$A$5:$A$504,0))="取消","取消請求へ消込","消込済")))))
A16: =IF(COUNTA(B16,D16,E16,F16)=0,"",ROW()-4) | G16: =IF(F16="","",IFERROR(INDEX(請求台帳!$D$5:$D$504,MATCH(F16,請求台帳!$A$5:$A$504,0)),"")) | H16: =IF(F16="","",IFERROR(INDEX(請求台帳!$I$5:$I$504,MATCH(F16,請求台帳!$A$5:$A$504,0)),"")) | I16: =IF(COUNTA(B16,D16,E16,F16)=0,"",IF(OR(B16="",E16=""),"要入力",IF(F16="","未消込",IF(ISNA(MATCH(F16,請求台帳!$A$5:$A$504,0)),"番号誤り",IF(INDEX(請求台帳!$T$5:$T$504,MATCH(F16,請求台帳!$A$5:$A$504,0))="取消","取消請求へ消込","消込済")))))
A17: =IF(COUNTA(B17,D17,E17,F17)=0,"",ROW()-4) | G17: =IF(F17="","",IFERROR(INDEX(請求台帳!$D$5:$D$504,MATCH(F17,請求台帳!$A$5:$A$504,0)),"")) | H17: =IF(F17="","",IFERROR(INDEX(請求台帳!$I$5:$I$504,MATCH(F17,請求台帳!$A$5:$A$504,0)),"")) | I17: =IF(COUNTA(B17,D17,E17,F17)=0,"",IF(OR(B17="",E17=""),"要入力",IF(F17="","未消込",IF(ISNA(MATCH(F17,請求台帳!$A$5:$A$504,0)),"番号誤り",IF(INDEX(請求台帳!$T$5:$T$504,MATCH(F17,請求台帳!$A$5:$A$504,0))="取消","取消請求へ消込","消込済")))))
A18: =IF(COUNTA(B18,D18,E18,F18)=0,"",ROW()-4) | G18: =IF(F18="","",IFERROR(INDEX(請求台帳!$D$5:$D$504,MATCH(F18,請求台帳!$A$5:$A$504,0)),"")) | H18: =IF(F18="","",IFERROR(INDEX(請求台帳!$I$5:$I$504,MATCH(F18,請求台帳!$A$5:$A$504,0)),"")) | I18: =IF(COUNTA(B18,D18,E18,F18)=0,"",IF(OR(B18="",E18=""),"要入力",IF(F18="","未消込",IF(ISNA(MATCH(F18,請求台帳!$A$5:$A$504,0)),"番号誤り",IF(INDEX(請求台帳!$T$5:$T$504,MATCH(F18,請求台帳!$A$5:$A$504,0))="取消","取消請求へ消込","消込済")))))
A19: =IF(COUNTA(B19,D19,E19,F19)=0,"",ROW()-4) | G19: =IF(F19="","",IFERROR(INDEX(請求台帳!$D$5:$D$504,MATCH(F19,請求台帳!$A$5:$A$504,0)),"")) | H19: =IF(F19="","",IFERROR(INDEX(請求台帳!$I$5:$I$504,MATCH(F19,請求台帳!$A$5:$A$504,0)),"")) | I19: =IF(COUNTA(B19,D19,E19,F19)=0,"",IF(OR(B19="",E19=""),"要入力",IF(F19="","未消込",IF(ISNA(MATCH(F19,請求台帳!$A$5:$A$504,0)),"番号誤り",IF(INDEX(請求台帳!$T$5:$T$504,MATCH(F19,請求台帳!$A$5:$A$504,0))="取消","取消請求へ消込","消込済")))))
A20: =IF(COUNTA(B20,D20,E20,F20)=0,"",ROW()-4) | G20: =IF(F20="","",IFERROR(INDEX(請求台帳!$D$5:$D$504,MATCH(F20,請求台帳!$A$5:$A$504,0)),"")) | H20: =IF(F20="","",IFERROR(INDEX(請求台帳!$I$5:$I$504,MATCH(F20,請求台帳!$A$5:$A$504,0)),"")) | I20: =IF(COUNTA(B20,D20,E20,F20)=0,"",IF(OR(B20="",E20=""),"要入力",IF(F20="","未消込",IF(ISNA(MATCH(F20,請求台帳!$A$5:$A$504,0)),"番号誤り",IF(INDEX(請求台帳!$T$5:$T$504,MATCH(F20,請求台帳!$A$5:$A$504,0))="取消","取消請求へ消込","消込済")))))
... A1004: =IF(COUNTA(B1004,D1004,E1004,F1004)=0,"",ROW()-4) | G1004: =IF(F1004="","",IFERROR(INDEX(請求台帳!$D$5:$D$504,MATCH(F1004,請求台帳!$A$5:$A$504,0)),"")) | H1004: =IF(F1004="","",IFERROR(INDEX(請求台帳!$I$5:$I$504,MATCH(F1004,請求台帳!$A$5:$A$504,0)),"")) | I1004: =IF(COUNTA(B1004,D1004,E1004,F1004)=0,"",IF(OR(B1004="",E1004=""),"要入力",IF(F1004="","未消込",IF(ISNA(MATCH(F1004,請求台帳!$A$5:$A$504,0)),"番号誤り",IF(INDEX(請求台帳!$T$5:$T$504,MATCH(F1004,請求台帳!$A$5:$A$504,0))="取消","取消請求へ消込","消込済")))))

Sheet 取引先別残高
A1: 取引先別残高
A2: 取引先マスタの順に自動表示(入力不要)。超過日数別の残高と、毎月請求先の対象月請求漏れ候補を表示します。
C3: 合計 | D3: =D205 -> 349300 | E3: =E205 -> 184300 | F3: =F205 -> 0 | G3: =G205 -> 165000 | H3: =H205 -> 0
A4: 取引先コード | B4: 取引先名 | C4: 営業担当 | D4: 未回収残高 | E4: 期日内 | F4: 超過 1〜30日 | G4: 超過 31〜60日 | H4: 超過 61日以上 | I4: 対象月の請求件数 | J4: 請求漏れ判定
A5: =IF(取引先マスタ!A5="","",取引先マスタ!A5) -> C001 | B5: =IF(A5="","",取引先マスタ!B5) -> 株式会社サンプル商事 | C5: =IF(A5="","",取引先マスタ!J5&"") -> 山田 | D5: =IF(A5="","",SUMIFS(請求台帳!$S$5:$S$504,請求台帳!$C$5:$C$504,A5,請求台帳!$T$5:$T$504,"<>取消")) -> 110000 | E5: =IF(A5="","",D5-SUM(F5:H5)) -> 110000 | F5: =IF(A5="","",SUMIFS(請求台帳!$S$5:$S$504,請求台帳!$C$5:$C$504,A5,請求台帳!$V$5:$V$504,">=1",請求台帳!$V$5:$V$504,"<=30")) -> 0 | G5: =IF(A5="","",SUMIFS(請求台帳!$S$5:$S$504,請求台帳!$C$5:$C$504,A5,請求台帳!$V$5:$V$504,">=31",請求台帳!$V$5:$V$504,"<=60")) -> 0 | H5: =IF(A5="","",SUMIFS(請求台帳!$S$5:$S$504,請求台帳!$C$5:$C$504,A5,請求台帳!$V$5:$V$504,">=61")) -> 0 | I5: =IF(A5="","",COUNTIFS(請求台帳!$C$5:$C$504,A5,請求台帳!$B$5:$B$504,">="&チェック!$C$4,請求台帳!$B$5:$B$504,"<="&EOMONTH(チェック!$C$4,0),請求台帳!$T$5:$T$504,"<>取消")) -> 0 | J5: =IF(A5="","",IF(AND(取引先マスタ!G5="有",I5=0),"請求漏れ候補","")) -> 請求漏れ候補
A6: =IF(取引先マスタ!A6="","",取引先マスタ!A6) -> C002 | B6: =IF(A6="","",取引先マスタ!B6) -> 有限会社テスト工業 | C6: =IF(A6="","",取引先マスタ!J6&"") -> 佐藤 | D6: =IF(A6="","",SUMIFS(請求台帳!$S$5:$S$504,請求台帳!$C$5:$C$504,A6,請求台帳!$T$5:$T$504,"<>取消")) -> 165000 | E6: =IF(A6="","",D6-SUM(F6:H6)) -> 0 | F6: =IF(A6="","",SUMIFS(請求台帳!$S$5:$S$504,請求台帳!$C$5:$C$504,A6,請求台帳!$V$5:$V$504,">=1",請求台帳!$V$5:$V$504,"<=30")) -> 0 | G6: =IF(A6="","",SUMIFS(請求台帳!$S$5:$S$504,請求台帳!$C$5:$C$504,A6,請求台帳!$V$5:$V$504,">=31",請求台帳!$V$5:$V$504,"<=60")) -> 165000 | H6: =IF(A6="","",SUMIFS(請求台帳!$S$5:$S$504,請求台帳!$C$5:$C$504,A6,請求台帳!$V$5:$V$504,">=61")) -> 0 | I6: =IF(A6="","",COUNTIFS(請求台帳!$C$5:$C$504,A6,請求台帳!$B$5:$B$504,">="&チェック!$C$4,請求台帳!$B$5:$B$504,"<="&EOMONTH(チェック!$C$4,0),請求台帳!$T$5:$T$504,"<>取消")) -> 0 | J6: =IF(A6="","",IF(AND(取引先マスタ!G6="有",I6=0),"請求漏れ候補",""))
A7: =IF(取引先マスタ!A7="","",取引先マスタ!A7) -> C003 | B7: =IF(A7="","",取引先マスタ!B7) -> 合同会社デモ | C7: =IF(A7="","",取引先マスタ!J7&"") -> 山田 | D7: =IF(A7="","",SUMIFS(請求台帳!$S$5:$S$504,請求台帳!$C$5:$C$504,A7,請求台帳!$T$5:$T$504,"<>取消")) -> 74300 | E7: =IF(A7="","",D7-SUM(F7:H7)) -> 74300 | F7: =IF(A7="","",SUMIFS(請求台帳!$S$5:$S$504,請求台帳!$C$5:$C$504,A7,請求台帳!$V$5:$V$504,">=1",請求台帳!$V$5:$V$504,"<=30")) -> 0 | G7: =IF(A7="","",SUMIFS(請求台帳!$S$5:$S$504,請求台帳!$C$5:$C$504,A7,請求台帳!$V$5:$V$504,">=31",請求台帳!$V$5:$V$504,"<=60")) -> 0 | H7: =IF(A7="","",SUMIFS(請求台帳!$S$5:$S$504,請求台帳!$C$5:$C$504,A7,請求台帳!$V$5:$V$504,">=61")) -> 0 | I7: =IF(A7="","",COUNTIFS(請求台帳!$C$5:$C$504,A7,請求台帳!$B$5:$B$504,">="&チェック!$C$4,請求台帳!$B$5:$B$504,"<="&EOMONTH(チェック!$C$4,0),請求台帳!$T$5:$T$504,"<>取消")) -> 1 | J7: =IF(A7="","",IF(AND(取引先マスタ!G7="有",I7=0),"請求漏れ候補",""))
A8: =IF(取引先マスタ!A8="","",取引先マスタ!A8) | B8: =IF(A8="","",取引先マスタ!B8) | C8: =IF(A8="","",取引先マスタ!J8&"") | D8: =IF(A8="","",SUMIFS(請求台帳!$S$5:$S$504,請求台帳!$C$5:$C$504,A8,請求台帳!$T$5:$T$504,"<>取消")) | E8: =IF(A8="","",D8-SUM(F8:H8)) | F8: =IF(A8="","",SUMIFS(請求台帳!$S$5:$S$504,請求台帳!$C$5:$C$504,A8,請求台帳!$V$5:$V$504,">=1",請求台帳!$V$5:$V$504,"<=30")) | G8: =IF(A8="","",SUMIFS(請求台帳!$S$5:$S$504,請求台帳!$C$5:$C$504,A8,請求台帳!$V$5:$V$504,">=31",請求台帳!$V$5:$V$504,"<=60")) | H8: =IF(A8="","",SUMIFS(請求台帳!$S$5:$S$504,請求台帳!$C$5:$C$504,A8,請求台帳!$V$5:$V$504,">=61")) | I8: =IF(A8="","",COUNTIFS(請求台帳!$C$5:$C$504,A8,請求台帳!$B$5:$B$504,">="&チェック!$C$4,請求台帳!$B$5:$B$504,"<="&EOMONTH(チェック!$C$4,0),請求台帳!$T$5:$T$504,"<>取消")) | J8: =IF(A8="","",IF(AND(取引先マスタ!G8="有",I8=0),"請求漏れ候補",""))
A9: =IF(取引先マスタ!A9="","",取引先マスタ!A9) | B9: =IF(A9="","",取引先マスタ!B9) | C9: =IF(A9="","",取引先マスタ!J9&"") | D9: =IF(A9="","",SUMIFS(請求台帳!$S$5:$S$504,請求台帳!$C$5:$C$504,A9,請求台帳!$T$5:$T$504,"<>取消")) | E9: =IF(A9="","",D9-SUM(F9:H9)) | F9: =IF(A9="","",SUMIFS(請求台帳!$S$5:$S$504,請求台帳!$C$5:$C$504,A9,請求台帳!$V$5:$V$504,">=1",請求台帳!$V$5:$V$504,"<=30")) | G9: =IF(A9="","",SUMIFS(請求台帳!$S$5:$S$504,請求台帳!$C$5:$C$504,A9,請求台帳!$V$5:$V$504,">=31",請求台帳!$V$5:$V$504,"<=60")) | H9: =IF(A9="","",SUMIFS(請求台帳!$S$5:$S$504,請求台帳!$C$5:$C$504,A9,請求台帳!$V$5:$V$504,">=61")) | I9: =IF(A9="","",COUNTIFS(請求台帳!$C$5:$C$504,A9,請求台帳!$B$5:$B$504,">="&チェック!$C$4,請求台帳!$B$5:$B$504,"<="&EOMONTH(チェック!$C$4,0),請求台帳!$T$5:$T$504,"<>取消")) | J9: =IF(A9="","",IF(AND(取引先マスタ!G9="有",I9=0),"請求漏れ候補",""))
A10: =IF(取引先マスタ!A10="","",取引先マスタ!A10) | B10: =IF(A10="","",取引先マスタ!B10) | C10: =IF(A10="","",取引先マスタ!J10&"") | D10: =IF(A10="","",SUMIFS(請求台帳!$S$5:$S$504,請求台帳!$C$5:$C$504,A10,請求台帳!$T$5:$T$504,"<>取消")) | E10: =IF(A10="","",D10-SUM(F10:H10)) | F10: =IF(A10="","",SUMIFS(請求台帳!$S$5:$S$504,請求台帳!$C$5:$C$504,A10,請求台帳!$V$5:$V$504,">=1",請求台帳!$V$5:$V$504,"<=30")) | G10: =IF(A10="","",SUMIFS(請求台帳!$S$5:$S$504,請求台帳!$C$5:$C$504,A10,請求台帳!$V$5:$V$504,">=31",請求台帳!$V$5:$V$504,"<=60")) | H10: =IF(A10="","",SUMIFS(請求台帳!$S$5:$S$504,請求台帳!$C$5:$C$504,A10,請求台帳!$V$5:$V$504,">=61")) | I10: =IF(A10="","",COUNTIFS(請求台帳!$C$5:$C$504,A10,請求台帳!$B$5:$B$504,">="&チェック!$C$4,請求台帳!$B$5:$B$504,"<="&EOMONTH(チェック!$C$4,0),請求台帳!$T$5:$T$504,"<>取消")) | J10: =IF(A10="","",IF(AND(取引先マスタ!G10="有",I10=0),"請求漏れ候補",""))
A11: =IF(取引先マスタ!A11="","",取引先マスタ!A11) | B11: =IF(A11="","",取引先マスタ!B11) | C11: =IF(A11="","",取引先マスタ!J11&"") | D11: =IF(A11="","",SUMIFS(請求台帳!$S$5:$S$504,請求台帳!$C$5:$C$504,A11,請求台帳!$T$5:$T$504,"<>取消")) | E11: =IF(A11="","",D11-SUM(F11:H11)) | F11: =IF(A11="","",SUMIFS(請求台帳!$S$5:$S$504,請求台帳!$C$5:$C$504,A11,請求台帳!$V$5:$V$504,">=1",請求台帳!$V$5:$V$504,"<=30")) | G11: =IF(A11="","",SUMIFS(請求台帳!$S$5:$S$504,請求台帳!$C$5:$C$504,A11,請求台帳!$V$5:$V$504,">=31",請求台帳!$V$5:$V$504,"<=60")) | H11: =IF(A11="","",SUMIFS(請求台帳!$S$5:$S$504,請求台帳!$C$5:$C$504,A11,請求台帳!$V$5:$V$504,">=61")) | I11: =IF(A11="","",COUNTIFS(請求台帳!$C$5:$C$504,A11,請求台帳!$B$5:$B$504,">="&チェック!$C$4,請求台帳!$B$5:$B$504,"<="&EOMONTH(チェック!$C$4,0),請求台帳!$T$5:$T$504,"<>取消")) | J11: =IF(A11="","",IF(AND(取引先マスタ!G11="有",I11=0),"請求漏れ候補",""))
A12: =IF(取引先マスタ!A12="","",取引先マスタ!A12) | B12: =IF(A12="","",取引先マスタ!B12) | C12: =IF(A12="","",取引先マスタ!J12&"") | D12: =IF(A12="","",SUMIFS(請求台帳!$S$5:$S$504,請求台帳!$C$5:$C$504,A12,請求台帳!$T$5:$T$504,"<>取消")) | E12: =IF(A12="","",D12-SUM(F12:H12)) | F12: =IF(A12="","",SUMIFS(請求台帳!$S$5:$S$504,請求台帳!$C$5:$C$504,A12,請求台帳!$V$5:$V$504,">=1",請求台帳!$V$5:$V$504,"<=30")) | G12: =IF(A12="","",SUMIFS(請求台帳!$S$5:$S$504,請求台帳!$C$5:$C$504,A12,請求台帳!$V$5:$V$504,">=31",請求台帳!$V$5:$V$504,"<=60")) | H12: =IF(A12="","",SUMIFS(請求台帳!$S$5:$S$504,請求台帳!$C$5:$C$504,A12,請求台帳!$V$5:$V$504,">=61")) | I12: =IF(A12="","",COUNTIFS(請求台帳!$C$5:$C$504,A12,請求台帳!$B$5:$B$504,">="&チェック!$C$4,請求台帳!$B$5:$B$504,"<="&EOMONTH(チェック!$C$4,0),請求台帳!$T$5:$T$504,"<>取消")) | J12: =IF(A12="","",IF(AND(取引先マスタ!G12="有",I12=0),"請求漏れ候補",""))
A13: =IF(取引先マスタ!A13="","",取引先マスタ!A13) | B13: =IF(A13="","",取引先マスタ!B13) | C13: =IF(A13="","",取引先マスタ!J13&"") | D13: =IF(A13="","",SUMIFS(請求台帳!$S$5:$S$504,請求台帳!$C$5:$C$504,A13,請求台帳!$T$5:$T$504,"<>取消")) | E13: =IF(A13="","",D13-SUM(F13:H13)) | F13: =IF(A13="","",SUMIFS(請求台帳!$S$5:$S$504,請求台帳!$C$5:$C$504,A13,請求台帳!$V$5:$V$504,">=1",請求台帳!$V$5:$V$504,"<=30")) | G13: =IF(A13="","",SUMIFS(請求台帳!$S$5:$S$504,請求台帳!$C$5:$C$504,A13,請求台帳!$V$5:$V$504,">=31",請求台帳!$V$5:$V$504,"<=60")) | H13: =IF(A13="","",SUMIFS(請求台帳!$S$5:$S$504,請求台帳!$C$5:$C$504,A13,請求台帳!$V$5:$V$504,">=61")) | I13: =IF(A13="","",COUNTIFS(請求台帳!$C$5:$C$504,A13,請求台帳!$B$5:$B$504,">="&チェック!$C$4,請求台帳!$B$5:$B$504,"<="&EOMONTH(チェック!$C$4,0),請求台帳!$T$5:$T$504,"<>取消")) | J13: =IF(A13="","",IF(AND(取引先マスタ!G13="有",I13=0),"請求漏れ候補",""))
A14: =IF(取引先マスタ!A14="","",取引先マスタ!A14) | B14: =IF(A14="","",取引先マスタ!B14) | C14: =IF(A14="","",取引先マスタ!J14&"") | D14: =IF(A14="","",SUMIFS(請求台帳!$S$5:$S$504,請求台帳!$C$5:$C$504,A14,請求台帳!$T$5:$T$504,"<>取消")) | E14: =IF(A14="","",D14-SUM(F14:H14)) | F14: =IF(A14="","",SUMIFS(請求台帳!$S$5:$S$504,請求台帳!$C$5:$C$504,A14,請求台帳!$V$5:$V$504,">=1",請求台帳!$V$5:$V$504,"<=30")) | G14: =IF(A14="","",SUMIFS(請求台帳!$S$5:$S$504,請求台帳!$C$5:$C$504,A14,請求台帳!$V$5:$V$504,">=31",請求台帳!$V$5:$V$504,"<=60")) | H14: =IF(A14="","",SUMIFS(請求台帳!$S$5:$S$504,請求台帳!$C$5:$C$504,A14,請求台帳!$V$5:$V$504,">=61")) | I14: =IF(A14="","",COUNTIFS(請求台帳!$C$5:$C$504,A14,請求台帳!$B$5:$B$504,">="&チェック!$C$4,請求台帳!$B$5:$B$504,"<="&EOMONTH(チェック!$C$4,0),請求台帳!$T$5:$T$504,"<>取消")) | J14: =IF(A14="","",IF(AND(取引先マスタ!G14="有",I14=0),"請求漏れ候補",""))
A15: =IF(取引先マスタ!A15="","",取引先マスタ!A15) | B15: =IF(A15="","",取引先マスタ!B15) | C15: =IF(A15="","",取引先マスタ!J15&"") | D15: =IF(A15="","",SUMIFS(請求台帳!$S$5:$S$504,請求台帳!$C$5:$C$504,A15,請求台帳!$T$5:$T$504,"<>取消")) | E15: =IF(A15="","",D15-SUM(F15:H15)) | F15: =IF(A15="","",SUMIFS(請求台帳!$S$5:$S$504,請求台帳!$C$5:$C$504,A15,請求台帳!$V$5:$V$504,">=1",請求台帳!$V$5:$V$504,"<=30")) | G15: =IF(A15="","",SUMIFS(請求台帳!$S$5:$S$504,請求台帳!$C$5:$C$504,A15,請求台帳!$V$5:$V$504,">=31",請求台帳!$V$5:$V$504,"<=60")) | H15: =IF(A15="","",SUMIFS(請求台帳!$S$5:$S$504,請求台帳!$C$5:$C$504,A15,請求台帳!$V$5:$V$504,">=61")) | I15: =IF(A15="","",COUNTIFS(請求台帳!$C$5:$C$504,A15,請求台帳!$B$5:$B$504,">="&チェック!$C$4,請求台帳!$B$5:$B$504,"<="&EOMONTH(チェック!$C$4,0),請求台帳!$T$5:$T$504,"<>取消")) | J15: =IF(A15="","",IF(AND(取引先マスタ!G15="有",I15=0),"請求漏れ候補",""))
A16: =IF(取引先マスタ!A16="","",取引先マスタ!A16) | B16: =IF(A16="","",取引先マスタ!B16) | C16: =IF(A16="","",取引先マスタ!J16&"") | D16: =IF(A16="","",SUMIFS(請求台帳!$S$5:$S$504,請求台帳!$C$5:$C$504,A16,請求台帳!$T$5:$T$504,"<>取消")) | E16: =IF(A16="","",D16-SUM(F16:H16)) | F16: =IF(A16="","",SUMIFS(請求台帳!$S$5:$S$504,請求台帳!$C$5:$C$504,A16,請求台帳!$V$5:$V$504,">=1",請求台帳!$V$5:$V$504,"<=30")) | G16: =IF(A16="","",SUMIFS(請求台帳!$S$5:$S$504,請求台帳!$C$5:$C$504,A16,請求台帳!$V$5:$V$504,">=31",請求台帳!$V$5:$V$504,"<=60")) | H16: =IF(A16="","",SUMIFS(請求台帳!$S$5:$S$504,請求台帳!$C$5:$C$504,A16,請求台帳!$V$5:$V$504,">=61")) | I16: =IF(A16="","",COUNTIFS(請求台帳!$C$5:$C$504,A16,請求台帳!$B$5:$B$504,">="&チェック!$C$4,請求台帳!$B$5:$B$504,"<="&EOMONTH(チェック!$C$4,0),請求台帳!$T$5:$T$504,"<>取消")) | J16: =IF(A16="","",IF(AND(取引先マスタ!G16="有",I16=0),"請求漏れ候補",""))
... A204: =IF(取引先マスタ!A204="","",取引先マスタ!A204) | B204: =IF(A204="","",取引先マスタ!B204) | C204: =IF(A204="","",取引先マスタ!J204&"") | D204: =IF(A204="","",SUMIFS(請求台帳!$S$5:$S$504,請求台帳!$C$5:$C$504,A204,請求台帳!$T$5:$T$504,"<>取消")) | E204: =IF(A204="","",D204-SUM(F204:H204)) | F204: =IF(A204="","",SUMIFS(請求台帳!$S$5:$S$504,請求台帳!$C$5:$C$504,A204,請求台帳!$V$5:$V$504,">=1",請求台帳!$V$5:$V$504,"<=30")) | G204: =IF(A204="","",SUMIFS(請求台帳!$S$5:$S$504,請求台帳!$C$5:$C$504,A204,請求台帳!$V$5:$V$504,">=31",請求台帳!$V$5:$V$504,"<=60")) | H204: =IF(A204="","",SUMIFS(請求台帳!$S$5:$S$504,請求台帳!$C$5:$C$504,A204,請求台帳!$V$5:$V$504,">=61")) | I204: =IF(A204="","",COUNTIFS(請求台帳!$C$5:$C$504,A204,請求台帳!$B$5:$B$504,">="&チェック!$C$4,請求台帳!$B$5:$B$504,"<="&EOMONTH(チェック!$C$4,0),請求台帳!$T$5:$T$504,"<>取消")) | J204: =IF(A204="","",IF(AND(取引先マスタ!G204="有",I204=0),"請求漏れ候補",""))
B205: 合計 | D205: =SUM(D5:D204) -> 349300 | E205: =SUM(E5:E204) -> 184300 | F205: =SUM(F5:F204) -> 0 | G205: =SUM(G5:G204) -> 165000 | H205: =SUM(H5:H204) -> 0

Sheet 取引先マスタ
A1: 取引先マスタ
A2: 取引先ごとの支払条件を登録します。請求台帳の入金期日は「支払サイト」「支払日」から自動計算されます。
A4: 取引先コード | B4: 取引先名 | C4: 振込名義(カナ) | D4: 締日(参考) | E4: 支払サイト(月) | F4: 支払日 | G4: 毎月請求 | H4: 既定の送付方法 | I4: 送付先(メール/住所) | J4: 営業担当 | K4: 備考 | L4: 重複チェック
A5: C001 | B5: 株式会社サンプル商事 | C5: カ)サンプルシヨウジ | D5: 末日 | E5: 1 | F5: 31 | G5: 有 | H5: メール(PDF) | I5: keiri@sample.example | J5: 山田 | K5: サンプル(運用前に削除) | L5: =IF(A5="","",IF(COUNTIF($A$5:$A$204,A5)>1,"コード重複",""))
A6: C002 | B6: 有限会社テスト工業 | C6: ユ)テストコウギヨウ | D6: 末日 | E6: 2 | F6: 10 | G6: 無 | H6: 郵送 | I6: 東京都○○区… | J6: 佐藤 | K6: サンプル(運用前に削除) | L6: =IF(A6="","",IF(COUNTIF($A$5:$A$204,A6)>1,"コード重複",""))
A7: C003 | B7: 合同会社デモ | C7: ド)デモ | D7: 20日 | E7: 1 | F7: 31 | G7: 有 | H7: 請求書発行システム | J7: 山田 | K7: サンプル(運用前に削除) | L7: =IF(A7="","",IF(COUNTIF($A$5:$A$204,A7)>1,"コード重複",""))
L8: =IF(A8="","",IF(COUNTIF($A$5:$A$204,A8)>1,"コード重複",""))
L9: =IF(A9="","",IF(COUNTIF($A$5:$A$204,A9)>1,"コード重複",""))
L10: =IF(A10="","",IF(COUNTIF($A$5:$A$204,A10)>1,"コード重複",""))
L11: =IF(A11="","",IF(COUNTIF($A$5:$A$204,A11)>1,"コード重複",""))
L12: =IF(A12="","",IF(COUNTIF($A$5:$A$204,A12)>1,"コード重複",""))
L13: =IF(A13="","",IF(COUNTIF($A$5:$A$204,A13)>1,"コード重複",""))
L14: =IF(A14="","",IF(COUNTIF($A$5:$A$204,A14)>1,"コード重複",""))
L15: =IF(A15="","",IF(COUNTIF($A$5:$A$204,A15)>1,"コード重複",""))
L16: =IF(A16="","",IF(COUNTIF($A$5:$A$204,A16)>1,"コード重複",""))
L17: =IF(A17="","",IF(COUNTIF($A$5:$A$204,A17)>1,"コード重複",""))
L18: =IF(A18="","",IF(COUNTIF($A$5:$A$204,A18)>1,"コード重複",""))
L19: =IF(A19="","",IF(COUNTIF($A$5:$A$204,A19)>1,"コード重複",""))
... L204: =IF(A204="","",IF(COUNTIF($A$5:$A$204,A204)>1,"コード重複",""))

Sheet 月次チェック記録
A1: 月次チェック記録
A2: 毎月、締め後(例: 翌月5営業日以内)に実施。各項目を確認したら「済」を選択し、実施者・承認者を記入します。
A4: 対象月 | B4: ①請求漏れ突合 (受注・納品一覧と台帳) | C4: ②未送付 0件 | D4: ③要入力 0件 | E4: ④未消込入金 0件 (番号誤り含む) | F4: ⑤期日超過の督促・ 状況確認 | G4: ⑥会計ソフト残高 との照合(差額0) | H4: ⑦毎月請求先の 請求漏れ候補 0件 | I4: 実施者 | J4: 実施日 | K4: 承認者(責任者) | L4: 承認日 | M4: 期日超過の件数・金額 / 特記事項 | N4: ※ 過去月で承認日が空欄の行はオレンジ表示
A5: 46266
A6: 46296
A7: 46327
A8: 46357
A9: 46388
A10: 46419
A11: 46447
A12: 46478
A13: 46508
A14: 46539
A15: 46569
A16: 46600
... A40: 47331

Sheet 設定
A1: 設定
A2: 黄色のセルを必要に応じて変更してください。プルダウンの選択肢は各リストに追記できます。 | F2: ▼ プルダウンの選択肢(空欄に追記すると選択肢に増えます)
B4: 請求番号の接頭辞 | C4: INV- | D4: 請求番号 = 接頭辞 + 5桁の連番(例: INV-00001) | F4: 税率 | G4: 送付方法 | H4: 入金口座 | I4: 取消 | J4: 有無 | K4: 実施
B5: 基準日 | C5: =TODAY() -> 46294 | D5: 通常は =TODAY() のまま。過去時点で確認したい場合のみ日付を直接入力 | F5: 0.1 | G5: メール(PDF) | H5: ○○銀行 本店 普通 | I5: 取消 | J5: 有 | K5: 済
B6: 期日間近とする日数 | C6: 7 | D6: 入金期日まで何日以内を「期日間近」とするか | F6: 0.08 | G6: 郵送 | H6: △△信用金庫 普通 | J6: 無 | K6: 該当なし
F7: 0 | G7: 請求書発行システム
G8: 手渡し
G9: その他
